Workbook

Sheet FINAL
A1: KEY | B1: T_date | C1: P_date | D1: T_details | E1: T_amount | F1: Cal_ind | G1: T_amount_abs | H1: Card_type | I1: T_type | J1: T_agency | K1: Fin_Type | L1: CC_Bill_Status | M1: EMI_Ind | N1: B_Month | O1: Remark
A2: =B2&C2&G2&H2&I2&J2 -> 437034370350CURRENTWITHDRAWSELF | B2: 43703 | C2: =B2 -> 43703 | D2: ATM CASH WITHDRAWAL,923816758781,4612 758781,COMM. BANK OF QATAR DOHA,4342041934720023 26/08 19.07 | E2: -50 | F2: 1 | G2: =ABS(E2)*F2 -> 50 | H2: CURRENT | I2: WITHDRAW | J2: SELF | K2: DEBIT | L2: NA | N2: =MONTH(C2) -> 8
A3: =B3&C3&G3&H3&I3&J3 -> 437034370310CURRENTSERVICEBANK | B3: 43703 | C3: =B3 -> 43703 | D3: SELF CHEQUE BOOK FEE,637024429596 | E3: -10 | F3: 1 | G3: =ABS(E3)*F3 -> 10 | H3: CURRENT | I3: SERVICE | J3: BANK | K3: DEBIT | L3: NA | N3: =MONTH(C3) -> 8
A4: =B4&C4&G4&H4&I4&J4 -> 437034370350CURRENTLOANFRIEND | B4: 43703 | C4: =B4 -> 43703 | D4: TRANSFER - CREDIT,260819113085,Transfer From 4010-512145-001,AKSHIT WALIA | E4: 50 | F4: 1 | G4: =ABS(E4)*F4 -> 50 | H4: CURRENT | I4: LOAN | J4: FRIEND | K4: CREDIT | L4: NA | N4: =MONTH(C4) -> 8
A5: =B5&C5&G5&H5&I5&J5 -> 437034370350CURRENTLOANFRIEND | B5: 43703 | C5: =B5 -> 43703 | D5: TRANSFER - CREDIT,260819113069,Transfer From 4010-512145-001,AKSHIT WALIA | E5: 50 | F5: 1 | G5: =ABS(E5)*F5 -> 50 | H5: CURRENT | I5: LOAN | J5: FRIEND | K5: CREDIT | L5: NA | N5: =MONTH(C5) -> 8
A6: =B6&C6&G6&H6&I6&J6 -> 437034370328CURRENTFOODCAFÉ/REST. | B6: 43703 | C6: =B6 -> 43703 | D6: NAPS PURCHASE,000001049025,4018 016772 72240402,HAREESONA DOHA,4342041934720023 26/08 19.30,63409000000 | E6: -28 | F6: 1 | G6: =ABS(E6)*F6 -> 28 | H6: CURRENT | I6: FOOD | J6: CAFÉ/REST. | K6: DEBIT | L6: NA | N6: =MONTH(C6) -> 8
A7: =B7&C7&G7&H7&I7&J7 -> 4370443704500CURRENTWITHDRAWSELF | B7: 43704 | C7: =B7 -> 43704 | D7: NAPS ATM,923907875302,4018 011576 IQ000136,IBQ QATAR AIRWAYS DOHA,4342041934720023 27/08 10.49,63402000000 | E7: -500 | F7: 1 | G7: =ABS(E7)*F7 -> 500 | H7: CURRENT | I7: WITHDRAW | J7: SELF | K7: DEBIT | L7: NA | N7: =MONTH(C7) -> 8
A8: =B8&C8&G8&H8&I8&J8 -> 43704437042559CURRENTTRANSFERINDIA | B8: 43704 | C8: =B8 -> 43704 | D8: TELEX TRANSFER,270819013421,family,Vineet Kumar Saraswat | E8: -2559 | F8: 1 | G8: =ABS(E8)*F8 -> 2559 | H8: CURRENT | I8: TRANSFER | J8: INDIA | K8: DEBIT | L8: NA | N8: =MONTH(C8) -> 8
A9: =B9&C9&G9&H9&I9&J9 -> 437044370415CURRENTSERVICEBANK | B9: 43704 | C9: =B9 -> 43704 | D9: TELEX CHARGE,270819013421,Telex Transfer Charges | E9: -15 | F9: 1 | G9: =ABS(E9)*F9 -> 15 | H9: CURRENT | I9: SERVICE | J9: BANK | K9: DEBIT | L9: NA | N9: =MONTH(C9) -> 8
A10: =B10&C10&G10&H10&I10&J10 -> 437044370418244CURRENTSALARYQATAR AIR | B10: 43704 | C10: =B10 -> 43704 | D10: SALARY TRANSFER,CDD 90827H005601,QCH4487250990000 QAR,QATAR AIRWAYS,2/SALA | E10: 12929 | F10: 1 | G10: 18244 | H10: CURRENT | I10: SALARY | J10: QATAR AIR | K10: CREDIT | L10: NA | N10: =MONTH(C10) -> 8
A11: =B11&C11&G11&H11&I11&J11 -> 43704437045315CURRENTRENTQATAR AIR | B11: 43704 | C11: =B11 -> 43704 | D11: COMPANY ACCOMODATION ALLOWANCES | E11: 5315 | F11: 1 | G11: =ABS(E11)*F11 -> 5315 | H11: CURRENT | I11: RENT | J11: QATAR AIR | K11: DEBIT | L11: NA | N11: =MONTH(C11) -> 8
A12: =B12&C12&G12&H12&I12&J12 -> 43704437092000CURRENTRENTCAP ONE | B12: 43704 | C12: 43709 | D12: NAPS ATM,923907875302,4018 011576 IQ000136,IBQ QATAR AIRWAYS DOHA,4342041934720023 27/08 10.49,63402000000-KARAH MAA ADVANCE TO CAP ONE | E12: -2000 | F12: 1 | G12: 2000 | H12: CURRENT | I12: RENT | J12: CAP ONE | K12: DEBIT | L12: NA | N12: =MONTH(C12) -> 9
A13: =B13&C13&G13&H13&I13&J13 -> 43704437094500CURRENTRENTCAP ONE | B13: 43704 | C13: 43709 | D13: NAPS ATM,923907875302,4018 011576 IQ000136,IBQ QATAR AIRWAYS DOHA,4342041934720023 27/08 10.49,63402000000-RENT SECURITY TO CAP ONE | E13: -4500 | F13: 1 | G13: 4500 | H13: CURRENT | I13: RENT | J13: CAP ONE | K13: DEBIT | L13: NA | N13: =MONTH(C13) -> 9
A14: =B14&C14&G14&H14&I14&J14 -> 43704437041092CURRENTLOANFRIEND | B14: 43704 | C14: =B14 -> 43704 | D14: TRANSFER - DEBIT,270819110844,helping amount,Akshit Walia | E14: -1092 | F14: 1 | G14: =ABS(E14)*F14 -> 1092 | H14: CURRENT | I14: LOAN | J14: FRIEND | K14: DEBIT | L14: NA | N14: =MONTH(C14) -> 8
A15: =B15&C15&G15&H15&I15&J15 -> 437054370515CURRENTSERVICEBANK | B15: 43705 | C15: =B15 -> 43705 | D15: COMMISSION/FEE,4700-193472-001,Re-Issuance of new cheque book-RIB | E15: -15 | F15: 1 | G15: =ABS(E15)*F15 -> 15 | H15: CURRENT | I15: SERVICE | J15: BANK | K15: DEBIT | L15: NA | N15: =MONTH(C15) -> 8
A16: =B16&C16&G16&H16&I16&J16 -> 437094370915CURRENTSERVICEBANK | B16: 43709 | C16: =B16 -> 43709 | D16: CREDIT,270819013421,BAW-TT Charge Refund | E16: 15 | F16: 1 | G16: =ABS(E16)*F16 -> 15 | H16: CURRENT | I16: SERVICE | J16: BANK | K16: CREDIT | L16: NA | N16: =MONTH(C16) -> 9
A17: =B17&C17&G17&H17&I17&J17 -> 437094370925CURRENTFOODQATAR AIR | B17: 43709 | C17: =B17 -> 43709 | D17: NAPS PURCHASE,000001048059,4018 007412 82491201,THE COFFEE SHOP QR TOWDOHA,4342041934720023 01/09 11.47,63409000000 | E17: -25 | F17: 1 | G17: =ABS(E17)*F17 -> 25 | H17: CURRENT | I17: FOOD | J17: QATAR AIR | K17: DEBIT | L17: NA | N17: =MONTH(C17) -> 9
A18: =B18&C18&G18&H18&I18&J18 -> 4371343718500MASTER CCVISAMINISTERY | B18: 43713 | C18: 43718 | D18: MINISTER OF FOREIGN AF DOHA QAT AUTH NO. 047645 | E18: 500 | F18: 1 | G18: =ABS(E18)*F18 -> 500 | H18: MASTER CC | I18: VISA | J18: MINISTERY | K18: DEBIT | L18: BILLED | N18: =MONTH(C18) -> 9
A19: =B19&C19&G19&H19&I19&J19 -> 43713437158MASTER CCTRANSPORTCAREEM | B19: 43713 | C19: 43715 | D19: CAREEM NETWORKS FZ LLC DUBAI ARE AUTH NO. 091262 | E19: 8 | F19: 1 | G19: =ABS(E19)*F19 -> 8 | H19: MASTER CC | I19: TRANSPORT | J19: CAREEM | K19: DEBIT | L19: BILLED | N19: =MONTH(C19) -> 9
A20: =B20&C20&G20&H20&I20&J20 -> 43714437168MASTER CCTRANSPORTCAREEM | B20: 43714 | C20: 43716 | D20: CAREEM NETWORKS FZ LLC DUBAI ARE AUTH NO. 071417 | E20: 8 | F20: 1 | G20: =ABS(E20)*F20 -> 8 | H20: MASTER CC | I20: TRANSPORT | J20: CAREEM | K20: DEBIT | L20: BILLED | N20: =MONTH(C20) -> 9
A21: =B21&C21&G21&H21&I21&J21 -> 437144371834MASTER CCFOODCAFÉ/REST. | B21: 43714 | C21: 43718 | D21: CAFE TASSE -SOUQ WAQEF DOHA QAT AUTH NO. 024771 | E21: 34 | F21: 1 | G21: =ABS(E21)*F21 -> 34 | H21: MASTER CC | I21: FOOD | J21: CAFÉ/REST. | K21: DEBIT | L21: BILLED | N21: =MONTH(C21) -> 9
A22: =B22&C22&G22&H22&I22&J22 -> 437154371835MASTER CCTRANSPORTCAREEM | B22: 43715 | C22: 43718 | D22: CAREEM NETWORKS FZ LLC DUBAI ARE AUTH NO. 052270 | E22: 35 | F22: 1 | G22: =ABS(E22)*F22 -> 35 | H22: MASTER CC | I22: TRANSPORT | J22: CAREEM | K22: DEBIT | L22: BILLED | N22: =MONTH(C22) -> 9
A23: =B23&C23&G23&H23&I23&J23 -> 437184372015MASTER CCFOODQATAR AIR | B23: 43718 | C23: 43720 | D23: THE COFFEE SHOP QR TOW DOHA QAT AUTH NO. 098436 | E23: 15 | F23: 1 | G23: =ABS(E23)*F23 -> 15 | H23: MASTER CC | I23: FOOD | J23: QATAR AIR | K23: DEBIT | L23: BILLED | N23: =MONTH(C23) -> 9
A24: =B24&C24&G24&H24&I24&J24 -> 437184372035MASTER CCFOODQATAR AIR | B24: 43718 | C24: 43720 | D24: QATAR AIR DOHA QAT AUTH NO. 018563 | E24: 35 | F24: 1 | G24: =ABS(E24)*F24 -> 35 | H24: MASTER CC | I24: FOOD | J24: QATAR AIR | K24: DEBIT | L24: BILLED | N24: =MONTH(C24) -> 9
A25: =B25&C25&G25&H25&I25&J25 -> 437194372112MASTER CCFOODQATAR AIR | B25: 43719 | C25: 43721 | D25: THE COFFEE SHOP QR TOW DOHA QAT AUTH NO. 058426 | E25: 12 | F25: 1 | G25: =ABS(E25)*F25 -> 12 | H25: MASTER CC | I25: FOOD | J25: QATAR AIR | K25: DEBIT | L25: BILLED | N25: =MONTH(C25) -> 9
A26: =B26&C26&G26&H26&I26&J26 -> 4372043720500CURRENTWITHDRAWSELF | B26: 43720 | C26: =B26 -> 43720 | D26: NAPS ATM,925505987099,4018 013997 IQ000148,QATAR AIRWAYS BRANCH 2DOHA,4342041934720023 12/09 08.48,63402000000 | E26: -500 | F26: 1 | G26: =ABS(E26)*F26 -> 500 | H26: CURRENT | I26: WITHDRAW | J26: SELF | K26: DEBIT | L26: NA | N26: =MONTH(C26) -> 9
A27: =B27&C27&G27&H27&I27&J27 -> 437204372511MASTER CCFOODQATAR AIR | B27: 43720 | C27: 43725 | D27: THE COFFEE SHOP QR TOW DOHA QAT AUTH NO. 089552 | E27: 11 | F27: 1 | G27: =ABS(E27)*F27 -> 11 | H27: MASTER CC | I27: FOOD | J27: QATAR AIR | K27: DEBIT | L27: BILLED | N27: =MONTH(C27) -> 9
A28: =B28&C28&G28&H28&I28&J28 -> 437204372512MASTER CCFOODQATAR AIR | B28: 43720 | C28: 43725 | D28: THE COFFEE SHOP QR TOW DOHA QAT AUTH NO. 024301 | E28: 12 | F28: 1 | G28: =ABS(E28)*F28 -> 12 | H28: MASTER CC | I28: FOOD | J28: QATAR AIR | K28: DEBIT | L28: BILLED | N28: =MONTH(C28) -> 9
A29: =B29&C29&G29&H29&I29&J29 -> 437204372535MASTER CCFOODQATAR AIR | B29: 43720 | C29: 43725 | D29: QATAR AIR DOHA QAT AUTH NO. 005171 | E29: 35 | F29: 1 | G29: =ABS(E29)*F29 -> 35 | H29: MASTER CC | I29: FOOD | J29: QATAR AIR | K29: DEBIT | L29: BILLED | N29: =MONTH(C29) -> 9
A30: =B30&C30&G30&H30&I30&J30 -> 43720437222MASTER CCTRANSPORTCAREEM | B30: 43720 | C30: 43722 | D30: CAREEM NETWORKS FZ LLC DUBAI ARE AUTH NO. 036073 | E30: 2 | F30: 1 | G30: =ABS(E30)*F30 -> 2 | H30: MASTER CC | I30: TRANSPORT | J30: CAREEM | K30: DEBIT | L30: BILLED | N30: =MONTH(C30) -> 9
A31: =B31&C31&G31&H31&I31&J31 -> 437214372254.7DINERSGROCERYLULU | B31: 43721 | C31: 43722 | D31: LULU EXPRESS TRADING COMP DOHA 634 AUTH NO. 028120 | E31: 54.7 | F31: 1 | G31: =ABS(E31)*F31 -> 54.7 | H31: DINERS | I31: GROCERY | J31: LULU | K31: DEBIT | L31: BILLED | N31: =MONTH(C31) -> 9
A32: =B32&C32&G32&H32&I32&J32 -> 437214372233DINERSFOODCAFÉ/REST. | B32: 43721 | C32: 43722 | D32: KAILASH PARBAT RESTAURANT DOHA 634 AUTH NO. 067662 | E32: 33 | F32: 1 | G32: =ABS(E32)*F32 -> 33 | H32: DINERS | I32: FOOD | J32: CAFÉ/REST. | K32: DEBIT | L32: BILLED | N32: =MONTH(C32) -> 9
A33: =B33&C33&G33&H33&I33&J33 -> 437234372515.71DINERSTRANSPORTUBER | B33: 43723 | C33: 43725 | D33: UBERBV UBER TRIP HELP.UBE HELP.UBER.COM 528 AUTH NO. 072654 | E33: 15.71 | F33: 1 | G33: =ABS(E33)*F33 -> 15.71 | H33: DINERS | I33: TRANSPORT | J33: UBER | K33: DEBIT | L33: BILLED | N33: =MONTH(C33) -> 9
A34: =B34&C34&G34&H34&I34&J34 -> 437234372513MASTER CCFOODQATAR AIR | B34: 43723 | C34: 43725 | D34: THE COFFEE SHOP QR TOW DOHA QAT AUTH NO. 007288 | E34: 13 | F34: 1 | G34: =ABS(E34)*F34 -> 13 | H34: MASTER CC | I34: FOOD | J34: QATAR AIR | K34: DEBIT | L34: BILLED | N34: =MONTH(C34) -> 9
A35: =B35&C35&G35&H35&I35&J35 -> 437244372638MASTER CCFOODQATAR AIR | B35: 43724 | C35: 43726 | D35: THE COFFEE SHOP QR TOW DOHA QAT AUTH NO. 064146 | E35: 38 | F35: 1 | G35: =ABS(E35)*F35 -> 38 | H35: MASTER CC | I35: FOOD | J35: QATAR AIR | K35: DEBIT | L35: BILLED | N35: =MONTH(C35) -> 9
A36: =B36&C36&G36&H36&I36&J36 -> 437284373244.25MASTER CCGROCERYGRANDMART | B36: 43728 | C36: 43732 | D36: GRAND MART SUPERMARKET DOHA QAT AUTH NO. 006245 | E36: 44.25 | F36: 1 | G36: =ABS(E36)*F36 -> 44.25 | H36: MASTER CC | I36: GROCERY | J36: GRANDMART | K36: DEBIT | L36: BILLED | N36: =MONTH(C36) -> 9
A37: =B37&C37&G37&H37&I37&J37 -> 4372943730333.17DINERSSHOPPINGLULU | B37: 43729 | C37: 43730 | D37: LULU HYPERMARKET DOHA 634 AUTH NO. 007898 | E37: 333.17 | F37: 1 | G37: =ABS(E37)*F37 -> 333.17 | H37: DINERS | I37: SHOPPING | J37: LULU | K37: DEBIT | L37: BILLED | M37: 1 | N37: =MONTH(C37) -> 9
A38: =B38&C38&G38&H38&I38&J38 -> 437294373025DINERSGROCERYLULU | B38: 43729 | C38: 43730 | D38: LULU HYPERMARKET DOHA 634 AUTH NO. 055996 | E38: 25 | F38: 1 | G38: =ABS(E38)*F38 -> 25 | H38: DINERS | I38: GROCERY | J38: LULU | K38: DEBIT | L38: BILLED | N38: =MONTH(C38) -> 9
A39: =B39&C39&G39&H39&I39&J39 -> 437294373210MASTER CCTRANSPORTCAREEM | B39: 43729 | C39: 43732 | D39: CAREEM NETWORKS FZ LLC DUBAI ARE AUTH NO. 081642 | E39: 10 | F39: 1 | G39: =ABS(E39)*F39 -> 10 | H39: MASTER CC | I39: TRANSPORT | J39: CAREEM | K39: DEBIT | L39: BILLED | N39: =MONTH(C39) -> 9
A40: =B40&C40&G40&H40&I40&J40 -> 43729437328MASTER CCTRANSPORTCAREEM | B40: 43729 | C40: 43732 | D40: CAREEM NETWORKS FZ LLC DUBAI ARE AUTH NO. 047498 | E40: 8 | F40: 1 | G40: =ABS(E40)*F40 -> 8 | H40: MASTER CC | I40: TRANSPORT | J40: CAREEM | K40: DEBIT | L40: BILLED | N40: =MONTH(C40) -> 9
A41: =B41&C41&G41&H41&I41&J41 -> 437304373213MASTER CCFOODQATAR AIR | B41: 43730 | C41: 43732 | D41: THE COFFEE SHOP QR TOW DOHA QAT AUTH NO. 093522 | E41: 13 | F41: 1 | G41: =ABS(E41)*F41 -> 13 | H41: MASTER CC | I41: FOOD | J41: QATAR AIR | K41: DEBIT | L41: BILLED | N41: =MONTH(C41) -> 9
A42: =B42&C42&G42&H42&I42&J42 -> 437304373220MASTER CCTELECOMOOREDOO | B42: 43730 | C42: 43732 | D42: OOREDOO TOP-UP DOHA QAT AUTH NO. 097475 | E42: 20 | F42: 1 | G42: =ABS(E42)*F42 -> 20 | H42: MASTER CC | I42: TELECOM | J42: OOREDOO | K42: DEBIT | L42: BILLED | N42: =MONTH(C42) -> 9
A43: =B43&C43&G43&H43&I43&J43 -> 43730437328MASTER CCTRANSPORTCAREEM | B43: 43730 | C43: 43732 | D43: CAREEM NETWORKS FZ LLC DUBAI ARE AUTH NO. 026855 | E43: 8 | F43: 1 | G43: =ABS(E43)*F43 -> 8 | H43: MASTER CC | I43: TRANSPORT | J43: CAREEM | K43: DEBIT | L43: BILLED | N43: =MONTH(C43) -> 9
A44: =B44&C44&G44&H44&I44&J44 -> 437314373239.5DINERSGROCERYNEW INDIAN SUP | B44: 43731 | C44: 43732 | D44: NEW INDIAN SUP MARKET DOHA 634 AUTH NO. 037976 | E44: 39.5 | F44: 1 | G44: =ABS(E44)*F44 -> 39.5 | H44: DINERS | I44: GROCERY | J44: NEW INDIAN SUP | K44: DEBIT | L44: BILLED | N44: =MONTH(C44) -> 9
A45: =B45&C45&G45&H45&I45&J45 -> 437314373315MASTER CCFOODQATAR AIR | B45: 43731 | C45: 43733 | D45: THE COFFEE SHOP QR TOW DOHA QAT AUTH NO. 042882 | E45: 15 | F45: 1 | G45: =ABS(E45)*F45 -> 15 | H45: MASTER CC | I45: FOOD | J45: QATAR AIR | K45: DEBIT | L45: BILLED | N45: =MONTH(C45) -> 9
A46: =B46&C46&G46&H46&I46&J46 -> 437334373513MASTER CCFOODCAFÉ/REST. | B46: 43733 | C46: 43735 | D46: FOOD SMART QATAR AIRWA DOHA QAT AUTH NO. 093312 | E46: 13 | F46: 1 | G46: =ABS(E46)*F46 -> 13 | H46: MASTER CC | I46: FOOD | J46: CAFÉ/REST. | K46: DEBIT | L46: BILLED | N46: =MONTH(C46) -> 9
A47: =B47&C47&G47&H47&I47&J47 -> 43733437358MASTER CCTRANSPORTCAREEM | B47: 43733 | C47: 43735 | D47: CAREEM NETWORKS FZ LLC DUBAI ARE AUTH NO. 034559 | E47: 8 | F47: 1 | G47: =ABS(E47)*F47 -> 8 | H47: MASTER CC | I47: TRANSPORT | J47: CAREEM | K47: DEBIT | L47: BILLED | N47: =MONTH(C47) -> 9
A48: =B48&C48&G48&H48&I48&J48 -> 437344373413717CURRENTSALARYQATAR AIR | B48: 43734 | C48: =B48 -> 43734 | D48: SALARY TRANSFER,CDD 90926H005160,QCH1104746094000 QAR,QATAR AIRWAYS,2/SALA | E48: 13717 | F48: 1 | G48: =ABS(E48)*F48 -> 13717 | H48: CURRENT | I48: SALARY | J48: QATAR AIR | K48: CREDIT | L48: NA | N48: =MONTH(C48) -> 9
A49: =B49&C49&G49&H49&I49&J49 -> 437364373820MASTER CCFOODCAFÉ/REST. | B49: 43736 | C49: 43738 | D49: HAREESNA RESTAURANT DOHA QAT AUTH NO. 010670 | E49: 20 | F49: 1 | G49: =ABS(E49)*F49 -> 20 | H49: MASTER CC | I49: FOOD | J49: CAFÉ/REST. | K49: DEBIT | L49: BILLED | N49: =MONTH(C49) -> 9
A50: =B50&C50&G50&H50&I50&J50 -> 4373643738123.75MASTER CCGROCERYCARREFOUR | B50: 43736 | C50: 43738 | D50: CARREFOUR DOHA QAT AUTH NO. 066470 | E50: 123.75 | F50: 1 | G50: =ABS(E50)*F50 -> 123.75 | H50: MASTER CC | I50: GROCERY | J50: CARREFOUR | K50: DEBIT | L50: BILLED | N50: =MONTH(C50) -> 9
A51: =B51&C51&G51&H51&I51&J51 -> 43737437371000CURRENTWITHDRAWSELF | B51: 43737 | C51: =B51 -> 43737 | D51: ATM CASH WITHDRAWAL,927115757728,4610 757728,COMM. BANK OF QATAR DOHA,4342041934720023 28/09 18.02 | E51: -1000 | F51: 1 | G51: =ABS(E51)*F51 -> 1000 | H51: CURRENT | I51: WITHDRAW | J51: SELF | K51: DEBIT | L51: NA | N51: =MONTH(C51) -> 9
A52: =B52&C52&G52&H52&I52&J52 -> 43737437372493.12CURRENTTRANSFERINDIA | B52: 43737 | C52: =B52 -> 43737 | D52: TELEX TRANSFER,270919013468,monthly,Vineet Kumar Saraswat | E52: -2493.12 | F52: 1 | G52: =ABS(E52)*F52 -> 2493.12 | H52: CURRENT | I52: TRANSFER | J52: INDIA | K52: DEBIT | L52: NA | N52: =MONTH(C52) -> 9
A53: =B53&C53&G53&H53&I53&J53 -> 437374373715CURRENTSERVICEBANK | B53: 43737 | C53: =B53 -> 43737 | D53: TELEX CHARGE,270919013468,Telex Transfer Charges | E53: -15 | F53: 1 | G53: =ABS(E53)*F53 -> 15 | H53: CURRENT | I53: SERVICE | J53: BANK | K53: DEBIT | L53: NA | N53: =MONTH(C53) -> 9
A54: =B54&C54&G54&H54&I54&J54 -> 437374373825DINERSGROCERYNEW INDIAN SUP | B54: 43737 | C54: 43738 | D54: NEW INDIAN SUP MARKET DOHA 634 AUTH NO. 065495 | E54: 25 | F54: 1 | G54: =ABS(E54)*F54 -> 25 | H54: DINERS | I54: GROCERY | J54: NEW INDIAN SUP | K54: DEBIT | L54: BILLED | N54: =MONTH(C54) -> 9
A55: =B55&C55&G55&H55&I55&J55 -> 4373743738100MASTER CCSERVICEBANK | B55: 43737 | C55: 43738 | D55: CBQ REWARDS DOHA 634 AUTH NO. 057409 | E55: 100 | F55: 1 | G55: =ABS(E55)*F55 -> 100 | H55: MASTER CC | I55: SERVICE | J55: BANK | K55: DEBIT | L55: BILLED | N55: =MONTH(C55) -> 9
A56: =B56&C56&G56&H56&I56&J56 -> 437384373810.84DINERSSERVICEBANK | B56: 43738 | C56: 43738 | D56: CREDIT SHIELD PLUS CHARGES | E56: 10.84 | F56: 1 | G56: =ABS(E56)*F56 -> 10.84 | H56: DINERS | I56: SERVICE | J56: BANK | K56: DEBIT | L56: BILLED | N56: =MONTH(C56) -> 9
A57: =B57&C57&G57&H57&I57&J57 -> 437384374042MASTER CCFOODQATAR AIR | B57: 43738 | C57: 43740 | D57: THE COFFEE SHOP QR TOW DOHA QAT AUTH NO. 017863 | E57: 42 | F57: 1 | G57: =ABS(E57)*F57 -> 42 | H57: MASTER CC | I57: FOOD | J57: QATAR AIR | K57: DEBIT | L57: BILLED | N57: =MONTH(C57) -> 10
A58: =B58&C58&G58&H58&I58&J58 -> 437394373915CURRENTSERVICEBANK | B58: 43739 | C58: =B58 -> 43739 | D58: CREDIT,270919013468,BAW-TT Charge Refund | E58: 15 | F58: 1 | G58: =ABS(E58)*F58 -> 15 | H58: CURRENT | I58: SERVICE | J58: BANK | K58: CREDIT | L58: NA | N58: =MONTH(C58) -> 10
A59: =B59&C59&G59&H59&I59&J59 -> 43739437394CURRENTSERVICEBANK | B59: 43739 | C59: =B59 -> 43739 | D59: TELEX CHARGE,ThirdParty Transfer Charges,011019113763 | E59: -4 | F59: 1 | G59: =ABS(E59)*F59 -> 4 | H59: CURRENT | I59: SERVICE | J59: BANK | K59: DEBIT | L59: NA | N59: =MONTH(C59) -> 10
A60: =B60&C60&G60&H60&I60&J60 -> 43739437394850CURRENTRENTCAP ONE | B60: 43739 | C60: =B60 -> 43739 | D60: TELEX TRANSFER,011019113763,Capital One OCT 19,Capital One Trading Wll | E60: -4850 | F60: 1 | G60: =ABS(E60)*F60 -> 4850 | H60: CURRENT | I60: RENT | J60: CAP ONE | K60: DEBIT | L60: NA | N60: =MONTH(C60) -> 10
A61: =B61&C61&G61&H61&I61&J61 -> 43739437391677.92CURRENTCC BILL PAYMENTBANK | B61: 43739 | C61: =B61 -> 43739 | D61: CREDIT CARD COLLECTION,011019702485,CARD NO 5416 xxxx xxxx 9104,Paid using bankDirect | E61: -1677.92 | F61: 1 | G61: =ABS(E61)*F61 -> 1677.92 | H61: CURRENT | I61: CC BILL PAYMENT | J61: BANK | K61: DEBIT | L61: NA | N61: =MONTH(C61) -> 10
A62: =B62&C62&G62&H62&I62&J62 -> 4373943741186.61MASTER CCTELECOMVODAFONE | B62: 43739 | C62: 43741 | D62: VODAFONE-MOBILE APP DOHA QAT AUTH NO. 018549 | E62: 186.61 | F62: 1 | G62: =ABS(E62)*F62 -> 186.61 | H62: MASTER CC | I62: TELECOM | J62: VODAFONE | K62: DEBIT | L62: BILLED | N62: =MONTH(C62) -> 10
A63: =B63&C63&G63&H63&I63&J63 -> 43739437381677.92MASTER CCCC BILL PAYMENTBANK | B63: 43739 | C63: 43738 | D63: PAID BY ACCOUNT | E63: -1677.92 | F63: 1 | G63: =ABS(E63)*F63 -> 1677.92 | H63: MASTER CC | I63: CC BILL PAYMENT | J63: BANK | K63: CREDIT | L63: BILLED | N63: =MONTH(C63) -> 9
A64: =B64&C64&G64&H64&I64&J64 -> 437394374136MASTER CCTRANSPORTCAREEM | B64: 43739 | C64: 43741 | D64: CAREEM NETWORKS FZ LLC DUBAI ARE AUTH NO. 040772 | E64: 36 | F64: 1 | G64: =ABS(E64)*F64 -> 36 | H64: MASTER CC | I64: TRANSPORT | J64: CAREEM | K64: DEBIT | L64: BILLED | N64: =MONTH(C64) -> 10
A65: =B65&C65&G65&H65&I65&J65 -> 43742437446MASTER CCTRANSPORTCAREEM | B65: 43742 | C65: 43744 | D65: CAREEM NETWORKS FZ LLC DUBAI ARE AUTH NO. 058410 | E65: 6 | F65: 1 | G65: =ABS(E65)*F65 -> 6 | H65: MASTER CC | I65: TRANSPORT | J65: CAREEM | K65: DEBIT | L65: BILLED | N65: =MONTH(C65) -> 10
A66: =B66&C66&G66&H66&I66&J66 -> 43744437450DINERSTRANSPORTALKHEBRA | B66: 43744 | C66: 43745 | D66: AL-KHEBRA DRIVING SCHOOL DOHA 634 AUTH NO. 045455 | E66: 2520 | F66: 0 | G66: =ABS(E66)*F66 -> 0 | H66: DINERS | I66: TRANSPORT | J66: ALKHEBRA | K66: DEBIT | L66: BILLED | N66: =MONTH(C66) -> 10
A67: =B67&C67&G67&H67&I67&J67 -> 437444374633MASTER CCFOODQATAR AIR | B67: 43744 | C67: 43746 | D67: THE COFFEE SHOP QR TOW DOHA QAT AUTH NO. 043584 | E67: 33 | F67: 1 | G67: =ABS(E67)*F67 -> 33 | H67: MASTER CC | I67: FOOD | J67: QATAR AIR | K67: DEBIT | L67: BILLED | N67: =MONTH(C67) -> 10
A68: =B68&C68&G68&H68&I68&J68 -> 437444374613MASTER CCFOODQATAR AIR | B68: 43744 | C68: 43746 | D68: THE COFFEE SHOP QR TOW DOHA QAT AUTH NO. 003656 | E68: 13 | F68: 1 | G68: =ABS(E68)*F68 -> 13 | H68: MASTER CC | I68: FOOD | J68: QATAR AIR | K68: DEBIT | L68: BILLED | N68: =MONTH(C68) -> 10
A69: =B69&C69&G69&H69&I69&J69 -> 4374443746500MASTER CCTRANSPORTMINISTERY | B69: 43744 | C69: 43746 | D69: HOLOTEQ AL SAD DOHA QAT AUTH NO. 097298 | E69: 500 | F69: 1 | G69: =ABS(E69)*F69 -> 500 | H69: MASTER CC | I69: TRANSPORT | J69: MINISTERY | K69: DEBIT | L69: BILLED | N69: =MONTH(C69) -> 10
A70: =B70&C70&G70&H70&I70&J70 -> 437444374612MASTER CCTRANSPORTCAREEM | B70: 43744 | C70: 43746 | D70: CAREEM NETWORKS FZ LLC DUBAI ARE AUTH NO. 074604 | E70: 12 | F70: 1 | G70: =ABS(E70)*F70 -> 12 | H70: MASTER CC | I70: TRANSPORT | J70: CAREEM | K70: DEBIT | L70: BILLED | N70: =MONTH(C70) -> 10
A71: =B71&C71&G71&H71&I71&J71 -> 437444374613MASTER CCTRANSPORTCAREEM | B71: 43744 | C71: 43746 | D71: CAREEM NETWORKS FZ LLC DUBAI ARE AUTH NO. 004454 | E71: 13 | F71: 1 | G71: =ABS(E71)*F71 -> 13 | H71: MASTER CC | I71: TRANSPORT | J71: CAREEM | K71: DEBIT | L71: BILLED | N71: =MONTH(C71) -> 10
A72: =B72&C72&G72&H72&I72&J72 -> 437454374724MASTER CCGROCERYFFC | B72: 43745 | C72: 43747 | D72: FAMILY FOOD CENTER DOHA QAT AUTH NO. 068418 | E72: 24 | F72: 1 | G72: =ABS(E72)*F72 -> 24 | H72: MASTER CC | I72: GROCERY | J72: FFC | K72: DEBIT | L72: BILLED | N72: =MONTH(C72) -> 10
A73: =B73&C73&G73&H73&I73&J73 -> 43746437460DINERSTRANSPORTALKHEBRA | B73: 43746 | C73: 43746 | D73: Credit for Transaction Instalment | E73: -2520 | F73: 0 | G73: =ABS(E73)*F73 -> 0 | H73: DINERS | I73: TRANSPORT | J73: ALKHEBRA | K73: CREDIT | L73: BILLED | N73: =MONTH(C73) -> 10
A74: =B74&C74&G74&H74&I74&J74 -> 4374643746420DINERSEDUCATIONALKHEBRA | B74: 43746 | C74: 43746 | D74: AL-KHEBRA DRIVING SCHOOL DOHA 634 AUTH NO. 045455 | E74: 420 | F74: 1 | G74: =ABS(E74)*F74 -> 420 | H74: DINERS | I74: EDUCATION | J74: ALKHEBRA | K74: DEBIT | L74: BILLED | M74: 1 | N74: =MONTH(C74) -> 10
A75: =B75&C75&G75&H75&I75&J75 -> 437464374824MASTER CCFOODQATAR AIR | B75: 43746 | C75: 43748 | D75: THE COFFEE SHOP QR TOW DOHA QAT AUTH NO. 022469 | E75: 24 | F75: 1 | G75: =ABS(E75)*F75 -> 24 | H75: MASTER CC | I75: FOOD | J75: QATAR AIR | K75: DEBIT | L75: BILLED | N75: =MONTH(C75) -> 10
A76: =B76&C76&G76&H76&I76&J76 -> 437474374913MASTER CCFOODQATAR AIR | B76: 43747 | C76: 43749 | D76: THE COFFEE SHOP QR TOW DOHA QAT AUTH NO. 073874 | E76: 13 | F76: 1 | G76: =ABS(E76)*F76 -> 13 | H76: MASTER CC | I76: FOOD | J76: QATAR AIR | K76: DEBIT | L76: BILLED | N76: =MONTH(C76) -> 10
A77: =B77&C77&G77&H77&I77&J77 -> 437504375167.6DINERSGROCERYLULU | B77: 43750 | C77: 43751 | D77: LULU EXPRESS TRADING COMP DOHA 634 AUTH NO. 036882 | E77: 67.6 | F77: 1 | G77: =ABS(E77)*F77 -> 67.6 | H77: DINERS | I77: GROCERY | J77: LULU | K77: DEBIT | L77: BILLED | N77: =MONTH(C77) -> 10
A78: =B78&C78&G78&H78&I78&J78 -> 43752437522603CURRENTTRANSFERINDIA | B78: 43752 | C78: =B78 -> 43752 | D78: TELEX TRANSFER,141019012304,Arti Saraswat | E78: -2603 | F78: 1 | G78: =ABS(E78)*F78 -> 2603 | H78: CURRENT | I78: TRANSFER | J78: INDIA | K78: DEBIT | L78: NA | N78: =MONTH(C78) -> 10
A79: =B79&C79&G79&H79&I79&J79 -> 437524375215CURRENTSERVICEBANK | B79: 43752 | C79: =B79 -> 43752 | D79: TELEX CHARGE,141019012304,Telex Transfer Charges | E79: -15 | F79: 1 | G79: =ABS(E79)*F79 -> 15 | H79: CURRENT | I79: SERVICE | J79: BANK | K79: DEBIT | L79: NA | N79: =MONTH(C79) -> 10
A80: =B80&C80&G80&H80&I80&J80 -> 437524375422MASTER CCFOODQATAR AIR | B80: 43752 | C80: 43754 | D80: THE COFFEE SHOP QR TOW DOHA QAT AUTH NO. 051449 | E80: 22 | F80: 1 | G80: =ABS(E80)*F80 -> 22 | H80: MASTER CC | I80: FOOD | J80: QATAR AIR | K80: DEBIT | L80: BILLED | N80: =MONTH(C80) -> 10
A81: =B81&C81&G81&H81&I81&J81 -> 437554376036MASTER CCFOODQATAR AIR | B81: 43755 | C81: 43760 | D81: THE COFFEE SHOP QR TOW DOHA QAT AUTH NO. 062996 | E81: 36 | F81: 1 | G81: =ABS(E81)*F81 -> 36 | H81: MASTER CC | I81: FOOD | J81: QATAR AIR | K81: DEBIT | L81: BILLED | N81: =MONTH(C81) -> 10
A82: =B82&C82&G82&H82&I82&J82 -> 4375743760640MASTER CCGOLDMALABAR | B82: 43757 | C82: 43760 | D82: MALABAR GOLD INT AL WA DOHA QAT AUTH NO. 094623 | E82: 640 | F82: 1 | G82: =ABS(E82)*F82 -> 640 | H82: MASTER CC | I82: GOLD | J82: MALABAR | K82: DEBIT | L82: BILLED | N82: =MONTH(C82) -> 10
A83: =B83&C83&G83&H83&I83&J83 -> 437584376010MASTER CCFOODQATAR AIR | B83: 43758 | C83: 43760 | D83: THE COFFEE SHOP QR TOW DOHA QAT AUTH NO. 038112 | E83: 10 | F83: 1 | G83: =ABS(E83)*F83 -> 10 | H83: MASTER CC | I83: FOOD | J83: QATAR AIR | K83: DEBIT | L83: BILLED | N83: =MONTH(C83) -> 10
A84: =B84&C84&G84&H84&I84&J84 -> 4375943759333.17DINERSSHOPPINGLULU | B84: 43759 | C84: 43759 | D84: LULU HYPERMARKET DOHA 634 AUTH NO. 007898 | E84: 333.17 | F84: 1 | G84: =ABS(E84)*F84 -> 333.17 | H84: DINERS | I84: SHOPPING | J84: LULU | K84: DEBIT | L84: BILLED | M84: 1 | N84: =MONTH(C84) -> 10
A85: =B85&C85&G85&H85&I85&J85 -> 437614376340MASTER CCFOODCAFÉ/REST. | B85: 43761 | C85: 43763 | D85: BURGER KING - CITY CEN DOHA QAT AUTH NO. 072790 | E85: 40 | F85: 1 | G85: =ABS(E85)*F85 -> 40 | H85: MASTER CC | I85: FOOD | J85: CAFÉ/REST. | K85: DEBIT | L85: BILLED | N85: =MONTH(C85) -> 10
A86: =B86&C86&G86&H86&I86&J86 -> 437674376713730CURRENTSALARYQATAR AIR | B86: 43767 | C86: =B86 -> 43767 | D86: SALARY TRANSFER,CDD 91029H005248,QCH4709518660000 QAR,QATAR AIRWAYS,2/SALA | E86: 13730 | F86: 1 | G86: =ABS(E86)*F86 -> 13730 | H86: CURRENT | I86: SALARY | J86: QATAR AIR | K86: CREDIT | L86: NA | N86: =MONTH(C86) -> 10
A87: =B87&C87&G87&H87&I87&J87 -> 43767437672475CURRENTCC BILL PAYMENTBANK | B87: 43767 | C87: =B87 -> 43767 | D87: CREDIT CARD COLLECTION,291019701463,CARD NO 3643 xxxxxx 1825,Paid using bankDirect | E87: -2475 | F87: 1 | G87: =ABS(E87)*F87 -> 2475 | H87: CURRENT | I87: CC BILL PAYMENT | J87: BANK | K87: DEBIT | L87: NA | N87: =MONTH(C87) -> 10
A88: =B88&C88&G88&H88&I88&J88 -> 43767437672475DINERSCC BILL PAYMENTBANK | B88: 43767 | C88: 43767 | D88: PAID BY ACCOUNT | E88: -2475 | F88: 1 | G88: =ABS(E88)*F88 -> 2475 | H88: DINERS | I88: CC BILL PAYMENT | J88: BANK | K88: CREDIT | L88: BILLED | N88: =MONTH(C88) -> 10
A89: =B89&C89&G89&H89&I89&J89 -> 4376843768100CURRENTCC BILL PAYMENTBANK | B89: 43768 | C89: =B89 -> 43768 | D89: CREDIT CARD COLLECTION,301019705383,CARD NO 5416 xxxx xxxx 9104,Paid using bankDirect | E89: -100 | F89: 1 | G89: =ABS(E89)*F89 -> 100 | H89: CURRENT | I89: CC BILL PAYMENT | J89: BANK | K89: DEBIT | L89: NA | N89: =MONTH(C89) -> 10
A90: =B90&C90&G90&H90&I90&J90 -> 4376843768100MASTER CCCC BILL PAYMENTBANK | B90: 43768 | C90: 43768 | D90: PAID BY ACCOUNT | E90: -100 | F90: 1 | G90: =ABS(E90)*F90 -> 100 | H90: MASTER CC | I90: CC BILL PAYMENT | J90: BANK | K90: CREDIT | L90: BILLED | N90: =MONTH(C90) -> 10
A91: =B91&C91&G91&H91&I91&J91 -> 437684376929MASTER CCTRANSPORTCAREEM | B91: 43768 | C91: 43769 | D91: CAREEM NETWORKS FZ LLC DUBAI ARE AUTH NO. 011484 | E91: 29 | F91: 1 | G91: =ABS(E91)*F91 -> 29 | H91: MASTER CC | I91: TRANSPORT | J91: CAREEM | K91: DEBIT | L91: BILLED | N91: =MONTH(C91) -> 10
A92: =B92&C92&G92&H92&I92&J92 -> 4376943769100CURRENTTELECOMOOREDOO | B92: 43769 | C92: =B92 -> 43769 | D92: NAPS PURCHASE,019304010696,4018 028969 31,QPay Payment Ooredoo3,4342041934720023 31/10 10.09,63493000000 | E92: -100 | F92: 1 | G92: =ABS(E92)*F92 -> 100 | H92: CURRENT | I92: TELECOM | J92: OOREDOO | K92: DEBIT | L92: NA | N92: =MONTH(C92) -> 10
A93: =B93&C93&G93&H93&I93&J93 -> 437694376937CURRENTMEDICALPHARMACY | B93: 43769 | C93: =B93 -> 43769 | D93: NAPS PURCHASE,000001215002,4018 031385 42811901,CARE N CURE PHARMACY DDOHA,4342041934720023 31/10 15.37,63409000000 | E93: -37 | F93: 1 | G93: =ABS(E93)*F93 -> 37 | H93: CURRENT | I93: MEDICAL | J93: PHARMACY | K93: DEBIT | L93: NA | N93: =MONTH(C93) -> 10
A94: =B94&C94&G94&H94&I94&J94 -> 437694376934CURRENTFOODQATAR AIR | B94: 43769 | C94: =B94 -> 43769 | D94: NAPS PURCHASE,000001117152,4018 026474 82491202,THE COFFEE SHOP QR TOWDOHA,4342041934720023 31/10 12.45,63409000000 | E94: -34 | F94: 1 | G94: =ABS(E94)*F94 -> 34 | H94: CURRENT | I94: FOOD | J94: QATAR AIR | K94: DEBIT | L94: NA | N94: =MONTH(C94) -> 10
A95: =B95&C95&G95&H95&I95&J95 -> 437694377116MASTER CCTRANSPORTCAREEM | B95: 43769 | C95: 43771 | D95: CAREEM NETWORKS FZ LLC DUBAI ARE AUTH NO. 070422 | E95: 16 | F95: 1 | G95: =ABS(E95)*F95 -> 16 | H95: MASTER CC | I95: TRANSPORT | J95: CAREEM | K95: DEBIT | L95: BILLED | N95: =MONTH(C95) -> 11
A96: =B96&C96&G96&H96&I96&J96 -> 437694377116MASTER CCTRANSPORTCAREEM | B96: 43769 | C96: 43771 | D96: CAREEM NETWORKS FZ LLC DUBAI ARE AUTH NO. 044443 | E96: 16 | F96: 1 | G96: =ABS(E96)*F96 -> 16 | H96: MASTER CC | I96: TRANSPORT | J96: CAREEM | K96: DEBIT | L96: BILLED | N96: =MONTH(C96) -> 11
A97: =B97&C97&G97&H97&I97&J97 -> 4377043774150MASTER CCTELECOMVODAFONE | B97: 43770 | C97: 43774 | D97: VODAFONE-MOBILE APP DOHA QAT AUTH NO. 066332 | E97: 150 | F97: 1 | G97: =ABS(E97)*F97 -> 150 | H97: MASTER CC | I97: TELECOM | J97: VODAFONE | K97: DEBIT | L97: BILLED | N97: =MONTH(C97) -> 11
A98: =B98&C98&G98&H98&I98&J98 -> 4377043771247.1DINERSGROCERYLULU | B98: 43770 | C98: 43771 | D98: LULU EXPRESS TRADING COMP DOHA 634 AUTH NO. 079070 | E98: 247.1 | F98: 1 | G98: =ABS(E98)*F98 -> 247.1 | H98: DINERS | I98: GROCERY | J98: LULU | K98: DEBIT | L98: BILLED | N98: =MONTH(C98) -> 11
A99: =B99&C99&G99&H99&I99&J99 -> 43770437728MASTER CCTRANSPORTCAREEM | B99: 43770 | C99: 43772 | D99: CAREEM NETWORKS FZ LLC DUBAI ARE AUTH NO. 094940 | E99: 8 | F99: 1 | G99: =ABS(E99)*F99 -> 8 | H99: MASTER CC | I99: TRANSPORT | J99: CAREEM | K99: DEBIT | L99: BILLED | N99: =MONTH(C99) -> 11
A100: =B100&C100&G100&H100&I100&J100 -> 4377043772160MASTER CCTRANSPORTCAREEM | B100: 43770 | C100: 43772 | D100: CAREEM NETWORKS FZ LLC DUBAI ARE AUTH NO. 075985 | E100: 160 | F100: 1 | G100: =ABS(E100)*F100 -> 160 | H100: MASTER CC | I100: TRANSPORT | J100: CAREEM | K100: DEBIT | L100: BILLED | N100: =MONTH(C100) -> 11
...

Sheet stock
A1: stock_name | B1: stock_ticker | C1: stock_pur_date | D1: stock_units | E1: stock_buy_price | F1: stock_broker | G1: stock_sector
A2: ASIANPAINT | B2: ASIANPAINT.NS | C2: 44623 | D2: 11 | E2: 2763.03 | F2: ZERODHA | G2: Chemicals
A3: ASTRAL | B3: ASTRAL.NS | C3: 44932 | D3: 19 | E3: 1669.85 | F3: ZERODHA | G3: Plastics - Tubes/Pipes
A4: CDSL | B4: CDSL.NS | C4: 44593 | D4: 50 | E4: 644.61 | F4: ZERODHA | G4: Banking & Financial Services
A5: HINDUNILVR | B5: HINDUNILVR.NS | C5: 44932 | D5: 8 | E5: 2548.41 | F5: ZERODHA | G5: Consumer Non-durables
A6: INFY | B6: INFY.NS | C6: 44932 | D6: 12 | E6: 1443.43 | F6: ZERODHA | G6: Information Technology
A7: ITC | B7: ITC.NS | C7: 44593 | D7: 83 | E7: 324.41 | F7: ZERODHA | G7: Consumer Non-durables
A8: ITCHOTELS | B8: ITCHOTELS.NS | C8: 45670 | D8: 8 | E8: 436.45 | F8: ZERODHA | G8: Hotels
A9: KEI | B9: KEI.NS | C9: 45444 | D9: 7 | E9: 4429.8 | F9: ZERODHA | G9: Cables
A10: MARICO | B10: MARICO.NS | C10: 44593 | D10: 9 | E10: 525.48 | F10: ZERODHA | G10: Consumer Non-durables
A11: PERSISTENT | B11: PERSISTENT.NS | C11: 44932 | D11: 5 | E11: 2413.17 | F11: ZERODHA | G11: Information Technology
A12: PIDILITIND | B12: PIDILITIND.NS | C12: 44932 | D12: 7 | E12: 2741.3 | F12: ZERODHA | G12: Chemicals
A13: RELIANCE | B13: RELIANCE.NS | C13: 44623 | D13: 19 | E13: 1290.22 | F13: ZERODHA | G13: Oil & Gas
... A15: SUNDARMFIN | B15: SUNDARMFIN.NS | C15: 45099 | D15: 5 | E15: 2875.16 | F15: ZERODHA | G15: Auto Parts

Sheet SIP
A1: Sr. | B1: Name | C1: SIP_Name | D1: ISIN Code | E1: Unit | F1: TYPE | G1: Investment_type | H1: Start_date | I1: Years_Till | J1: Total_Investment | K1: Initial_Investment | L1: Link
A2: 1 | B2: ADITYA BIRLA SL SHORT TERM FUND(G) | C2: Aditya Birla SL Short Term Fund(G) | D2: INF209K01942 | E2: 0 | F2: Regular | G2: One Time | H2: 44344 | I2: =(TODAY()-H2)/365.25 -> 4.0246407 | J2: 0 | K2: =J2 -> 0 | L2: Aditya Birla Sun Life Short Term Fund - Regular Plan - Growth [37.0711] | Aditya Birla Sun Life Mutual Fund - Moneycontrol
A3: 2 | B3: ADITYA BIRLA SUN LIFE MNC FUND - GROWTH-REGULAR PLAN | C3: Birla Sun Life MNC Fund | D3: INF209K01322 | E3: 0 | F3: Regular | G3: SIP | H3: 44027 | I3: =(TODAY()-H3)/365.25 -> 4.8925394 | J3: 0 | K3: =J3 -> 0 | L3: https://www.moneycontrol.com/mutual-funds/amc-details/BS
A4: 3 | B4: ADITYA BIRLA SUN LIFE MUTUAL FUND TAX RELIEF 96 GROWTH | C4: Birla Sun Life Tax Relief 96 | D4: INF209K01108 | E4: 0 | F4: Tax Saver | G4: One Time | H4: 43101 | I4: =(TODAY()-H4)/365.25 -> 7.4277892 | J4: 0 | K4: =J4 -> 0 | L4: https://www.moneycontrol.com/mutual-funds/amc-details/BS
A5: 16 | B5: HDFC BALANCED DIRECT FUND | C5: HDFC Balanced Advantage Fund - Direct Plan - Growth | D5: INF179K01WA6 | E5: 82 | F5: Direct | G5: SIP | H5: 44935 | I5: =(TODAY()-H5)/365.25 -> 2.4065708 | J5: 33000 | K5: =J5 -> 33000
A6: 5 | B6: KOTAK LOW DURATION STD GROWTH | C6: Kotak Low Duration Fund | D6: INF178L01202 | E6: 0 | F6: Regular | G6: One Time | H6: 42948 | I6: =(TODAY()-H6)/365.25 -> 7.8466804 | J6: 0 | K6: =J6 -> 0 | L6: https://www.moneycontrol.com/mutual-funds/amc-details/KM
A7: 6 | B7: KOTAK MUTUAL TAX SAVER FUND | C7: Kotak Tax Saver | D7: INF174K01369 | E7: 0 | F7: Tax Saver | G7: One Time | H7: 43101 | I7: =(TODAY()-H7)/365.25 -> 7.4277892 | J7: 0 | K7: =J7 -> 0 | L7: https://www.moneycontrol.com/mutual-funds/amc-details/KM
A8: 7 | B8: KOTAK FLEXICAP FUND GR (REG PLAN) | C8: Kotak Flexicap Fund | D8: INF174K01336 | E8: 4806.783 | F8: Regular | G8: SIP | H8: 43235 | I8: =(TODAY()-H8)/365.25 -> 7.0609172 | J8: 170843.34 | K8: =J8 -> 170843.34 | L8: https://www.moneycontrol.com/mutual-funds/amc-details/KM
A9: 4 | B9: KOTAK FOCUSED EQUITY FUND GROWTH (REGULAR PLAN) | C9: Kotak Focused Equity Fund | D9: INF174KA1EK3 | E9: 10303.074 | F9: Regular | G9: SIP | H9: 44027 | I9: =(TODAY()-H9)/365.25 -> 4.8925394 | J9: 145000 | K9: =J9 -> 145000 | L9: https://www.moneycontrol.com/mf/mfinfo/amc_sch_listing.php?ffid=KM
A10: 9 | B10: NIPPON INDIA INCOME FUND - GROWTH | C10: Nippon India Income Fund | D10: INF204K01CL1 | E10: 0 | F10: Regular | G10: SIP | H10: 44027 | I10: =(TODAY()-H10)/365.25 -> 4.8925394 | J10: 0 | K10: =J10 -> 0 | L10: https://www.moneycontrol.com/mutual-funds/amc-details/RC
A11: 8 | B11: NIPPON INDIA GOLD SAVINGS FUND - SIP | C11: Nippon India Gold Savings Fund | D11: INF204K01KN0 | E11: 651.662 | F11: Regular | G11: SIP | H11: 44058 | I11: =(TODAY()-H11)/365.25 -> 4.807666 | J11: 13000 | K11: =J11 -> 13000 | L11: https://www.moneycontrol.com/mutual-funds/nav/nippon-india-gold-savings-fund-growth/MRC647
A12: 12 | B12: NIPPON INDIA PHARMA | C12: Nippon India Pharma Fund | D12: INF204K01968 | E12: 939 | F12: Regular | G12: SIP | H12: 43344 | I12: =(TODAY()-H12)/365.25 -> 6.7624914 | J12: 235000 | K12: =J12 -> 235000 | L12: https://www.moneycontrol.com/mutual-funds/amc-details/RC
A13: 13 | B13: NIPPON INDIA SMALL CAP | C13: Nippon India Small Cap | D13: INF204K01HY3 | E13: 1418 | F13: Regular | G13: SIP | H13: 44454 | I13: =(TODAY()-H13)/365.25 -> 3.7234771 | J13: 126000 | K13: =J13 -> 126000 | L13: https://www.moneycontrol.com/mutual-funds/nav/nippon-india-small-cap-fund-growth/MRC587
A14: 15 | B14: ADITYA BIRLA SUN LIFE FRONTLINE EQUITY FUND - REGULAR PLAN - GROWTH | C14: Birla Sun Life Frontline Eqt Fund | D14: INF209K01BR9 | E14: 0 | F14: Regular | G14: One Time | H14: 44621 | I14: =(TODAY()-H14)/365.25 -> 3.266256 | J14: 0 | K14: =J14 -> 0 | L14: https://www.moneycontrol.com/mutual-funds/nav/aditya-birla-sun-life-frontline-equity-fund/MAC031
A15: 14 | B15: NIPPON INDIA VALUE FUND | C15: Nippon India Value Fund | D15: INF204K01GB3 | E15: 521 | F15: Regular | G15: SIP | H15: 44454 | I15: =(TODAY()-H15)/365.25 -> 3.7234771 | J15: 67500 | K15: =J15 -> 67500 | L15: https://www.moneycontrol.com/mutual-funds/nav/nippon-india-value-fund/MRC098
A16: 17 | B16: PARAG PARIKH FLEXI DIRECT FUND | C16: Parag Parikh Flexi Cap Fund - Direct Plan - Growth | D16: INF879O01027 | E16: 916 | F16: Direct | G16: SIP | H16: 44935 | I16: =(TODAY()-H16)/365.25 -> 2.4065708 | J16: 64360 | K16: =J16 -> 64360
A17: 18 | B17: Tata Gold ETF Fund of Fund | C17: Tata Gold ETF Fund of Fund | D17: INF277KA1869 | E17: 499.975 | F17: Direct | G17: SIP | H17: 45310 | J17: 5000 | K17: =J17 -> 5000

Sheet SIP_Name
A1: ISIN | B1: SIP_NICK_NAME | C1: BRAND | D1: FUND_TYPE | E1: INVESTMENT_RANGE
A2: INF174K01336 | B2: KOTAK STD MULT | C2: KOTAK | D2: EQUITY | E2: LOW-MID
A3: INF174K01369 | B3: KOTAK TAX SAVER | C3: KOTAK | D3: ELSS | E3: MID-LONG
A4: INF174KA1EK3 | B4: KOTAK FOCUSED EQUITY SIP | C4: KOTAK | D4: EQUITY | E4: LOW-MID
A5: INF178L01202 | B5: KOTAK LOW DUR | C5: KOTAK | D5: DEBT | E5: LOW
A6: INF204K01968 | B6: NIPPON IND PHARMA | C6: NIPPON | D6: EQUITY | E6: LOW-MID
A7: INF204K01CL1 | B7: NIPPON IND INCOME SIP | C7: NIPPON | D7: DEBT | E7: MID-LONG
A8: INF204K01KN0 | B8: NIPPON IND GOLD SIP | C8: NIPPON | D8: COMMODITY | E8: LONG
A9: INF209K01108 | B9: ABSL TAX RELIEF | C9: ABSL | D9: ELSS | E9: MID-LONG
A10: INF209K01322 | B10: ABSL MNC FUND SIP | C10: ABSL | D10: EQUITY | E10: LOW-MID
A11: INF209K01942 | B11: ABSL SHORT TERM | C11: ABSL | D11: DEBT | E11: LOW
A12: INF204K01HY3 | B12: NIPPON INDIA SMALL CAP | C12: NIPPON | D12: EQUITY | E12: LOW-MID
... A17: INF277KA1869 | B17: Tata Gold ETF Fund of Fund | C17: TATA | D17: EQUITY | E17: MID-LONG

Sheet stocks and mf
A1: Stocks/ETFs | D1: Holdings - 24-Nov-23 IST
A2: Security | B2: No. of Smallcases | C2: Quantity | D2: Average Cost â‚¹ | E2: Portfolio Weight % | F2: LTP â‚¹ | G2: Invested Value â‚¹ | H2: Current Value â‚¹ | I2: P & L â‚¹ | J2: Net Change % | K2: Daily Change â‚¹ | L2: Daily Change %
A3: ASIANPAINT | B3: 1 | C3: 2 | D3: 2846.95 | E3: 3.24 | F3: 3128.5 | G3: 5693.9 | H3: 6257 | I3: 563.1 | J3: 9.89 | K3: 5.55 | L3: 0.18
A4: ASTRAL | B4: 1 | C4: 5 | D4: 1551.52 | E4: 5.01 | F4: 1938.1 | G4: 7757.6 | H4: 9690.5 | I4: 1932.9 | J4: 24.92 | K4: -15.85 | L4: -0.81
A5: CDSL | B5: 0 | C5: 25 | D5: 1289.22 | E5: 23.07 | F5: 1783.5 | G5: 32230.5 | H5: 44587.5 | I5: 12357 | J5: 38.34 | K5: -8.6 | L5: -0.48
A6: HINDUNILVR | B6: 1 | C6: 4 | D6: 2624.14 | E6: 5.2 | F6: 2511.5 | G6: 10496.56 | H6: 10046 | I6: -450.56 | J6: -4.29 | K6: -8.4 | L6: -0.33
A7: INFY | B7: 1 | C7: 7 | D7: 1422.35 | E7: 5.23 | F7: 1443.75 | G7: 9956.45 | H7: 10106.25 | I7: 149.8 | J7: 1.5 | K7: -5.5 | L7: -0.38
A8: ITC | B8: 1 | C8: 51 | D8: 256.49 | E8: 11.58 | F8: 438.75 | G8: 13080.99 | H8: 22376.25 | I8: 9295.26 | J8: 71.06 | K8: -1.6 | L8: -0.36
A9: JIOFIN | B9: 1 | C9: 3 | D9: 117.39 | E9: 0.34 | F9: 220.85 | G9: 352.17 | H9: 662.55 | I9: 310.38 | J9: 88.13 | K9: -0.4 | L9: -0.18
A10: LAOPALA | B10: 1 | C10: 18 | D10: 385.87 | E10: 3.57 | F10: 383.05 | G10: 6945.66 | H10: 6894.9 | I10: -50.76 | J10: -0.73 | K10: 1.55 | L10: 0.41
A11: MARICO | B11: 1 | C11: 25 | D11: 511.44 | E11: 6.91 | F11: 533.95 | G11: 12786 | H11: 13348.75 | I11: 562.75 | J11: 4.4 | K11: 3.05 | L11: 0.57
A12: PERSISTENT | B12: 1 | C12: 2 | D12: 4329.6 | E12: 6.62 | F12: 6396.35 | G12: 8659.2 | H12: 12792.7 | I12: 4133.5 | J12: 47.74 | K12: 17.5 | L12: 0.27
A13: PIDILITIND | B13: 1 | C13: 4 | D13: 2572 | E13: 5.17 | F13: 2496.05 | G13: 10288 | H13: 9984.2 | I13: -303.8 | J13: -2.95 | K13: -13.25 | L13: -0.53
A14: REDINGTON | B14: 1 | C14: 64 | D14: 172.16 | E14: 5.36 | F14: 161.8 | G14: 11018.24 | H14: 10355.2 | I14: -663.04 | J14: -6.02 | K14: 3.65 | L14: 2.31
... A17: SUNDARMFIN | B17: 1 | C17: 4 | D17: 2602.7 | E17: 6.46 | F17: 3124 | G17: 10410.8 | H17: 12496 | I17: 2085.2 | J17: 20.03 | K17: -11.9 | L17: -0.38
A19: Smallcases
A20: Dividend Aristocrats | B20: - | C20: - | D20: - | E20: 66.24 | F20: - | G20: 120532.25 | H20: 128041.65 | I20: 7509.4 | J20: 6.23 | K20: - | L20: -
A22: Fund Name | B22: AMC Name | C22: Category | D22: Sub-Category | E22: Plan Type | F22: Option Type | G22: NAV â‚¹ | H22: Units | I22: Invested Amt â‚¹ | J22: Current Value â‚¹ | K22: Weight % | L22: P&L â‚¹ | M22: P&L % | N22: XIRR % | O22: Invested Since
A23: Aditya Birla SL MNC Fund | B23: Aditya Birla Sun Life AMC Limited | C23: Equity | D23: Thematic Fund - MNC | E23: Standard | F23: Growth | G23: 1095.25 | H23: 5.89 | I23: 5518.27 | J23: 6455.4 | K23: 0.53 | L23: 937.13 | M23: 16.98 | N23: 1.95 | O23: 44026
A24: Aditya Birla SL Multi-Cap Fund | B24: Aditya Birla Sun Life AMC Limited | C24: Equity | D24: Multi Cap Fund | E24: Standard | F24: Growth | G24: 14.65 | H24: 393.95 | I24: 4770.73 | J24: 5771.37 | K24: 0.48 | L24: 1000.64 | M24: 20.97 | N24: 26.37 | O24: 44957
A25: HDFC Balanced Advantage Fund | B25: HDFC Asset Management Company Limited | C25: Hybrid | D25: Balanced Advantage Fund | E25: Direct | F25: Growth | G25: 423.38 | H25: 71.91 | I25: 27998.7 | J25: 30445.33 | K25: 2.51 | L25: 2446.63 | M25: 8.74 | N25: 28.83 | O25: 44935
A26: Kotak Flexicap Fund | B26: Kotak Mahindra Asset Management Company Limited | C26: Equity | D26: Flexi Cap Fund | E26: Standard | F26: Growth | G26: 61.76 | H26: 4806.78 | I26: 170840.48 | J26: 296886.15 | K26: 24.49 | L26: 126045.67 | M26: 73.78 | N26: 13.08 | O26: 42938
A27: Kotak Focused Equity Fund | B27: Kotak Mahindra Asset Management Company Limited | C27: Equity | D27: Focused Fund | E27: Standard | F27: Growth | G27: 18.81 | H27: 10303.07 | I27: 144992.76 | J27: 193780.23 | K27: 15.98 | L27: 48787.47 | M27: 33.65 | N27: 13.98 | O27: 44026
A28: Parag Parikh Flexi Cap Fund | B28: PPFAS Asset Management Pvt. Ltd. | C28: Equity | D28: Flexi Cap Fund | E28: Direct | F28: Growth | G28: 66.24 | H28: 809.96 | I28: 48497.59 | J28: 53650.22 | K28: 4.43 | L28: 5152.63 | M28: 10.62 | N28: 32.06 | O28: 44935
A29: Nippon India Gold Savings Fund | B29: Nippon Life India Asset Management Limited | C29: Commodity | D29: FoFs - Gold | E29: Standard | F29: Growth | G29: 24.16 | H29: 651.66 | I29: 12999.36 | J29: 15744.15 | K29: 1.3 | L29: 2744.79 | M29: 21.11 | N29: 7.14 | O29: 44060
A30: Nippon India Pharma Fund | B30: Nippon Life India Asset Management Limited | C30: Equity | D30: Sectoral Fund - Pharma & Health Care | E30: Standard | F30: Growth | G30: 370 | H30: 939.46 | I30: 234990.39 | J30: 347602.26 | K30: 28.67 | L30: 112611.88 | M30: 47.92 | N30: 18.03 | O30: 43346
A31: Nippon India Small Cap Fund | B31: Nippon Life India Asset Management Limited | C31: Equity | D31: Small Cap Fund | E31: Standard | F31: Growth | G31: 128.9 | H31: 1400.07 | I31: 123274.45 | J31: 180465.72 | K31: 14.89 | L31: 57191.27 | M31: 46.39 | N31: 28.77 | O31: 44441
A32: Nippon India Value Fund | B32: Nippon Life India Asset Management Limited | C32: Equity | D32: Value Fund | E32: Standard | F32: Growth | G32: 160.78 | H32: 507.28 | I32: 64996.69 | J32: 81561.26 | K32: 6.73 | L32: 16564.57 | M32: 25.49 | N32: 21.46 | O32: 44455
A33: Total | I33: 838879.43 | J33: 1212362.1 | K33: 100 | L33: 373482.66 | M33: 44.52

Sheet FD_RD
A1: Sr_No | B1: TYPE | C1: Account_No | D1: Nick_Name | E1: Deposit_Date | F1: ROI(%p.a) | G1: Incremental | H1: Tenor | I1: Maturity_Date | J1: Maturity_Amount | K1: RD_Installment | L1: Available_Balance | M1: BANK
A2: 0 | B2: PPF | C2: 33436074337 | D2: Mr. VINEET KUMAR SARASWAT | E2: 41586 | F2: 0.071 | G2: 0 | H2: 15 | I2: =E2+(H2*365.25) -> 47064.75 | J2: =L2 -> 428312 | L2: 428312 | M2: SBI
A3: 1 | B3: FD | C3: 43971647953 | D3: Mr. VINEET KUMAR SARASWAT | E3: 45751 | F3: 0.0725 | G3: 0 | H3: 1 | I3: =E3+444 -> 46195 | J3: 873085 | L3: 800000 | M3: SBI
A4: 2 | B4: FD | C4: 43971669217 | D4: Mr. VINEET KUMAR SARASWAT | E4: 45751 | F4: 0.0725 | G4: 0 | H4: 1 | I4: =E4+444 -> 46195 | J4: 1091356 | L4: 1000000 | M4: SBI
A5: 3 | B5: FD | C5: 43971646223 | D5: Mr. VINEET KUMAR SARASWAT | E5: 45751 | F5: 0.0725 | G5: 0 | H5: 1 | I5: =E5+444 -> 46195 | J5: 1309627 | L5: 1200000 | M5: SBI
A6: 7 | B6: NRE | C6: 39435504915 | D6: Mr. VINEET KUMAR SARASWAT | E6: 44307 | F6: 0.027 | G6: 0 | H6: 10 | I6: =E6+(H6*365.25) -> 47959.5 | J6: 0 | L6: =J6 -> 0 | M6: SBI
A7: 8 | B7: NRO | C7: 20181220065 | D7: Mr. VINEET KUMAR SARASWAT | E7: 44307 | F7: 0.027 | G7: 0 | H7: 10 | I7: =E7+(H7*365.25) -> 47959.5 | J7: 0 | L7: =J7 -> 0 | M7: SBI
A8: 9 | B8: SAVING | C8: 6.1260001e+15 | D8: Mr. VINEET KUMAR SARASWAT | E8: 44533 | F8: 0 | G8: 0 | H8: 10 | I8: =E8+(H8*365.25) -> 48185.5 | J8: 0 | L8: =J8 -> 0 | M8: PNB

Sheet LIC
A1: Policy_Number | B1: Date_Of_Commence | C1: Due_Dates | D1: Premium_Amount | E1: Payment_Date | F1: Premium_Paid | G1: Acc_Pre_Paid | H1: Service_ax | I1: Sum_Assured | J1: Bonus
A2: 234397289 | B2: 39627 | C2: 39627 | D2: 2347 | E2: 39627 | F2: 2347 | G2: =F2 -> 2347 | H2: 0 | I2: 200000 | J2: 2085.1064
A3: 234397289 | B3: 39627 | C3: 39719 | D3: 2347 | E3: 39719 | F3: 2347 | G3: =G2+F3 -> 4694 | H3: 0 | I3: 200000 | J3: 4170.2128
A4: 234397289 | B4: 39627 | C4: 39810 | D4: 2347 | E4: 39810 | F4: 2347 | G4: =G3+F4 -> 7041 | H4: 0 | I4: 200000 | J4: 6255.3191
A5: 234397289 | B5: 39627 | C5: 39900 | D5: 2347 | E5: 39900 | F5: 2347 | G5: =G4+F5 -> 9388 | H5: 0 | I5: 200000 | J5: 8340.4255
A6: 234397289 | B6: 39627 | C6: 39992 | D6: 2347 | E6: 39992 | F6: 2347 | G6: =G5+F6 -> 11735 | H6: 0 | I6: 200000 | J6: 10425.532
A7: 234397289 | B7: 39627 | C7: 40084 | D7: 2347 | E7: 40084 | F7: 2347 | G7: =G6+F7 -> 14082 | H7: 0 | I7: 200000 | J7: 12510.638
A8: 234397289 | B8: 39627 | C8: 40175 | D8: 2347 | E8: 40175 | F8: 2347 | G8: =G7+F8 -> 16429 | H8: 0 | I8: 200000 | J8: 14595.745
A9: 234397289 | B9: 39627 | C9: 40265 | D9: 2347 | E9: 40265 | F9: 2347 | G9: =G8+F9 -> 18776 | H9: 0 | I9: 200000 | J9: 16680.851
A10: 234397289 | B10: 39627 | C10: 40357 | D10: 2347 | E10: 40357 | F10: 2347 | G10: =G9+F10 -> 21123 | H10: 0 | I10: 200000 | J10: 18765.957
A11: 234397289 | B11: 39627 | C11: 40449 | D11: 2347 | E11: 40449 | F11: 2347 | G11: =G10+F11 -> 23470 | H11: 0 | I11: 200000 | J11: 20851.064
A12: 234397289 | B12: 39627 | C12: 40540 | D12: 2347 | E12: 40540 | F12: 2347 | G12: =G11+F12 -> 25817 | H12: 0 | I12: 200000 | J12: 22936.17
A13: 234397289 | B13: 39627 | C13: 40630 | D13: 2347 | E13: 40630 | F13: 2347 | G13: =G12+F13 -> 28164 | H13: 0 | I13: 200000 | J13: 25021.277
A14: 234397289 | B14: 39627 | C14: 40722 | D14: 2347 | E14: 40722 | F14: 2347 | G14: =G13+F14 -> 30511 | H14: 0 | I14: 200000 | J14: 27106.383
... A87: 117645635 | B87: 41834 | C87: 45487 | D87: 18966 | E87: 45464 | F87: 2347 | G87: =G86+F87 -> 550841 | H87: 0 | I87: 500000 | J87: 142800
A88: 234397289 | B88: 39627 | C88: 45563 | D88: 2347 | G88: =G87+F88 -> 550841 | H88: 0 | I88: 200000
A89: 234397289 | B89: 39627 | C89: 45654 | D89: 2347 | G89: =G88+F89 -> 550841 | H89: 0 | I89: 200000
A90: 117645635 | B90: 41834 | C90: 45671 | D90: 18966 | G90: =G89+F90 -> 550841 | I90: 500000
A91: 234397289 | B91: 39627 | C91: 45744 | D91: 2347 | G91: =G90+F91 -> 550841 | H91: 0 | I91: 200000
A92: 234397289 | B92: 39627 | C92: 45836 | D92: 2347 | G92: =G91+F92 -> 550841 | H92: 0 | I92: 200000
A93: 117645635 | B93: 41834 | C93: 45852 | D93: 18966 | G93: =G92+F93 -> 550841 | I93: 500000
A94: 234397289 | B94: 39627 | C94: 45928 | D94: 2347 | G94: =G93+F94 -> 550841 | H94: 0 | I94: 200000
A95: 234397289 | B95: 39627 | C95: 46019 | D95: 2347 | G95: =G94+F95 -> 550841 | H95: 0 | I95: 200000
A96: 117645635 | B96: 41834 | C96: 46036 | D96: 18966 | G96: =G95+F96 -> 550841 | I96: 500000
A97: 234397289 | B97: 39627 | C97: 46109 | D97: 2347 | G97: =G96+F97 -> 550841 | H97: 0 | I97: 200000
A98: 234397289 | B98: 39627 | C98: 46201 | D98: 2347 | G98: =G97+F98 -> 550841 | H98: 0 | I98: 200000
A99: 117645635 | B99: 41834 | C99: 46217 | D99: 18966 | G99: =G98+F99 -> 550841 | I99: 500000
A100: 234397289 | B100: 39627 | C100: 46293 | D100: 2347 | G100: =G99+F100 -> 550841 | H100: 0 | I100: 200000
A101: 234397289 | B101: 39627 | C101: 46384 | D101: 2347 | G101: =G100+F101 -> 550841 | H101: 0 | I101: 200000
A102: 117645635 | B102: 41834 | C102: 46401 | D102: 18966 | G102: =G101+F102 -> 550841 | I102: 500000
A103: 234397289 | B103: 39627 | C103: 46474 | D103: 2347 | G103: =G102+F103 -> 550841 | H103: 0 | I103: 200000
A104: 234397289 | B104: 39627 | C104: 46566 | D104: 2347 | G104: =G103+F104 -> 550841 | H104: 0 | I104: 200000
A105: 117645635 | B105: 41834 | C105: 46582 | D105: 18966 | G105: =G104+F105 -> 550841 | I105: 500000
A106: 234397289 | B106: 39627 | C106: 46658 | D106: 2347 | G106: =G105+F106 -> 550841 | H106: 0 | I106: 200000
A107: 234397289 | B107: 39627 | C107: 46749 | D107: 2347 | G107: =G106+F107 -> 550841 | H107: 0 | I107: 200000
A108: 117645635 | B108: 41834 | C108: 46766 | D108: 18966 | G108: =G107+F108 -> 550841 | I108: 500000
A109: 234397289 | B109: 39627 | C109: 46839 | D109: 2347 | G109: =G108+F109 -> 550841 | H109: 0 | I109: 200000
A110: 234397289 | B110: 39627 | C110: 46932 | D110: 2347 | G110: =G109+F110 -> 550841 | H110: 0 | I110: 200000
A111: 117645635 | B111: 41834 | C111: 46948 | D111: 18966 | G111: =G110+F111 -> 550841 | I111: 500000
A112: 234397289 | B112: 39627 | C112: 47024 | D112: 2347 | G112: =G111+F112 -> 550841 | H112: 0 | I112: 200000
A113: 234397289 | B113: 39627 | C113: 47115 | D113: 2347 | G113: =G112+F113 -> 550841 | H113: 0 | I113: 200000
A114: 117645635 | B114: 41834 | C114: 47132 | D114: 18966 | G114: =G113+F114 -> 550841 | I114: 500000
A115: 234397289 | B115: 39627 | C115: 47205 | D115: 2347 | G115: =G114+F115 -> 550841 | H115: 0 | I115: 200000
A116: 234397289 | B116: 39627 | C116: 47297 | D116: 2347 | G116: =G115+F116 -> 550841 | H116: 0 | I116: 200000
A117: 117645635 | B117: 41834 | C117: 47313 | G117: =G116+F117 -> 550841 | I117: 500000
A118: 117645635 | B118: 41834 | C118: 47497 | G118: =G117+F118 -> 550841 | I118: 500000
A119: 117645635 | B119: 41834 | C119: 47678 | G119: =G118+F119 -> 550841 | I119: 500000
A120: 117645635 | B120: 41834 | C120: 47862 | G120: =G119+F120 -> 550841 | I120: 500000
A121: 117645635 | B121: 41834 | C121: 48043 | G121: =G120+F121 -> 550841 | I121: 500000
A122: 117645635 | B122: 41834 | C122: 48227 | G122: =G121+F122 -> 550841 | I122: 500000
A123: 117645635 | B123: 41834 | C123: 48409 | G123: =G122+F123 -> 550841 | I123: 500000
A124: 117645635 | B124: 41834 | C124: 48593 | G124: =G123+F124 -> 550841 | I124: 500000
A125: 117645635 | B125: 41834 | C125: 48774 | G125: =G124+F125 -> 550841 | I125: 500000
A126: 117645635 | B126: 41834 | C126: 48958 | G126: =G125+F126 -> 550841 | I126: 500000
A127: 117645635 | B127: 41834 | C127: 49140 | G127: =G126+F127 -> 550841 | I127: 500000

Sheet GOLD_RESERVE
A1: SR | B1: PUR_DATE | C1: Commodity | D1: INVOICE_NUM | E1: ITEM_CODE | F1: ITEM | G1: QUANTITY | H1: QUALITY | I1: GOLD_WEIGHT_GRMS | J1: GOLD_RATE_PER_1GRAM | K1: GOLD_RATE_INR_PER_GRAM | L1: NET_WEIGHT | M1: MAKING_CHARGE | N1: %_MAKING | O1: AMOUNT | P1: %_TAX | Q1: TAX_AMOUNT | R1: TTL_AMOUNT_QAR | S1: TTL_AMOUNT_INR | T1: JEWELLERS | U1: PLACE | V1: P_TYPE | W1: REMARK
A2: 1 | B2: 42005 | C2: Gold | D2: A001 | E2: C004 | F2: CHAIN | G2: 1 | T2: KANPUR | U2: KANPUR | V2: SELF | W2: VINEET
A3: 2 | B3: 42005 | C3: Gold | D3: A002 | E3: C005 | F3: LOCKET | G3: 1 | T3: KANPUR | U3: KANPUR | V3: SELF | W3: VINEET
A4: 3 | B4: 43070 | C4: Gold | D4: A003 | E4: C002 | F4: RING | G4: 1 | T4: HATHRAS | U4: HATHRAS | V4: SELF | W4: VINEET
A5: 4 | B5: 43070 | C5: Gold | D5: A004 | E5: C003 | F5: RING | G5: 1 | T5: KANPUR | U5: KANPUR | V5: SELF | W5: VINEET
A6: 5 | B6: 43070 | C6: Gold | D6: A005 | E6: C006 | F6: BANGLE | G6: 4 | T6: MUNNILAL | U6: KANPUR | V6: SELF | W6: ARTI
A7: 6 | B7: 43070 | C7: Gold | D7: A006 | E7: C007 | F7: NECKLACE | G7: 1 | T7: MUNNILAL | U7: KANPUR | V7: SELF | W7: ARTI
A8: 7 | B8: 43070 | C8: Gold | D8: A007 | E8: C008 | F8: KANTHI | G8: 1 | T8: MUNNILAL | U8: KANPUR | V8: SELF | W8: ARTI
A9: 8 | B9: 43070 | C9: Gold | D9: A008 | E9: C009 | F9: EARRING | G9: 1 | T9: KSHAMTA MAAM | U9: DELHI | V9: SELF | W9: ARTI
A10: 9 | B10: 43070 | C10: Gold | D10: A009 | E10: C010 | F10: EARRING | G10: 1 | T10: MUNNILAL | U10: KANPUR | V10: SELF | W10: ARTI
A11: 10 | B11: 43760 | C11: Gold | D11: A010 | E11: C001 | F11: RING | G11: 1 | H11: 22K | I11: 3.35 | J11: 169 | K11: =J11*19.41 -> 3280.29 | L11: =I11 -> 3.35 | M11: 73.5 | N11: =M11/(I11*J11) -> 0.12982425 | O11: =(I11*J11)+M11 -> 639.65 | P11: 0 | Q11: =O11*P11 -> 0 | R11: =O11+Q11 -> 639.65 | S11: =R11*K11/J11 -> 12415.606 | T11: MALABAR | U11: DOHA | V11: GIFT | W11: KAPIL BHAI
A12: 11 | B12: 44148 | C12: Gold | D12: A011 | E12: C011 | F12: Nose Ring | G12: 1 | H12: 20K | I12: 1.99 | T12: MUNNILAL | U12: KANPUR | V12: SELF | W12: ARTI
A13: 12 | B13: 43784 | C13: Gold | D13: WETGNC004603 | E13: 800110269085 | F13: NECKLACE | G13: 1 | H13: 22K | I13: 13.72 | J13: 169.5 | K13: =J13*19.72 -> 3342.54 | L13: =I13 -> 13.72 | M13: 316.41 | N13: =M13/(I13*J13) -> 0.13605872 | O13: =(I13*J13)+M13 -> 2641.95 | P13: 0 | Q13: =O13*P13 -> 0 | R13: =O13+Q13 -> 2641.95 | S13: =R13*K13/J13 -> 52099.254 | T13: KALYAN | U13: DOHA | V13: SELF | W13: ARTI
A14: 13 | B14: 43847 | C14: Gold | D14: QMDLC10500020727 | E14: 131000449407 | F14: EARRING | G14: 1 | H14: 22K | I14: 1.29 | J14: 179 | K14: =J14*19.51 -> 3492.29 | L14: 1.29 | M14: 44.09 | N14: =M14/(I14*J14) -> 0.19094019 | O14: =(I14*J14)+M14 -> 275 | P14: 0 | Q14: =O14*P14 -> 0 | R14: =O14+Q14 -> 275 | S14: =R14*K14/J14 -> 5365.25 | T14: MALABAR | U14: DOHA | V14: SELF | W14: ARTI
A15: 14 | B15: 43867 | C15: Gold | D15: WETGNC005891 | E15: 800110303818 | F15: RING | G15: 1 | H15: 22K | I15: 4.43 | J15: 179.5 | K15: =J15*19.55 -> 3509.225 | L15: =I15 -> 4.43 | M15: 95.81 | N15: =M15/(I15*J15) -> 0.12048769 | O15: =(I15*J15)+M15 -> 890.995 | P15: 0 | Q15: =O15*P15 -> 0 | R15: =O15+Q15 -> 890.995 | S15: =R15*K15/J15 -> 17418.952 | T15: KALYAN | U15: DOHA | V15: GIFT | W15: DOLLY
A16: 15 | B16: 43869 | C16: Gold | D16: HBKGNB002614 | E16: 800110270040 | F16: CHAIN | G16: 1 | H16: 22K | I16: 4.64 | J16: 181 | K16: =J16*19.65 -> 3556.65 | L16: 4.63 | M16: 117.16 | N16: =M16/(I16*J16) -> 0.13950276 | O16: =(I16*J16)+M16 -> 957 | P16: 0 | Q16: =O16*P16 -> 0 | R16: =O16+Q16 -> 957 | S16: =R16*K16/J16 -> 18805.05 | T16: KALYAN | U16: DOHA | V16: GIFT | W16: KIRTI
A17: 16 | B17: 43869 | C17: Gold | D17: HBKGNB002614 | E17: 800110221945 | F17: PENDANT | G17: 1 | H17: 22K | I17: 1.74 | J17: 181 | K17: =J17*19.65 -> 3556.65 | L17: 1.71 | M17: 50.87 | N17: =M17/(I17*J17) -> 0.16152283 | O17: =(I17*J17)+M17 -> 365.81 | P17: 0 | Q17: =O17*P17 -> 0 | R17: =O17+Q17 -> 365.81 | S17: =R17*K17/J17 -> 7188.1665 | T17: KALYAN | U17: DOHA | V17: GIFT | W17: KIRTI
A18: 17 | B18: 44053 | C18: Gold | D18: QMDLC10300024044 | E18: 131000517089 | F18: COIN | G18: 1 | H18: 22K | I18: 4 | J18: 234.5 | K18: =J18*20.25 -> 4748.625 | L18: 4 | M18: 6 | N18: =M18/(I18*J18) -> 0.0063965885 | O18: =(I18*J18)+M18 -> 944 | P18: 0 | Q18: =O18*P18 -> 0 | R18: =O18+Q18 -> 944 | S18: =R18*K18/J18 -> 19116 | T18: MALABAR | U18: DOHA | V18: SELF | W18: ARTI
A19: 18 | B19: 44053 | C19: Gold | D19: QMDLC10300024044 | E19: 131000517135 | F19: COIN | G19: 2 | H19: 22K | I19: 4 | J19: 234.5 | K19: =J19*20.25 -> 4748.625 | L19: 4 | M19: 6 | N19: =M19/(I19*J19) -> 0.0063965885 | O19: =(I19*J19)+M19 -> 944 | P19: 0 | Q19: =O19*P19 -> 0 | R19: =O19+Q19 -> 944 | S19: =R19*K19/J19 -> 19116 | T19: MALABAR | U19: DOHA | V19: SELF | W19: ARTI
A20: 19 | B20: 44232 | C20: Gold | D20: HBKGPB001225 | E20: 800110342105 | F20: CHAIN | G20: 1 | H20: 22K | I20: 8.68 | J20: 208 | K20: =J20*20.05 -> 4170.4 | L20: 8.68 | M20: 135.56 | N20: =M20/(I20*J20) -> 0.07508419 | O20: =(I20*J20)+M20 -> 1941 | P20: 0 | Q20: =O20*P20 -> 0 | R20: =O20+Q20 -> 1941 | S20: =R20*K20/J20 -> 38917.05 | T20: KALYAN | U20: DOHA | V20: SELF | W20: HARSHI
A21: 20 | B21: 44510 | C21: SILVER | D21: PAPA65000 | E21: S001 | F21: BLOCK | G21: 1 | H21: 24K | I21: 1000 | J21: =K21/20 -> 3.25 | K21: 65 | L21: 1000 | M21: 0 | N21: =M21/(I21*J21) -> 0 | O21: =(I21*J21)+M21 -> 3250 | P21: 0 | Q21: =O21*P21 -> 0 | R21: =O21+Q21 -> 3250 | S21: =R21*K21/J21 -> 65000 | T21: PAPA_KNP | U21: DOHA | V21: SELF | W21: VIRAAJ
A22: 21 | B22: 44685 | C22: Gold | D22: HQ CS-041392 | E22: BAN002886 | F22: BANGLE | G22: 2 | H22: 22K | I22: 35.08 | J22: 205.7 | K22: =J22*20.95 -> 4309.415 | L22: 35.08 | M22: 1900 | N22: =M22/(I22*J22) -> 0.26330537 | O22: =(I22*J22)+M22 -> 9115.956 | P22: 0 | Q22: 32.005434 | R22: =O22+Q22 -> 9147.9614 | S22: =R22*K22/J22 -> 191649.79 | T22: GRK GOLD | U22: SIN | V22: SELF | W22: ARTI
A23: 22 | B23: 44685 | C23: Gold | D23: HQ CS-041392 | E23: RIN012799 | F23: RING | G23: 1 | H23: 22K | I23: 0 | J23: 0 | K23: =J23*20.95 -> 0 | L23: 0 | M23: 0 | N23: 0 | O23: =(I23*J23)+M23 -> 0 | P23: 0 | Q23: 0 | R23: =O23+Q23 -> 0 | S23: 0 | T23: SOLD | U23: SIN | V23: SELF | W23: VINEET
A24: 23 | B24: 44685 | C24: SILVER | D24: HQ CS-041392 | E24: SIL001894 | F24: COW | G24: 1 | H24: 20k | I24: 17.88 | J24: 7.92 | K24: =J24*20.95 -> 165.924 | L24: 17.88 | M24: 35 | N24: =M24/(I24*J24) -> 0.24715838 | O24: =(I24*J24)+M24 -> 176.6096 | P24: 0 | Q24: =O24*P24 -> 0 | R24: =O24+Q24 -> 176.6096 | S24: =R24*K24/J24 -> 3699.9711 | T24: GRK GOLD | U24: SIN | V24: SELF | W24: ARTI
A25: 24 | B25: 44823 | C25: Gold | D25: WETGRC002981 | E25: 800110460272 | F25: EARRING | G25: 1 | H25: 22K | I25: 2.2 | J25: 195.5 | K25: =J25*21.9 -> 4281.45 | L25: 2.2 | M25: 84.9 | N25: =M25/(I25*J25) -> 0.19739595 | O25: =(I25*J25)+M25 -> 515 | P25: 0 | Q25: =O25*P25 -> 0 | R25: =O25+Q25 -> 515 | S25: =R25*K25/J25 -> 11278.5 | T25: KALYAN | U25: DOHA | V25: SELF | W25: ARTI
A26: 25 | B26: 44837 | C26: Gold | D26: QMDLC10200056539 | E26: 131001029667 | F26: EARRING | G26: 1 | H26: 22K | I26: 9.86 | J26: 200 | K26: =J26*22.5 -> 4500 | L26: 9.8 | M26: 508 | N26: =M26/(I26*J26) -> 0.25760649 | O26: =(I26*J26)+M26 -> 2480 | P26: 0 | Q26: =O26*P26 -> 0 | R26: =O26+Q26 -> 2480 | S26: =R26*K26/J26 -> 55800 | T26: MALABAR | U26: DOHA | V26: SELF | W26: ARTI
A27: 26 | B27: 44878 | C27: Gold | D27: WETGRB003312 | E27: 800110463172 | F27: CHAIN | G27: 1 | H27: 22K | I27: 20.54 | J27: 199.01 | K27: =J27*22.12 -> 4402.1012 | L27: =I27 -> 20.54 | M27: 422.33 | N27: =M27/(I27*J27) -> 0.10331814 | O27: =(I27*J27)+M27 -> 4509.9954 | P27: 0 | Q27: =O27*P27 -> 0 | R27: =O27+Q27 -> 4509.9954 | S27: =R27*K27/J27 -> 99761.098 | T27: KALYAN | U27: DOHA | V27: SELF | W27: VINEET
A28: 27 | B28: 45489 | C28: Gold | D28: BRVGTC001587 | E28: 800110574408 | F28: PENDANT | G28: 1 | H28: 22K | I28: 2.23 | J28: 280 | K28: =J28*22.92 -> 6417.6 | L28: 2.23 | M28: 111.6 | N28: =M28/(I28*J28) -> 0.17873158 | O28: =(I28*J28)+M28 -> 736 | P28: 0 | Q28: =O28*P28 -> 0 | R28: =O28+Q28 -> 736 | S28: =R28*K28/J28 -> 16869.12 | T28: KALYAN | U28: DOHA | V28: SELF | W28: HARSHI
A29: 28 | B29: 45513 | C29: Gold | D29: ALIGTSD00028 | E29: *** | F29: CHAIN | G29: 1 | H29: 22K | I29: 11.86 | J29: 279 | K29: 6425 | L29: 11.86 | M29: 487.0204 | N29: =M29/(I29*J29) -> 0.14718321 | O29: =(I29*J29)+M29 -> 3795.9604 | P29: 0 | Q29: 113.5 | R29: =O29+Q29 -> 3909.4604 | S29: =R29*K29/J29 -> 90029.688 | T29: KALYAN | U29: ALIGARH | V29: SELF | W29: VIRAAJ
A30: 29 | B30: 45569 | C30: Gold | D30: WETGTB001710 | E30: 800110581838 | F30: RING | G30: 1 | H30: 22K | I30: 8.26 | J30: 302.5 | K30: =J30*23.05 -> 6972.625 | L30: 8.26 | M30: 293.72 | N30: =M30/(I30*J30) -> 0.11755148 | O30: =(I30*J30)+M30 -> 2792.37 | P30: 0 | Q30: 0 | R30: =O30+Q30 -> 2792.37 | S30: =R30*K30/J30 -> 64364.128 | T30: GRK GOLD | U30: DOHA | V30: SELF | W30: VINEET
A31: 30 | B31: 45569 | C31: Gold | D31: WETGTB001710 | E31: 800710004990 | F31: PENDANT | G31: 1 | H31: 22K | I31: 14.38 | J31: 302.5 | K31: =J31*23.05 -> 6972.625 | L31: 14.38 | M31: 696.32 | N31: =M31/(I31*J31) -> 0.1600754 | O31: =(I31*J31)+M31 -> 5046.27 | P31: 0 | Q31: 0 | R31: =O31+Q31 -> 5046.27 | S31: =R31*K31/J31 -> 116316.52 | T31: GRK GOLD | U31: DOHA | V31: SELF | W31: VINEET
A32: 31 | B32: 45583 | C32: Gold | D32: BRVGTB001156 | E32: 800110545356 | F32: NECKLACE | G32: 1 | H32: 22K | I32: 45.25 | J32: 307 | K32: =J32*23.92 -> 7343.44 | L32: 45.25 | M32: 2640 | N32: =M32/(I32*J32) -> 0.19004085 | O32: =(I32*J32)+M32 -> 16531.75 | P32: 0 | Q32: =O32*P32 -> 0 | R32: =O32+Q32 -> 16531.75 | S32: =R32*K32/J32 -> 395439.46 | T32: KALYAN | U32: DOHA | V32: SELF | W32: ARTI

Sheet Asset
A1: Sr. | B1: Asset_Details | C1: Datadate | D1: Perchase_Date | E1: Perchase_Value | F1: Insurance_Date | G1: Ins_Valid_from | H1: Ins_Valid_To | I1: Insurance_Amount | J1: Insurance_Renewal_Date | K1: Obj_IDV | L1: Expected_Amount
A2: 1 | B2: Hyundai Car - DL9CAQ6746 | C2: =D2 -> 43383 | D2: 43383 | E2: 751000 | F2: 43383 | G2: =D2 -> 43383 | H2: 43747.25 | I2: 36013 | J2: =H2-7 -> 43740.25 | K2: 667276 | L2: =E2*90% -> 675900
A3: 2 | B3: Hyundai Car - DL9CAQ6746 | C3: =J2 -> 43740.25 | D3: 43383 | E3: =E2 -> 751000 | F3: 43747.25 | G3: =G2+365 -> 43748 | H3: =G3+365 -> 44113 | I3: 13291 | J3: =H3-7 -> 44106 | K3: 596778 | L3: =L2*90% -> 608310
A4: 2 | B4: Mitshubishi Car | C4: 44753 | D4: 44753 | E4: =70000*21.6 -> 1512000 | F4: 44613 | G4: =F4 -> 44613 | H4: =G4+365 -> 44978 | I4: =1800*21.6 -> 38880 | J4: =H4-7 -> 44971 | K4: =75000*21.6 -> 1620000 | L4: =E4 -> 1512000

Sheet SIP_Transations
A1: Scheme_Name | B1: ISIN Code | C1: Asset_Sub_Category | D1: SIP_Trnx_Type | E1: Folio_No. | F1: SIP_Trnx_Date | G1: Num_Units | H1: SIP_Buy_Price | I1: SIP_Invst_Amount
A2: KOTAK FLEXICAP FUND(G) | B2: INF174K01336 | C2: Flexi Cap Fund | D2: SIP | E2: 4343476/67 | F2: 43110 | G2: 9.16 | H2: 33.892 | I2: 310
A3: KOTAK FLEXICAP FUND(G) | B3: INF174K01336 | C3: Flexi Cap Fund | D3: STP | E3: 4343476/67 | F3: 43153 | G3: 31.06 | H3: 32.196 | I3: 1000
A4: KOTAK FLEXICAP FUND(G) | B4: INF174K01336 | C4: Flexi Cap Fund | D4: STP | E4: 4343476/67 | F4: 43154 | G4: 30.707 | H4: 32.566 | I4: 1000
A5: KOTAK FLEXICAP FUND(G) | B5: INF174K01336 | C5: Flexi Cap Fund | D5: STP | E5: 4343476/67 | F5: 43157 | G5: 30.346 | H5: 32.953 | I5: 1000
A6: KOTAK FLEXICAP FUND(G) | B6: INF174K01336 | C6: Flexi Cap Fund | D6: STP | E6: 4343476/67 | F6: 43158 | G6: 30.418 | H6: 32.875 | I6: 1000
A7: KOTAK FLEXICAP FUND(G) | B7: INF174K01336 | C7: Flexi Cap Fund | D7: STP | E7: 4343476/67 | F7: 43159 | G7: 30.553 | H7: 32.73 | I7: 1000
A8: KOTAK FLEXICAP FUND(G) | B8: INF174K01336 | C8: Flexi Cap Fund | D8: STP | E8: 4343476/67 | F8: 43160 | G8: 30.713 | H8: 32.559 | I8: 1000
A9: KOTAK FLEXICAP FUND(G) | B9: INF174K01336 | C9: Flexi Cap Fund | D9: STP | E9: 4343476/67 | F9: 43164 | G9: 61.94 | H9: 32.289 | I9: 2000
A10: KOTAK FLEXICAP FUND(G) | B10: INF174K01336 | C10: Flexi Cap Fund | D10: STP | E10: 4343476/67 | F10: 43165 | G10: 31.248 | H10: 32.002 | I10: 1000
A11: KOTAK FLEXICAP FUND(G) | B11: INF174K01336 | C11: Flexi Cap Fund | D11: STP | E11: 4343476/67 | F11: 43166 | G11: 31.595 | H11: 31.651 | I11: 1000
A12: KOTAK FLEXICAP FUND(G) | B12: INF174K01336 | C12: Flexi Cap Fund | D12: STP | E12: 4343476/67 | F12: 43167 | G12: 31.322 | H12: 31.926 | I12: 1000
A13: KOTAK FLEXICAP FUND(G) | B13: INF174K01336 | C13: Flexi Cap Fund | D13: STP | E13: 4343476/67 | F13: 43168 | G13: 31.381 | H13: 31.866 | I13: 1000
... A97: KOTAK FLEXICAP FUND(G) | B97: INF174K01336 | C97: Flexi Cap Fund | D97: STP | E97: 4343476/67 | F97: 43293 | G97: 29.692 | H97: 33.679 | I97: 1000
A98: ADITYA BIRLA SL TAX RELIEF '96(G) | B98: INF209K01108 | C98: Equity - ELSS | D98: SIP | E98: 1019420000 | F98: 43322 | G98: 77.28 | H98: 32.35 | I98: 2500
A99: NIPPON INDIA PHARMA FUND(G) | B99: INF204K01968 | C99: Equity - Sectoral Fund - Pharma & Health Care | D99: PUR | E99: 499203639934 | F99: 43346 | G99: 123.135 | H99: 162.423 | I99: 20000
A100: KOTAK LOW DURATION FUND(G) | B100: INF178L01202 | C100: Debt - Low Duration Fund | D100: Additional Purchase | E100: 4343476/67 | F100: 43347 | G100: 6.872 | H100: 2182.682 | I100: 14999
A101: ADITYA BIRLA SL TAX RELIEF '96(G) | B101: INF209K01108 | C101: Equity - ELSS | D101: STP | E101: 1019420000 | F101: 43364 | G101: 75.543 | H101: 31.77 | I101: 2400
A102: ADITYA BIRLA SL TAX RELIEF '96(G) | B102: INF209K01108 | C102: Equity - ELSS | D102: STP | E102: 1019420000 | F102: 43395 | G102: 83.045 | H102: 28.9 | I102: 2400
A103: ADITYA BIRLA SL TAX RELIEF '96(G) | B103: INF209K01108 | C103: Equity - ELSS | D103: STP | E103: 1019420000 | F103: 43426 | G103: 80.618 | H103: 29.77 | I103: 2400
A104: ADITYA BIRLA SL TAX RELIEF '96(G) | B104: INF209K01108 | C104: Equity - ELSS | D104: STP | E104: 1019420000 | F104: 43455 | G104: 78.585 | H104: 30.54 | I104: 2400
A105: ADITYA BIRLA SL TAX RELIEF '96(G) | B105: INF209K01108 | C105: Equity - ELSS | D105: STP | E105: 1019420000 | F105: 43486 | G105: 78.483 | H105: 30.58 | I105: 2400
A106: ADITYA BIRLA SL TAX RELIEF '96(G) | B106: INF209K01108 | C106: Equity - ELSS | D106: STP | E106: 1019420000 | F106: 43517 | G106: 80.999 | H106: 29.63 | I106: 2400
A107: ADITYA BIRLA SL TAX RELIEF '96(G) | B107: INF209K01108 | C107: Equity - ELSS | D107: STP | E107: 1019420000 | F107: 43546 | G107: 29.152 | H107: 31.11 | I107: 907
A108: KOTAK FLEXICAP FUND(G) | B108: INF174K01336 | C108: Flexi Cap Fund | D108: Additional Purchase | E108: 4343476/67 | F108: 43955 | G108: 863.916 | H108: 28.938 | I108: 25000
A109: KOTAK LOW DURATION FUND(G) | B109: INF178L01202 | C109: Debt - Low Duration Fund | D109: Additional Purchase | E109: 4343476/67 | F109: 43955 | G109: 2.03 | H109: 2462.528 | I109: 4999
A110: NIPPON INDIA PHARMA FUND(G) | B110: INF204K01968 | C110: Equity - Sectoral Fund - Pharma & Health Care | D110: PUR | E110: 499203639934 | F110: 43955 | G110: 110.381 | H110: 181.191 | I110: 20000
A111: ADITYA BIRLA SL MNC FUND-REG(G) | B111: INF209K01322 | C111: Equity - Thematic Fund - MNC | D111: Additional Purchase | E111: 1019420000 | F111: 44027 | G111: 6.903 | H111: 724.25 | I111: 5000
A112: KOTAK FOCUSED EQUITY FUND-REG(G) | B112: INF174KA1EK3 | C112: Equity - Focused Fund | D112: Additional Purchase | E112: 4343476/67 | F112: 44027 | G112: 515.226 | H112: 9.704 | I112: 5000
A113: NIPPON INDIA INCOME FUND(G) | B113: INF204K01CL1 | C113: Debt - Medium to Long Duration Fund | D113: PUR | E113: 499203639934 | F113: 44027 | G113: 71.344 | H113: 70.079 | I113: 5000
A114: NIPPON INDIA PHARMA FUND(G) | B114: INF204K01968 | C114: Equity - Sectoral Fund - Pharma & Health Care | D114: PUR | E114: 499203639934 | F114: 44027 | G114: 25.83 | H114: 193.566 | I114: 5000
A115: ADITYA BIRLA SL MNC FUND-REG(G) | B115: INF209K01322 | C115: Equity - Thematic Fund - MNC | D115: SIP | E115: 1019420000 | F115: 44060 | G115: 6.612 | H115: 756.18 | I115: 5000
A116: KOTAK FOCUSED EQUITY FUND-REG(G) | B116: INF174KA1EK3 | C116: Equity - Focused Fund | D116: SIP | E116: 4343476/67 | F116: 44060 | G116: 491.376 | H116: 10.175 | I116: 5000
A117: NIPPON INDIA GOLD SAVINGS FUND(G) | B117: INF204K01KN0 | C117: FoFs (Domestic / Overseas ) - Gold | D117: Systematic Investment | E117: 499203639934 | F117: 44060 | G117: 46.089 | H117: 21.696 | I117: 1000
A118: NIPPON INDIA INCOME FUND(G) | B118: INF204K01CL1 | C118: Debt - Medium to Long Duration Fund | D118: Systematic Investment | E118: 499203639934 | F118: 44060 | G118: 57.446 | H118: 69.627 | I118: 4000
A119: NIPPON INDIA PHARMA FUND(G) | B119: INF204K01968 | C119: Equity - Sectoral Fund - Pharma & Health Care | D119: Systematic Investment | E119: 499203639934 | F119: 44060 | G119: 22.407 | H119: 223.138 | I119: 5000
A120: ADITYA BIRLA SL MNC FUND-REG(G) | B120: INF209K01322 | C120: Equity - Thematic Fund - MNC | D120: SIP | E120: 1019420000 | F120: 44089 | G120: 6.252 | H120: 799.73 | I120: 5000
A121: KOTAK FOCUSED EQUITY FUND-REG(G) | B121: INF174KA1EK3 | C121: Equity - Focused Fund | D121: SIP | E121: 4343476/67 | F121: 44089 | G121: 478.353 | H121: 10.452 | I121: 5000
A122: NIPPON INDIA GOLD SAVINGS FUND(G) | B122: INF204K01KN0 | C122: FoFs (Domestic / Overseas ) - Gold | D122: Systematic Investment | E122: 499203639934 | F122: 44089 | G122: 46.697 | H122: 21.414 | I122: 1000
A123: NIPPON INDIA INCOME FUND(G) | B123: INF204K01CL1 | C123: Debt - Medium to Long Duration Fund | D123: Systematic Investment | E123: 499203639934 | F123: 44089 | G123: 57.563 | H123: 69.486 | I123: 4000
A124: NIPPON INDIA PHARMA FUND(G) | B124: INF204K01968 | C124: Equity - Sectoral Fund - Pharma & Health Care | D124: Systematic Investment | E124: 499203639934 | F124: 44089 | G124: 22.525 | H124: 221.966 | I124: 5000
A125: ADITYA BIRLA SL MNC FUND-REG(G) | B125: INF209K01322 | C125: Equity - Thematic Fund - MNC | D125: SIP | E125: 1019420000 | F125: 44119 | G125: 6.597 | H125: 757.91 | I125: 5000
A126: KOTAK FOCUSED EQUITY FUND-REG(G) | B126: INF174KA1EK3 | C126: Equity - Focused Fund | D126: SIP | E126: 4343476/67 | F126: 44119 | G126: 471.853 | H126: 10.596 | I126: 5000
A127: NIPPON INDIA GOLD SAVINGS FUND(G) | B127: INF204K01KN0 | C127: FoFs (Domestic / Overseas ) - Gold | D127: Systematic Investment | E127: 499203639934 | F127: 44119 | G127: 48.04 | H127: 20.815 | I127: 1000
A128: NIPPON INDIA INCOME FUND(G) | B128: INF204K01CL1 | C128: Debt - Medium to Long Duration Fund | D128: Systematic Investment | E128: 499203639934 | F128: 44119 | G128: 56.757 | H128: 70.472 | I128: 4000
A129: NIPPON INDIA PHARMA FUND(G) | B129: INF204K01968 | C129: Equity - Sectoral Fund - Pharma & Health Care | D129: Systematic Investment | E129: 499203639934 | F129: 44119 | G129: 22.053 | H129: 226.716 | I129: 5000
A130: ADITYA BIRLA SL MNC FUND-REG(G) | B130: INF209K01322 | C130: Equity - Thematic Fund - MNC | D130: SIP | E130: 1019420000 | F130: 44152 | G130: 6.297 | H130: 794.02 | I130: 5000
A131: KOTAK FOCUSED EQUITY FUND-REG(G) | B131: INF174KA1EK3 | C131: Equity - Focused Fund | D131: SIP | E131: 4343476/67 | F131: 44152 | G131: 437.577 | H131: 11.426 | I131: 5000
A132: NIPPON INDIA GOLD SAVINGS FUND(G) | B132: INF204K01KN0 | C132: FoFs (Domestic / Overseas ) - Gold | D132: Systematic Investment | E132: 499203639934 | F132: 44152 | G132: 47.829 | H132: 20.907 | I132: 1000
A133: NIPPON INDIA INCOME FUND(G) | B133: INF204K01CL1 | C133: Debt - Medium to Long Duration Fund | D133: Systematic Investment | E133: 499203639934 | F133: 44152 | G133: 56.372 | H133: 70.954 | I133: 4000
A134: NIPPON INDIA PHARMA FUND(G) | B134: INF204K01968 | C134: Equity - Sectoral Fund - Pharma & Health Care | D134: Systematic Investment | E134: 499203639934 | F134: 44152 | G134: 21.831 | H134: 229.021 | I134: 5000
A135: ADITYA BIRLA SL MNC FUND-REG(G) | B135: INF209K01322 | C135: Equity - Thematic Fund - MNC | D135: SIP | E135: 1019420000 | F135: 44180 | G135: 5.914 | H135: 845.45 | I135: 5000
A136: KOTAK FOCUSED EQUITY FUND-REG(G) | B136: INF174KA1EK3 | C136: Equity - Focused Fund | D136: SIP | E136: 4343476/67 | F136: 44180 | G136: 415.055 | H136: 12.046 | I136: 5000
A137: NIPPON INDIA GOLD SAVINGS FUND(G) | B137: INF204K01KN0 | C137: FoFs (Domestic / Overseas ) - Gold | D137: Systematic Investment | E137: 499203639934 | F137: 44180 | G137: 49.727 | H137: 20.109 | I137: 1000
A138: NIPPON INDIA INCOME FUND(G) | B138: INF204K01CL1 | C138: Debt - Medium to Long Duration Fund | D138: Systematic Investment | E138: 499203639934 | F138: 44180 | G138: 56.164 | H138: 71.217 | I138: 4000
A139: NIPPON INDIA PHARMA FUND(G) | B139: INF204K01968 | C139: Equity - Sectoral Fund - Pharma & Health Care | D139: Systematic Investment | E139: 499203639934 | F139: 44180 | G139: 20.352 | H139: 245.667 | I139: 5000
A140: ADITYA BIRLA SL MNC FUND-REG(G) | B140: INF209K01322 | C140: Equity - Thematic Fund - MNC | D140: SIP | E140: 1019420000 | F140: 44211 | G140: 5.603 | H140: 892.31 | I140: 5000
A141: KOTAK FOCUSED EQUITY FUND-REG(G) | B141: INF174KA1EK3 | C141: Equity - Focused Fund | D141: SIP | E141: 4343476/67 | F141: 44211 | G141: 388.27 | H141: 12.877 | I141: 5000
A142: NIPPON INDIA GOLD SAVINGS FUND(G) | B142: INF204K01KN0 | C142: FoFs (Domestic / Overseas ) - Gold | D142: Systematic Investment | E142: 499203639934 | F142: 44211 | G142: 49.497 | H142: 20.202 | I142: 1000
A143: NIPPON INDIA INCOME FUND(G) | B143: INF204K01CL1 | C143: Debt - Medium to Long Duration Fund | D143: Systematic Investment | E143: 499203639934 | F143: 44211 | G143: 56.273 | H143: 71.079 | I143: 4000
A144: NIPPON INDIA PHARMA FUND(G) | B144: INF204K01968 | C144: Equity - Sectoral Fund - Pharma & Health Care | D144: Systematic Investment | E144: 499203639934 | F144: 44211 | G144: 19.384 | H144: 257.931 | I144: 5000
A145: ADITYA BIRLA SL MNC FUND-REG(G) | B145: INF209K01322 | C145: Equity - Thematic Fund - MNC | D145: SIP | E145: 1019420000 | F145: 44244 | G145: 5.526 | H145: 904.73 | I145: 5000
A146: KOTAK FOCUSED EQUITY FUND-REG(G) | B146: INF174KA1EK3 | C146: Equity - Focused Fund | D146: SIP | E146: 4343476/67 | F146: 44244 | G146: 360.109 | H146: 13.884 | I146: 5000
A147: NIPPON INDIA GOLD SAVINGS FUND(G) | B147: INF204K01KN0 | C147: FoFs (Domestic / Overseas ) - Gold | D147: Systematic Investment | E147: 499203639934 | F147: 44244 | G147: 52.577 | H147: 19.019 | I147: 1000
A148: NIPPON INDIA INCOME FUND(G) | B148: INF204K01CL1 | C148: Debt - Medium to Long Duration Fund | D148: Systematic Investment | E148: 499203639934 | F148: 44244 | G148: 57.125 | H148: 70.018 | I148: 4000
A149: NIPPON INDIA PHARMA FUND(G) | B149: INF204K01968 | C149: Equity - Sectoral Fund - Pharma & Health Care | D149: Systematic Investment | E149: 499203639934 | F149: 44244 | G149: 19.74 | H149: 253.284 | I149: 5000
A150: ADITYA BIRLA SL MNC FUND-REG(G) | B150: INF209K01322 | C150: Equity - Thematic Fund - MNC | D150: SIP | E150: 1019420000 | F150: 44272 | G150: 5.519 | H150: 905.96 | I150: 5000
A151: KOTAK FOCUSED EQUITY FUND-REG(G) | B151: INF174KA1EK3 | C151: Equity - Focused Fund | D151: SIP | E151: 4343476/67 | F151: 44272 | G151: 371.177 | H151: 13.47 | I151: 5000
A152: NIPPON INDIA GOLD SAVINGS FUND(G) | B152: INF204K01KN0 | C152: FoFs (Domestic / Overseas ) - Gold | D152: Systematic Investment | E152: 499203639934 | F152: 44272 | G152: 54.444 | H152: 18.367 | I152: 1000
A153: NIPPON INDIA INCOME FUND(G) | B153: INF204K01CL1 | C153: Debt - Medium to Long Duration Fund | D153: Systematic Investment | E153: 499203639934 | F153: 44272 | G153: 57.532 | H153: 69.523 | I153: 4000
A154: NIPPON INDIA PHARMA FUND(G) | B154: INF204K01968 | C154: Equity - Sectoral Fund - Pharma & Health Care | D154: Systematic Investment | E154: 499203639934 | F154: 44272 | G154: 20.588 | H154: 242.846 | I154: 5000
A155: ADITYA BIRLA SL MNC FUND-REG(G) | B155: INF209K01322 | C155: Equity - Thematic Fund - MNC | D155: SIP | E155: 1019420000 | F155: 44305 | G155: 5.642 | H155: 886.16 | I155: 5000
A156: KOTAK FOCUSED EQUITY FUND-REG(G) | B156: INF174KA1EK3 | C156: Equity - Focused Fund | D156: SIP | E156: 4343476/67 | F156: 44305 | G156: 379.718 | H156: 13.167 | I156: 5000
A157: NIPPON INDIA GOLD SAVINGS FUND(G) | B157: INF204K01KN0 | C157: FoFs (Domestic / Overseas ) - Gold | D157: Systematic Investment | E157: 499203639934 | F157: 44305 | G157: 51.335 | H157: 19.479 | I157: 1000
A158: NIPPON INDIA INCOME FUND(G) | B158: INF204K01CL1 | C158: Debt - Medium to Long Duration Fund | D158: Systematic Investment | E158: 499203639934 | F158: 44305 | G158: 56.621 | H158: 70.642 | I158: 4000
A159: NIPPON INDIA PHARMA FUND(G) | B159: INF204K01968 | C159: Equity - Sectoral Fund - Pharma & Health Care | D159: Systematic Investment | E159: 499203639934 | F159: 44305 | G159: 18.482 | H159: 270.517 | I159: 5000
A160: ADITYA BIRLA SL MNC FUND-REG(G) | B160: INF209K01322 | C160: Equity - Thematic Fund - MNC | D160: SIP | E160: 1019420000 | F160: 44334 | G160: 5.495 | H160: 909.93 | I160: 5000
A161: NIPPON INDIA GOLD SAVINGS FUND(G) | B161: INF204K01KN0 | C161: FoFs (Domestic / Overseas ) - Gold | D161: Systematic Investment | E161: 499203639934 | F161: 44334 | G161: 50.668 | H161: 19.736 | I161: 1000
A162: NIPPON INDIA INCOME FUND(G) | B162: INF204K01CL1 | C162: Debt - Medium to Long Duration Fund | D162: Systematic Investment | E162: 499203639934 | F162: 44334 | G162: 56.159 | H162: 71.223 | I162: 4000
A163: NIPPON INDIA PHARMA FUND(G) | B163: INF204K01968 | C163: Equity - Sectoral Fund - Pharma & Health Care | D163: Systematic Investment | E163: 499203639934 | F163: 44334 | G163: 17.442 | H163: 286.647 | I163: 5000
A164: ADITYA BIRLA SL SHORT TERM FUND(G) | B164: INF209K01942 | C164: Debt - Short Duration Fund | D164: Switch-In | E164: 1019420000 | F164: 44344 | G164: 578.667 | H164: 37.007 | I164: 21415
A165: KOTAK FOCUSED EQUITY FUND-REG(G) | B165: INF174KA1EK3 | C165: Equity - Focused Fund | D165: Switch-In | E165: 4343476/67 | F165: 44344 | G165: 355.525 | H165: 14.063 | I165: 5000
A166: KOTAK LOW DURATION FUND(G) | B166: INF178L01202 | C166: Debt - Low Duration Fund | D166: Switch-In | E166: 4343476/67 | F166: 44344 | G166: 7.637 | H166: 2649.494 | I166: 20234
A167: ADITYA BIRLA SL MNC FUND-REG(G) | B167: INF209K01322 | C167: Equity - Thematic Fund - MNC | D167: SIP | E167: 1019420000 | F167: 44364 | G167: 5.253 | H167: 951.7 | I167: 5000
A168: KOTAK FOCUSED EQUITY FUND-REG(G) | B168: INF174KA1EK3 | C168: Equity - Focused Fund | D168: SIP | E168: 4343476/67 | F168: 44364 | G168: 342.097 | H168: 14.615 | I168: 5000
A169: NIPPON INDIA GOLD SAVINGS FUND(G) | B169: INF204K01KN0 | C169: FoFs (Domestic / Overseas ) - Gold | D169: Systematic Investment | E169: 499203639934 | F169: 44364 | G169: 51.588 | H169: 19.383 | I169: 1000
A170: NIPPON INDIA INCOME FUND(G) | B170: INF204K01CL1 | C170: Debt - Medium to Long Duration Fund | D170: Systematic Investment | E170: 499203639934 | F170: 44364 | G170: 56.167 | H170: 71.212 | I170: 4000
A171: NIPPON INDIA PHARMA FUND(G) | B171: INF204K01968 | C171: Equity - Sectoral Fund - Pharma & Health Care | D171: Systematic Investment | E171: 499203639934 | F171: 44364 | G171: 16.943 | H171: 295.088 | I171: 5000
A172: NIPPON INDIA GOLD SAVINGS FUND(G) | B172: INF204K01KN0 | C172: FoFs (Domestic / Overseas ) - Gold | D172: Systematic Investment | E172: 499203639934 | F172: 44392 | G172: 50.83 | H172: 19.6726 | I172: 1000
A173: NIPPON INDIA INCOME FUND(G) | B173: INF204K01CL1 | C173: Debt - Medium to Long Duration Fund | D173: Systematic Investment | E173: 499203639934 | F173: 44392 | G173: 56.246 | H173: 71.1125 | I173: 4000
A174: NIPPON INDIA PHARMA FUND(G) | B174: INF204K01968 | C174: Equity - Sectoral Fund - Pharma & Health Care | D174: Systematic Investment | E174: 499203639934 | F174: 44392 | G174: 16.1 | H174: 310.5478 | I174: 5000
A175: ADITYA BIRLA SL MNC FUND-REG(G) | B175: INF209K01322 | C175: Equity - Thematic Fund - MNC | D175: SIP | E175: 1019420000 | F175: 44396 | G175: 5.128 | H175: 974.91 | I175: 5000
A176: KOTAK FOCUSED EQUITY FUND-REG(G) | B176: INF174KA1EK3 | C176: Equity - Focused Fund | D176: SIP | E176: 4343476/67 | F176: 44396 | G176: 335.239 | H176: 14.914 | I176: 5000
A177: Nippon India Gold Savings Fund(G) | B177: INF204K01KN0 | C177: FoFs (Domestic / Overseas ) - Gold | D177: Systematic Investment | E177: 499203639934 | F177: 44424 | G177: 52.341 | H177: 19.105 | I177: 999.949
A178: Nippon India Pharma Fund(G) | B178: INF204K01968 | C178: Equity - Sectoral Fund - Pharma & Health Care | D178: Systematic Investment | E178: 499203639934 | F178: 44424 | G178: 16.389 | H178: 305.065 | I178: 4999.704
A179: Nippon India Income Fund(G) | B179: INF204K01CL1 | C179: Debt - Medium to Long Duration Fund | D179: Systematic Investment | E179: 499203639934 | F179: 44425 | G179: 56.03 | H179: 71.387 | I179: 3999.814
A180: Aditya Birla SL MNC Fund-Reg(G) | B180: INF209K01322 | C180: Equity - Thematic Fund - MNC | D180: Systematic - Instalment 13/953 - via Internet | E180: 1019420000 | F180: 44428 | G180: 5.186 | H180: 964.12 | I180: 4999.926
A181: ADITYA BIRLA SL SHORT TERM FUND(G) | B181: INF209K01942 | C181: Debt - Short Duration Fund | D181: Systematic - To ABSL MNC Fund - Growth - Instalment 1/60 - via Internet | E181: 1019420000 | F181: 44428 | G181: 13.343 | H181: 37.472 | I181: 499.982
A182: Kotak Focused Equity Fund-Reg(G) | B182: INF174KA1EK3 | C182: Equity - Focused Fund | D182: Systematic - Instalment 13/953 - via Internet | E182: 4343476/67 | F182: 44428 | G182: 327.724 | H182: 15.256 | I182: 4999.757
A183: Kotak Low Duration Fund(G) | B183: INF178L01202 | C183: Debt - Low Duration Fund | D183: Systematic - To Kotak Flexicap Fund - Reg Growth - Instalment 1/98 - via Interne | E183: 4343476/67 | F183: 44428 | G183: 0.187 | H183: 2675.951 | I183: 500.403
...

Sheet GOLD RATE
A1: GRAM | B1: GOLD_RATE | C1: High | D1: Low | E1: Change | F1: G_DATADATE
A2: 1 GRAM GOLD 24K | B2: 174.66 | C2: =B2*100.1% -> 174.83466 | D2: =B2*99.9% -> 174.48534 | E2: =C2-D2 -> 0.34932 | F2: 43775
A3: 1 GRAM GOLD 24K | B3: 172.39 | C3: =B3*100.1% -> 172.56239 | D3: =B3*99.9% -> 172.21761 | E3: =C3-D3 -> 0.34478 | F3: 43776
A4: 1 GRAM GOLD 24K | B4: 170.94 | C4: =B4*100.1% -> 171.11094 | D4: =B4*99.9% -> 170.76906 | E4: =C4-D4 -> 0.34188 | F4: 43777
A5: 1 GRAM GOLD 24K | B5: 170.93 | C5: =B5*100.1% -> 171.10093 | D5: =B5*99.9% -> 170.75907 | E5: =C5-D5 -> 0.34186 | F5: 43779
A6: 1 GRAM GOLD 24K | B6: 170.35 | C6: =B6*100.1% -> 170.52035 | D6: =B6*99.9% -> 170.17965 | E6: =C6-D6 -> 0.3407 | F6: 43780
A7: 1 GRAM GOLD 24K | B7: 170.57 | C7: =B7*100.1% -> 170.74057 | D7: =B7*99.9% -> 170.39943 | E7: =C7-D7 -> 0.34114 | F7: 43781
A8: 1 GRAM GOLD 24K | B8: 171.33 | C8: =B8*100.1% -> 171.50133 | D8: =B8*99.9% -> 171.15867 | E8: =C8-D8 -> 0.34266 | F8: 43782
A9: 1 GRAM GOLD 24K | B9: 171.69 | C9: =B9*100.1% -> 171.86169 | D9: =B9*99.9% -> 171.51831 | E9: =C9-D9 -> 0.34338 | F9: 43783
A10: 1 GRAM GOLD 24K | B10: 171.52 | C10: =B10*100.1% -> 171.69152 | D10: =B10*99.9% -> 171.34848 | E10: =C10-D10 -> 0.34304 | F10: 43784
A11: 1 GRAM GOLD 24K | B11: 171.53 | C11: =B11*100.1% -> 171.70153 | D11: =B11*99.9% -> 171.35847 | E11: =C11-D11 -> 0.34306 | F11: 43786
A12: 1 GRAM GOLD 24K | B12: 172.04 | C12: =B12*100.1% -> 172.21204 | D12: =B12*99.9% -> 171.86796 | E12: =C12-D12 -> 0.34408 | F12: 43787
A13: 1 GRAM GOLD 24K | B13: 172.37 | C13: =B13*100.1% -> 172.54237 | D13: =B13*99.9% -> 172.19763 | E13: =C13-D13 -> 0.34474 | F13: 43788
... A78: GRAM 22K | B78: 165.13 | C78: =B78*100.1% -> 165.29513 | D78: =B78*99.9% -> 164.96487 | E78: =C78-D78 -> 0.33026 | F78: 43833

Sheet CURRENCY
A1: CURRENCY | B1: AGAINST_DOLLAR | C1: DOLLAR_AGAINST_CURRENCY | D1: C_DATADATE
A2: Indian Rupee | B2: 71.78379 | C2: 0.013930722 | D2: 43833
A3: Indian Rupee | B3: 71.3452 | C3: 0.01401636 | D3: 43832
A4: Indian Rupee | B4: 71.33559 | C4: 0.014018248 | D4: 43831
A5: Indian Rupee | B5: 71.30648 | C5: 0.014023971 | D5: 43830
A6: Indian Rupee | B6: 71.31903 | C6: 0.014021503 | D6: 43829
A7: Indian Rupee | B7: 71.45145 | C7: 0.013995517 | D7: 43826
A8: Indian Rupee | B8: 71.21529 | C8: 0.014041928 | D8: 43825
A9: Indian Rupee | B9: 71.26409 | C9: 0.014032313 | D9: 43824
A10: Indian Rupee | B10: 71.28851 | C10: 0.014027506 | D10: 43823
A11: Indian Rupee | B11: 71.21938 | C11: 0.014041122 | D11: 43822
A12: Indian Rupee | B12: 71.06456 | C12: 0.014071712 | D12: 43819
A13: Indian Rupee | B13: 71.18341 | C13: 0.014048217 | D13: 43818
... A131: Indian Rupee | B131: 68.57479 | C131: 0.014582618 | D131: 43654
A132: Qatari Riyal | B132: 3.63257 | C132: =1/B132 -> 0.27528719 | D132: 43833
A133: Qatari Riyal | B133: 3.64509 | C133: =1/B133 -> 0.27434165 | D133: 43832
A134: Qatari Riyal | B134: 3.6448 | C134: =1/B134 -> 0.27436348 | D134: 43831
A135: Qatari Riyal | B135: 3.64317 | C135: =1/B135 -> 0.27448623 | D135: 43830
A136: Qatari Riyal | B136: 3.63759 | C136: =1/B136 -> 0.27490729 | D136: 43829
A137: Qatari Riyal | B137: 3.63047 | C137: =1/B137 -> 0.27544643 | D137: 43828
A138: Qatari Riyal | B138: 3.63167 | C138: =1/B138 -> 0.27535542 | D138: 43826
A139: Qatari Riyal | B139: 3.64015 | C139: =1/B139 -> 0.27471395 | D139: 43825
A140: Qatari Riyal | B140: 3.63531 | C140: =1/B140 -> 0.2750797 | D140: 43824
A141: Qatari Riyal | B141: 3.63654 | C141: =1/B141 -> 0.27498666 | D141: 43823
A142: Qatari Riyal | B142: 3.63802 | C142: =1/B142 -> 0.27487479 | D142: 43822
A143: Qatari Riyal | B143: 3.64721 | C143: =1/B143 -> 0.27418218 | D143: 43821
... A284: Qatari Riyal | B284: 3.63988 | C284: =1/B284 -> 0.27473433 | D284: 43654

Sheet Asset_Type
A1: Invest_Type | B1: Asset_Type | C1: Asset_Group
A2: FD | B2: In-Hand India | C2: Current
A3: QAR-RD | B3: In-Hand Qatar | C3: Current
A4: MUTUAL FUND | B4: Investment | C4: Current
A5: LIC | B5: Investment | C5: Non-Current
A6: NRE-SBI | B6: In-Hand India | C6: Current
A7: PPF-SBI | B7: Investment | C7: Non-Current
A8: Gold | B8: Investment | C8: Current
A9: NRO-SBI | B9: In-Hand India | C9: Current
A10: SILVER | B10: Investment | C10: Current
A11: SAVING | B11: In-Hand India | C11: Current
A12: FD-SBI | B12: In-Hand India | C12: Current
... A15: STOCKS | B15: Investment | C15: Current

Sheet Budget Processing on Actual
B1: =B5 -> 1 | C1: =C5 -> 2 | D1: =D5 -> 3 | E1: =E5 -> 4 | F1: =F5 -> 5 | G1: =G5 -> 6 | H1: =H5 -> 7 | I1: =I5 -> 8 | ... M1: =M5 -> 12 | P1: Month | Q1: 1 | R1: 2 | S1: 3 | T1: 4 | U1: 5 | V1: 6 | W1: 7 | X1: 8 | Y1: 9 | Z1: 10 | AA1: 11 | AB1: 12 | AC1: TTL
A2: Closing Balance | B2: =B6-SUM(B7:B24) -> 0 | C2: =C6-SUM(C7:C24) -> 0 | D2: =D6-SUM(D7:D24) -> 0 | E2: =E6-SUM(E7:E24) -> 0 | F2: =F6-SUM(F7:F24) -> 0 | G2: =G6-SUM(G7:G24) -> 0 | H2: =H6-SUM(H7:H24) -> 0 | I2: =I6-SUM(I7:I24) -> 0 | ... M2: =M6-SUM(M7:M24) -> -1.0236341e-05 | P2: Closing Balance | Q2: =Q6-Q3 -> 0.029129348 | R2: =R6-R3 -> 0.0028679774 | S2: =S6-S3 -> 0.01514409 | T2: =T6-T3 -> 0.048431084 | U2: =U6-U3 -> 0.017545226 | V2: =V6-V3 -> 0.046087497 | W2: =W6-W3 -> 0.019826127 | X2: =X6-X3 -> 0.032876146 | ... AC2: =AC6-AC3 -> 0.021364961 | AD2: =$AD$6*AC2 -> 7556.0177
A3: Expenditure | B3: =B6-B2 -> 1 | C3: =C6-C2 -> 1 | D3: =D6-D2 -> 1 | E3: =E6-E2 -> 1 | F3: =F6-F2 -> 1 | G3: =G6-G2 -> 1 | H3: =H6-H2 -> 1 | I3: =I6-I2 -> 1 | ... M3: =M6-M2 -> 1.0000102 | P3: Expenditure | Q3: =SUM(Q7:Q24) -> 0.97087065 | R3: =SUM(R7:R24) -> 0.99713202 | S3: =SUM(S7:S24) -> 0.98485591 | T3: =SUM(T7:T24) -> 0.95156892 | U3: =SUM(U7:U24) -> 0.98245477 | V3: =SUM(V7:V24) -> 0.9539125 | W3: =SUM(W7:W24) -> 0.98017387 | X3: =SUM(X7:X24) -> 0.96712385 | ... AC3: =SUM(AC7:AC24) -> 0.97863504 | AD3: =$AD$6*AC3 -> 346107.98
A5: Month | B5: 1 | C5: 2 | D5: 3 | E5: 4 | F5: 5 | G5: 6 | H5: 7 | I5: 8 | J5: 9 | K5: 10 | L5: 11 | M5: 12 | N5: TTL | AD5: 29472
A6: SALARY | B6: 1 | C6: 1 | D6: 1 | E6: 1 | F6: 1 | G6: 1 | H6: 1 | I6: 1 | J6: 1 | K6: 1 | L6: 1 | M6: 1 | N6: =AVERAGE(B6:M6) -> 1 | P6: SALARY | Q6: =IF(B6>0%,($N6+B6)/2,B6) -> 1 | R6: =IF(C6>0%,($N6+C6)/2,C6) -> 1 | S6: =IF(D6>0%,($N6+D6)/2,D6) -> 1 | T6: =IF(E6>0%,($N6+E6)/2,E6) -> 1 | U6: =IF(F6>0%,($N6+F6)/2,F6) -> 1 | V6: =IF(G6>0%,($N6+G6)/2,G6) -> 1 | W6: =IF(H6>0%,($N6+H6)/2,H6) -> 1 | X6: =IF(I6>0%,($N6+I6)/2,I6) -> 1 | ... AB6: =IF(M6>0%,($N6+M6)/2,M6) -> 1 | AC6: =AVERAGE(Q6:AB6) -> 1 | AD6: =AD5*12 -> 353664
A7: RENT | B7: =VLOOKUP($A7,$A$26:$M$43,B$5+1,0) -> 0.32739308 | C7: =VLOOKUP($A7,$A$26:$M$43,C$5+1,0) -> 0.41377962 | D7: =VLOOKUP($A7,$A$26:$M$43,D$5+1,0) -> 0.27105907 | E7: =VLOOKUP($A7,$A$26:$M$43,E$5+1,0) -> 0.37996497 | F7: =VLOOKUP($A7,$A$26:$M$43,F$5+1,0) -> 0.29951406 | G7: =VLOOKUP($A7,$A$26:$M$43,G$5+1,0) -> 0.35486666 | H7: =VLOOKUP($A7,$A$26:$M$43,H$5+1,0) -> 0.24216397 | I7: =VLOOKUP($A7,$A$26:$M$43,I$5+1,0) -> 0.28344945 | ... M7: =VLOOKUP($A7,$A$26:$M$43,M$5+1,0) -> 0.28064975 | N7: =AVERAGE(B7:M7) -> 0.32748241 | P7: RENT | Q7: =IF(B7>0%,($N7+B7)/2,B7) -> 0.32743775 | R7: =IF(C7>0%,($N7+C7)/2,C7) -> 0.37063102 | S7: =IF(D7>0%,($N7+D7)/2,D7) -> 0.29927074 | T7: =IF(E7>0%,($N7+E7)/2,E7) -> 0.35372369 | U7: =IF(F7>0%,($N7+F7)/2,F7) -> 0.31349823 | V7: =IF(G7>0%,($N7+G7)/2,G7) -> 0.34117453 | W7: =IF(H7>0%,($N7+H7)/2,H7) -> 0.28482319 | X7: =IF(I7>0%,($N7+I7)/2,I7) -> 0.30546593 | ... AB7: =IF(M7>0%,($N7+M7)/2,M7) -> 0.30406608 | AC7: =AVERAGE(Q7:AB7) -> 0.32748241 | AD7: =$AD$6*AC7 -> 115818.74
A8: SAVING | B8: =VLOOKUP($A8,$A$26:$M$43,B$5+1,0) -> 0.20063086 | C8: =VLOOKUP($A8,$A$26:$M$43,C$5+1,0) -> 0.16136253 | D8: =VLOOKUP($A8,$A$26:$M$43,D$5+1,0) -> 0.38796622 | E8: =VLOOKUP($A8,$A$26:$M$43,E$5+1,0) -> 0.1676316 | F8: =VLOOKUP($A8,$A$26:$M$43,F$5+1,0) -> 0.34902722 | G8: =VLOOKUP($A8,$A$26:$M$43,G$5+1,0) -> 0.37751772 | H8: =VLOOKUP($A8,$A$26:$M$43,H$5+1,0) -> 0.44899703 | I8: =VLOOKUP($A8,$A$26:$M$43,I$5+1,0) -> 0.40595552 | ... M8: =VLOOKUP($A8,$A$26:$M$43,M$5+1,0) -> 0.20472681 | N8: =AVERAGE(B8:M8) -> 0.254829 | P8: SAVING | Q8: =IF(B8>0%,($N8+B8)/2,B8) -> 0.22772993 | R8: =IF(C8>0%,($N8+C8)/2,C8) -> 0.20809576 | S8: =IF(D8>0%,($N8+D8)/2,D8) -> 0.32139761 | T8: =IF(E8>0%,($N8+E8)/2,E8) -> 0.2112303 | U8: =IF(F8>0%,($N8+F8)/2,F8) -> 0.30192811 | V8: =IF(G8>0%,($N8+G8)/2,G8) -> 0.31617336 | W8: =IF(H8>0%,($N8+H8)/2,H8) -> 0.35191301 | X8: =IF(I8>0%,($N8+I8)/2,I8) -> 0.33039226 | ... AB8: =IF(M8>0%,($N8+M8)/2,M8) -> 0.22977791 | AC8: =AVERAGE(Q8:AB8) -> 0.254829 | AD8: =$AD$6*AC8 -> 90123.843
A9: TRANSFER | B9: =VLOOKUP($A9,$A$26:$M$43,B$5+1,0) -> 0.15823756 | C9: =VLOOKUP($A9,$A$26:$M$43,C$5+1,0) -> 0.11669968 | D9: =VLOOKUP($A9,$A$26:$M$43,D$5+1,0) -> 0.11999537 | E9: =VLOOKUP($A9,$A$26:$M$43,E$5+1,0) -> 0.092793406 | F9: =VLOOKUP($A9,$A$26:$M$43,F$5+1,0) -> 0.065427182 | G9: =VLOOKUP($A9,$A$26:$M$43,G$5+1,0) -> 0.054783214 | H9: =VLOOKUP($A9,$A$26:$M$43,H$5+1,0) -> 0.14876994 | I9: =VLOOKUP($A9,$A$26:$M$43,I$5+1,0) -> 0.20837851 | ... M9: =VLOOKUP($A9,$A$26:$M$43,M$5+1,0) -> 0.15320219 | N9: =AVERAGE(B9:M9) -> 0.14125384 | P9: TRANSFER | Q9: =IF(B9>0%,($N9+B9)/2,B9) -> 0.1497457 | R9: =IF(C9>0%,($N9+C9)/2,C9) -> 0.12897676 | S9: =IF(D9>0%,($N9+D9)/2,D9) -> 0.1306246 | T9: =IF(E9>0%,($N9+E9)/2,E9) -> 0.11702362 | U9: =IF(F9>0%,($N9+F9)/2,F9) -> 0.10334051 | V9: =IF(G9>0%,($N9+G9)/2,G9) -> 0.098018526 | W9: =IF(H9>0%,($N9+H9)/2,H9) -> 0.14501189 | X9: =IF(I9>0%,($N9+I9)/2,I9) -> 0.17481617 | ... AB9: =IF(M9>0%,($N9+M9)/2,M9) -> 0.14722802 | AC9: =AVERAGE(Q9:AB9) -> 0.14125384 | AD9: =$AD$6*AC9 -> 49956.398
A10: WITHDRAW | B10: =VLOOKUP($A10,$A$26:$M$43,B$5+1,0) -> 0.072956675 | C10: =VLOOKUP($A10,$A$26:$M$43,C$5+1,0) -> 0.046103579 | D10: =VLOOKUP($A10,$A$26:$M$43,D$5+1,0) -> 0.093111893 | E10: =VLOOKUP($A10,$A$26:$M$43,E$5+1,0) -> 0 | F10: =VLOOKUP($A10,$A$26:$M$43,F$5+1,0) -> 0.032467648 | G10: =VLOOKUP($A10,$A$26:$M$43,G$5+1,0) -> 0.064717323 | H10: =VLOOKUP($A10,$A$26:$M$43,H$5+1,0) -> 0.029442428 | I10: =VLOOKUP($A10,$A$26:$M$43,I$5+1,0) -> 0.01130509 | ... M10: =VLOOKUP($A10,$A$26:$M$43,M$5+1,0) -> 0.038857149 | N10: =AVERAGE(B10:M10) -> 0.046914755 | P10: WITHDRAW | Q10: =IF(B10>0%,($N10+B10)/2,B10) -> 0.059935715 | R10: =IF(C10>0%,($N10+C10)/2,C10) -> 0.046509167 | S10: =IF(D10>0%,($N10+D10)/2,D10) -> 0.070013324 | T10: =IF(E10>0%,($N10+E10)/2,E10) -> 0 | U10: =IF(F10>0%,($N10+F10)/2,F10) -> 0.039691202 | V10: =IF(G10>0%,($N10+G10)/2,G10) -> 0.055816039 | W10: =IF(H10>0%,($N10+H10)/2,H10) -> 0.038178591 | X10: =IF(I10>0%,($N10+I10)/2,I10) -> 0.029109923 | ... AB10: =IF(M10>0%,($N10+M10)/2,M10) -> 0.042885952 | AC10: =AVERAGE(Q10:AB10) -> 0.044959973 | AD10: =$AD$6*AC10 -> 15900.724
A11: GROCERY | B11: =VLOOKUP($A11,$A$26:$M$43,B$5+1,0) -> 0.095997852 | C11: =VLOOKUP($A11,$A$26:$M$43,C$5+1,0) -> 0.055406359 | D11: =VLOOKUP($A11,$A$26:$M$43,D$5+1,0) -> 0.063234976 | E11: =VLOOKUP($A11,$A$26:$M$43,E$5+1,0) -> 0.19582724 | F11: =VLOOKUP($A11,$A$26:$M$43,F$5+1,0) -> 0.047876794 | G11: =VLOOKUP($A11,$A$26:$M$43,G$5+1,0) -> 0.07818543 | H11: =VLOOKUP($A11,$A$26:$M$43,H$5+1,0) -> 0.051484502 | I11: =VLOOKUP($A11,$A$26:$M$43,I$5+1,0) -> 0.027530773 | ... M11: =VLOOKUP($A11,$A$26:$M$43,M$5+1,0) -> 0.093739086 | N11: =AVERAGE(B11:M11) -> 0.070973542 | P11: GROCERY | Q11: =IF(B11>0%,($N11+B11)/2,B11) -> 0.083485697 | R11: =IF(C11>0%,($N11+C11)/2,C11) -> 0.063189951 | S11: =IF(D11>0%,($N11+D11)/2,D11) -> 0.067104259 | T11: =IF(E11>0%,($N11+E11)/2,E11) -> 0.13340039 | U11: =IF(F11>0%,($N11+F11)/2,F11) -> 0.059425168 | V11: =IF(G11>0%,($N11+G11)/2,G11) -> 0.074579486 | W11: =IF(H11>0%,($N11+H11)/2,H11) -> 0.061229022 | X11: =IF(I11>0%,($N11+I11)/2,I11) -> 0.049252157 | ... AB11: =IF(M11>0%,($N11+M11)/2,M11) -> 0.082356314 | AC11: =AVERAGE(Q11:AB11) -> 0.070973542 | AD11: =$AD$6*AC11 -> 25100.787
A12: GOLD | B12: =VLOOKUP($A12,$A$26:$M$43,B$5+1,0) -> 0.070804453 | C12: =VLOOKUP($A12,$A$26:$M$43,C$5+1,0) -> 0.097370759 | D12: =VLOOKUP($A12,$A$26:$M$43,D$5+1,0) -> 0 | E12: =VLOOKUP($A12,$A$26:$M$43,E$5+1,0) -> 0 | F12: =VLOOKUP($A12,$A$26:$M$43,F$5+1,0) -> 0 | G12: =VLOOKUP($A12,$A$26:$M$43,G$5+1,0) -> 0 | H12: =VLOOKUP($A12,$A$26:$M$43,H$5+1,0) -> 0 | I12: =VLOOKUP($A12,$A$26:$M$43,I$5+1,0) -> 0.007584688 | ... M12: =VLOOKUP($A12,$A$26:$M$43,M$5+1,0) -> 0 | N12: =AVERAGE(B12:M12) -> 0.024552225 | P12: GOLD | Q12: =IF(B12>0%,($N12+B12)/2,B12) -> 0.047678339 | R12: =IF(C12>0%,($N12+C12)/2,C12) -> 0.060961492 | S12: =IF(D12>0%,($N12+D12)/2,D12) -> 0 | T12: =IF(E12>0%,($N12+E12)/2,E12) -> 0 | U12: =IF(F12>0%,($N12+F12)/2,F12) -> 0 | V12: =IF(G12>0%,($N12+G12)/2,G12) -> 0 | W12: =IF(H12>0%,($N12+H12)/2,H12) -> 0 | X12: =IF(I12>0%,($N12+I12)/2,I12) -> 0.016068456 | ... AB12: =IF(M12>0%,($N12+M12)/2,M12) -> 0 | AC12: =AVERAGE(Q12:AB12) -> 0.017391159 | AD12: =$AD$6*AC12 -> 6150.6269
A13: EDUCATION | B13: =VLOOKUP($A13,$A$26:$M$43,B$5+1,0) -> 0.015320902 | C13: =VLOOKUP($A13,$A$26:$M$43,C$5+1,0) -> 0.019363503 | D13: =VLOOKUP($A13,$A$26:$M$43,D$5+1,0) -> 0.0086904433 | E13: =VLOOKUP($A13,$A$26:$M$43,E$5+1,0) -> 0.04150931 | F13: =VLOOKUP($A13,$A$26:$M$43,F$5+1,0) -> 0.0013675374 | G13: =VLOOKUP($A13,$A$26:$M$43,G$5+1,0) -> 0 | H13: =VLOOKUP($A13,$A$26:$M$43,H$5+1,0) -> 0 | I13: =VLOOKUP($A13,$A$26:$M$43,I$5+1,0) -> 0 | ... M13: =VLOOKUP($A13,$A$26:$M$43,M$5+1,0) -> 0.0085985262 | N13: =AVERAGE(B13:M13) -> 0.0093640738 | P13: EDUCATION | Q13: =IF(B13>0%,($N13+B13)/2,B13) -> 0.012342488 | R13: =IF(C13>0%,($N13+C13)/2,C13) -> 0.014363789 | S13: =IF(D13>0%,($N13+D13)/2,D13) -> 0.0090272586 | T13: =IF(E13>0%,($N13+E13)/2,E13) -> 0.025436692 | U13: =IF(F13>0%,($N13+F13)/2,F13) -> 0.0053658056 | V13: =IF(G13>0%,($N13+G13)/2,G13) -> 0 | W13: =IF(H13>0%,($N13+H13)/2,H13) -> 0 | X13: =IF(I13>0%,($N13+I13)/2,I13) -> 0 | ... AB13: =IF(M13>0%,($N13+M13)/2,M13) -> 0.0089813 | AC13: =AVERAGE(Q13:AB13) -> 0.0078033949 | AD13: =$AD$6*AC13 -> 2759.7798
A14: SHOPPING | B14: =VLOOKUP($A14,$A$26:$M$43,B$5+1,0) -> 0.020857219 | C14: =VLOOKUP($A14,$A$26:$M$43,C$5+1,0) -> 0.022274944 | D14: =VLOOKUP($A14,$A$26:$M$43,D$5+1,0) -> 0.0058453577 | E14: =VLOOKUP($A14,$A$26:$M$43,E$5+1,0) -> 0 | F14: =VLOOKUP($A14,$A$26:$M$43,F$5+1,0) -> 0.010811727 | G14: =VLOOKUP($A14,$A$26:$M$43,G$5+1,0) -> 0.024031699 | H14: =VLOOKUP($A14,$A$26:$M$43,H$5+1,0) -> 0.014220693 | I14: =VLOOKUP($A14,$A$26:$M$43,I$5+1,0) -> 0.0013155014 | ... M14: =VLOOKUP($A14,$A$26:$M$43,M$5+1,0) -> 0.056824794 | N14: =AVERAGE(B14:M14) -> 0.019659234 | P14: TRAVEL | Q14: =IF(B14>0%,($N14+B14)/2,B14) -> 0.020258227 | R14: =IF(C14>0%,($N14+C14)/2,C14) -> 0.020967089 | S14: =IF(D14>0%,($N14+D14)/2,D14) -> 0.012752296 | T14: =IF(E14>0%,($N14+E14)/2,E14) -> 0 | U14: =IF(F14>0%,($N14+F14)/2,F14) -> 0.015235481 | V14: =IF(G14>0%,($N14+G14)/2,G14) -> 0.021845467 | W14: =IF(H14>0%,($N14+H14)/2,H14) -> 0.016939964 | X14: =IF(I14>0%,($N14+I14)/2,I14) -> 0.010487368 | ... AB14: =IF(M14>0%,($N14+M14)/2,M14) -> 0.038242014 | AC14: =AVERAGE(Q14:AB14) -> 0.0188401 | AD14: =$AD$6*AC14 -> 6663.065
A15: TRANSPORT | B15: =VLOOKUP($A15,$A$26:$M$43,B$5+1,0) -> 0.0077064136 | C15: =VLOOKUP($A15,$A$26:$M$43,C$5+1,0) -> 0.0071188536 | D15: =VLOOKUP($A15,$A$26:$M$43,D$5+1,0) -> 0.0062987092 | E15: =VLOOKUP($A15,$A$26:$M$43,E$5+1,0) -> 0.018490883 | F15: =VLOOKUP($A15,$A$26:$M$43,F$5+1,0) -> 0.0017207854 | G15: =VLOOKUP($A15,$A$26:$M$43,G$5+1,0) -> 0.009450455 | H15: =VLOOKUP($A15,$A$26:$M$43,H$5+1,0) -> 0.013080093 | I15: =VLOOKUP($A15,$A$26:$M$43,I$5+1,0) -> 0.0086500386 | ... M15: =VLOOKUP($A15,$A$26:$M$43,M$5+1,0) -> 0.031076507 | N15: =AVERAGE(B15:M15) -> 0.012985702 | P15: SHOPPING | Q15: =IF(B15>0%,($N15+B15)/2,B15) -> 0.010346058 | R15: =IF(C15>0%,($N15+C15)/2,C15) -> 0.010052278 | S15: =IF(D15>0%,($N15+D15)/2,D15) -> 0.0096422058 | T15: =IF(E15>0%,($N15+E15)/2,E15) -> 0.015738293 | U15: =IF(F15>0%,($N15+F15)/2,F15) -> 0.0073532439 | V15: =IF(G15>0%,($N15+G15)/2,G15) -> 0.011218079 | W15: =IF(H15>0%,($N15+H15)/2,H15) -> 0.013032898 | X15: =IF(I15>0%,($N15+I15)/2,I15) -> 0.010817871 | ... AB15: =IF(M15>0%,($N15+M15)/2,M15) -> 0.022031105 | AC15: =AVERAGE(Q15:AB15) -> 0.012985702 | AD15: =$AD$6*AC15 -> 4592.5755
A16: TRAVEL | B16: =VLOOKUP($A16,$A$26:$M$43,B$5+1,0) -> 0 | C16: =VLOOKUP($A16,$A$26:$M$43,C$5+1,0) -> 0.030197844 | D16: =VLOOKUP($A16,$A$26:$M$43,D$5+1,0) -> 0.029485433 | E16: =VLOOKUP($A16,$A$26:$M$43,E$5+1,0) -> 0.067052642 | F16: =VLOOKUP($A16,$A$26:$M$43,F$5+1,0) -> 0.17831233 | G16: =VLOOKUP($A16,$A$26:$M$43,G$5+1,0) -> 0 | H16: =VLOOKUP($A16,$A$26:$M$43,H$5+1,0) -> 0.017665457 | I16: =VLOOKUP($A16,$A$26:$M$43,I$5+1,0) -> 0 | ... M16: =VLOOKUP($A16,$A$26:$M$43,M$5+1,0) -> 0.083963175 | N16: =AVERAGE(B16:M16) -> 0.052522741 | P16: TRANSPORT | Q16: =IF(B16>0%,($N16+B16)/2,B16) -> 0 | R16: =IF(C16>0%,($N16+C16)/2,C16) -> 0.041360293 | S16: =IF(D16>0%,($N16+D16)/2,D16) -> 0.041004087 | T16: =IF(E16>0%,($N16+E16)/2,E16) -> 0.059787691 | U16: =IF(F16>0%,($N16+F16)/2,F16) -> 0.11541753 | V16: =IF(G16>0%,($N16+G16)/2,G16) -> 0 | W16: =IF(H16>0%,($N16+H16)/2,H16) -> 0.035094099 | X16: =IF(I16>0%,($N16+I16)/2,I16) -> 0 | ... AB16: =IF(M16>0%,($N16+M16)/2,M16) -> 0.068242958 | AC16: =AVERAGE(Q16:AB16) -> 0.045957399 | AD16: =$AD$6*AC16 -> 16253.477
A17: TELECOM | B17: =VLOOKUP($A17,$A$26:$M$43,B$5+1,0) -> 0.016050469 | C17: =VLOOKUP($A17,$A$26:$M$43,C$5+1,0) -> 0.012475628 | D17: =VLOOKUP($A17,$A$26:$M$43,D$5+1,0) -> 0.0091042739 | E17: =VLOOKUP($A17,$A$26:$M$43,E$5+1,0) -> 0.026821057 | F17: =VLOOKUP($A17,$A$26:$M$43,F$5+1,0) -> 0.0097402945 | G17: =VLOOKUP($A17,$A$26:$M$43,G$5+1,0) -> 0.020925268 | H17: =VLOOKUP($A17,$A$26:$M$43,H$5+1,0) -> 0.0091271527 | I17: =VLOOKUP($A17,$A$26:$M$43,I$5+1,0) -> 0.0073996956 | ... M17: =VLOOKUP($A17,$A$26:$M$43,M$5+1,0) -> 0.017647451 | N17: =AVERAGE(B17:M17) -> 0.013795989 | P17: TELECOM | Q17: =IF(B17>0%,($N17+B17)/2,B17) -> 0.014923229 | R17: =IF(C17>0%,($N17+C17)/2,C17) -> 0.013135809 | S17: =IF(D17>0%,($N17+D17)/2,D17) -> 0.011450131 | T17: =IF(E17>0%,($N17+E17)/2,E17) -> 0.020308523 | U17: =IF(F17>0%,($N17+F17)/2,F17) -> 0.011768142 | V17: =IF(G17>0%,($N17+G17)/2,G17) -> 0.017360628 | W17: =IF(H17>0%,($N17+H17)/2,H17) -> 0.011461571 | X17: =IF(I17>0%,($N17+I17)/2,I17) -> 0.010597842 | ... AB17: =IF(M17>0%,($N17+M17)/2,M17) -> 0.01572172 | AC17: =AVERAGE(Q17:AB17) -> 0.013795989 | AD17: =$AD$6*AC17 -> 4879.1446
A18: FOOD | B18: =VLOOKUP($A18,$A$26:$M$43,B$5+1,0) -> 0.011709546 | C18: =VLOOKUP($A18,$A$26:$M$43,C$5+1,0) -> 0.0094973373 | D18: =VLOOKUP($A18,$A$26:$M$43,D$5+1,0) -> 0.0044279878 | E18: =VLOOKUP($A18,$A$26:$M$43,E$5+1,0) -> 0.0081208199 | F18: =VLOOKUP($A18,$A$26:$M$43,F$5+1,0) -> 0.0024350736 | G18: =VLOOKUP($A18,$A$26:$M$43,G$5+1,0) -> 0.014108376 | H18: =VLOOKUP($A18,$A$26:$M$43,H$5+1,0) -> 0.015207014 | I18: =VLOOKUP($A18,$A$26:$M$43,I$5+1,0) -> 0.014861055 | ... M18: =VLOOKUP($A18,$A$26:$M$43,M$5+1,0) -> 0.017545088 | N18: =AVERAGE(B18:M18) -> 0.013864733 | P18: FOOD | Q18: =IF(B18>0%,($N18+B18)/2,B18) -> 0.01278714 | R18: =IF(C18>0%,($N18+C18)/2,C18) -> 0.011681035 | S18: =IF(D18>0%,($N18+D18)/2,D18) -> 0.0091463605 | T18: =IF(E18>0%,($N18+E18)/2,E18) -> 0.010992777 | U18: =IF(F18>0%,($N18+F18)/2,F18) -> 0.0081499035 | V18: =IF(G18>0%,($N18+G18)/2,G18) -> 0.013986555 | W18: =IF(H18>0%,($N18+H18)/2,H18) -> 0.014535874 | X18: =IF(I18>0%,($N18+I18)/2,I18) -> 0.014362894 | ... AB18: =IF(M18>0%,($N18+M18)/2,M18) -> 0.015704911 | AC18: =AVERAGE(Q18:AB18) -> 0.013864733 | AD18: =$AD$6*AC18 -> 4903.457
... A22: SERVICE | B22: =VLOOKUP($A22,$A$26:$M$43,B$5+1,0) -> 0.00087584488 | C22: =VLOOKUP($A22,$A$26:$M$43,C$5+1,0) -> 0.00036882863 | D22: =VLOOKUP($A22,$A$26:$M$43,D$5+1,0) -> 0.0005795698 | E22: =VLOOKUP($A22,$A$26:$M$43,E$5+1,0) -> 0.00029801174 | F22: =VLOOKUP($A22,$A$26:$M$43,F$5+1,0) -> 0.0012993553 | G22: =VLOOKUP($A22,$A$26:$M$43,G$5+1,0) -> 0.00034515906 | H22: =VLOOKUP($A22,$A$26:$M$43,H$5+1,0) -> 0.0027072313 | I22: =VLOOKUP($A22,$A$26:$M$43,I$5+1,0) -> 0.00098662608 | ... M22: =VLOOKUP($A22,$A$26:$M$43,M$5+1,0) -> 0.0016060819 | N22: =AVERAGE(B22:M22) -> 0.0012635273 | P22: SERVICE | Q22: =IF(B22>0%,($N22+B22)/2,B22) -> 0.0010696861 | R22: =IF(C22>0%,($N22+C22)/2,C22) -> 0.00081617796 | S22: =IF(D22>0%,($N22+D22)/2,D22) -> 0.00092154855 | T22: =IF(E22>0%,($N22+E22)/2,E22) -> 0.00078076951 | U22: =IF(F22>0%,($N22+F22)/2,F22) -> 0.0012814413 | V22: =IF(G22>0%,($N22+G22)/2,G22) -> 0.00080434317 | W22: =IF(H22>0%,($N22+H22)/2,H22) -> 0.0019853793 | X22: =IF(I22>0%,($N22+I22)/2,I22) -> 0.0011250767 | ... AB22: =IF(M22>0%,($N22+M22)/2,M22) -> 0.0014348046 | AC22: =AVERAGE(Q22:AB22) -> 0.0012635273 | AD22: =$AD$6*AC22 -> 446.86412
A24: =COUNTA(A7:A22)=COUNTA(A26:A41) -> TRUE
A25: T_type | B25: 1 | C25: 2 | D25: 3 | E25: 4 | F25: 5 | G25: 6 | H25: 7 | I25: 8 | J25: 9 | K25: 10 | L25: 11 | M25: 12
A26: RENT | B26: 0.32739308 | C26: 0.41377962 | D26: 0.27105907 | E26: 0.37996497 | F26: 0.29951406 | G26: 0.35486666 | H26: 0.24216397 | I26: 0.28344945 | J26: 0.49778476 | K26: 0.29492323 | L26: 0.28424033 | M26: 0.28064975
A27: SAVING | B27: 0.20063086 | C27: 0.16136253 | D27: 0.38796622 | E27: 0.1676316 | F27: 0.34902722 | G27: 0.37751772 | H27: 0.44899703 | I27: 0.40595552 | J27: 0.099999053 | K27: 0.10228551 | L27: 0.15184792 | M27: 0.20472681
A28: TRANSFER | B28: 0.15823756 | C28: 0.11669968 | D28: 0.11999537 | E28: 0.092793406 | F28: 0.065427182 | G28: 0.054783214 | H28: 0.14876994 | I28: 0.20837851 | J28: 0.10540679 | K28: 0.35150757 | L28: 0.11984464 | M28: 0.15320219
A29: GROCERY | B29: 0.095997852 | C29: 0.055406359 | D29: 0.063234976 | E29: 0.19582724 | F29: 0.047876794 | G29: 0.07818543 | H29: 0.051484502 | I29: 0.027530773 | J29: 0.043550114 | K29: 0.047609815 | L29: 0.051239563 | M29: 0.093739086
A30: TRAVEL | B30: 0 | C30: 0.030197844 | D30: 0.029485433 | E30: 0.067052642 | F30: 0.17831233 | G30: 0 | H30: 0.017665457 | I30: 0 | J30: 0.11831467 | K30: 0.012160611 | L30: 0.093120739 | M30: 0.083963175
A31: WITHDRAW | B31: 0.072956675 | C31: 0.046103579 | D31: 0.093111893 | E31: 0 | F31: 0.032467648 | G31: 0.064717323 | H31: 0.029442428 | I31: 0.01130509 | J31: 0.05263108 | K31: 0.045460228 | L31: 0.075923961 | M31: 0.038857149
A32: GOLD | B32: 0.070804453 | C32: 0.097370759 | D32: 0 | E32: 0 | F32: 0 | G32: 0 | H32: 0 | I32: 0.007584688 | J32: 0 | K32: 0.014547273 | L32: 0.10431952 | M32: 0
A33: SHOPPING | B33: 0.020857219 | C33: 0.022274944 | D33: 0.0058453577 | E33: 0 | F33: 0.010811727 | G33: 0.024031699 | H33: 0.014220693 | I33: 0.0013155014 | J33: 0.023418094 | K33: 0.034371796 | L33: 0.021938988 | M33: 0.056824794
A34: FOOD | B34: 0.011709546 | C34: 0.0094973373 | D34: 0.0044279878 | E34: 0.0081208199 | F34: 0.0024350736 | G34: 0.014108376 | H34: 0.015207014 | I34: 0.014861055 | J34: 0.023262938 | K34: 0.029674164 | L34: 0.015527399 | M34: 0.017545088
A35: TRANSPORT | B35: 0.0077064136 | C35: 0.0071188536 | D35: 0.0062987092 | E35: 0.018490883 | F35: 0.0017207854 | G35: 0.009450455 | H35: 0.013080093 | I35: 0.0086500386 | J35: 0.015928481 | K35: 0.020350271 | L35: 0.015956939 | M35: 0.031076507
A36: TELECOM | B36: 0.016050469 | C36: 0.012475628 | D36: 0.0091042739 | E36: 0.026821057 | F36: 0.0097402945 | G36: 0.020925268 | H36: 0.0091271527 | I36: 0.0073996956 | J36: 0.0061052053 | K36: 0.015834025 | L36: 0.014321347 | M36: 0.017647451
... A41: SERVICE | B41: 0.00087584488 | C41: 0.00036882863 | D41: 0.0005795698 | E41: 0.00029801174 | F41: 0.0012993553 | G41: 0.00034515906 | H41: 0.0027072313 | I41: 0.00098662608 | J41: 0.0027334478 | K41: 0.0012501563 | L41: 0.0021120148 | M41: 0.0016060819
A43: =A7=A26 -> TRUE
A44: =A8=A27 -> TRUE
A45: =A9=A28 -> TRUE
A46: =A10=A29 -> FALSE
A47: =A11=A30 -> FALSE
A48: =A12=A31 -> FALSE
A49: =A13=A32 -> FALSE
A50: =A14=A33 -> TRUE
A51: =A15=A34 -> FALSE
A52: =A16=A35 -> FALSE
A53: =A17=A36 -> TRUE
A54: =A18=A37 -> FALSE
... A59: =A23=A42 -> TRUE

Sheet %BUDGET
A1: Trans_type | B1: 43678 | C1: 43709 | D1: 43739 | E1: 43770 | F1: 43800 | G1: 43831 | H1: 43862 | I1: 43891 | J1: 43922 | K1: 43952 | L1: 43983 | M1: 44013 | N1: 44044 | O1: 44075 | P1: 44105 | Q1: 44136 | R1: 44166 | S1: 44197 | T1: 44228 | U1: 44256 | V1: 44287 | W1: 44317 | X1: 44348 | Y1: 44378 | Z1: 44409 | AA1: 44440 | AB1: 44470 | AC1: 44501 | AD1: 44531 | AE1: 44562 | AF1: 44593 | AG1: 44621 | AH1: 44652 | AI1: 44682 | AJ1: 44713 | AK1: 44743 | AL1: 44774 | AM1: 44805 | AN1: 44835 | AO1: 44866 | AP1: 44896 | AQ1: 44927 | AR1: 44958 | AS1: 44986 | AT1: 45017 | AU1: 45047 | AV1: 45078 | AW1: 45108 | AX1: 45139 | AY1: 45170 | AZ1: 45200 | BA1: 45231 | BB1: 45261 | BC1: 45292 | BD1: 45323 | BE1: 45352 | BF1: 45383 | BG1: 45413 | BH1: 45444 | BI1: 45474 | BJ1: 45505 | BK1: 45536 | BL1: 45566 | BM1: 45597 | BN1: 45627
A2: SALARY | B2: =SUM(B3:B18) -> 1.0000039 | C2: =SUM(C3:C18) -> 0.99996645 | D2: =SUM(D3:D18) -> 0.99997956 | E2: =SUM(E3:E18) -> 1.0000186 | F2: =SUM(F3:F18) -> 1.0000186 | G2: =SUM(G3:G18) -> 1.0000209 | H2: =SUM(H3:H18) -> 1.0000249 | I2: =SUM(I3:I18) -> 1.0000249 | ... BN2: =SUM(BN3:BN18) -> 1
A3: RENT | B3: 0.2913 | C3: 0.4734 | D3: 0.3532 | E3: 0.3532 | F3: 0.3532 | G3: 0.3532 | H3: 0.3532 | I3: 0.3532 | J3: 0.3714 | K3: 0.3714 | L3: 0.28422877 | M3: 0.28422877 | N3: 0.331715 | O3: 0.35558252 | P3: 0.33373786 | Q3: 0.33373786 | R3: 0.33373786 | S3: 0.33373786 | T3: 0.33373786 | U3: 0.202206 | V3: 0.2213 | W3: 0.2213 | X3: 0.2213 | Y3: 0.2213 | Z3: 0.23471 | AA3: 0.42921 | AB3: 0.32191 | AC3: 0.24142926 | AD3: 0.21596199 | AE3: 0.21802326 | AF3: 0.21802326 | AG3: 0.20478748 | AH3: 0.20478748 | AI3: 0.20478748 | AJ3: 0.20478748 | AK3: 0.20478748 | AL3: 0.21802326 | AM3: 0.25029 | AN3: 0.25029 | AO3: 0.25029 | AP3: 0.25029 | AQ3: 0.25029 | AR3: 0.25029 | AS3: 0.25029 | AT3: 0.25029 | AU3: 0.25029 | AV3: 0.25029 | AW3: 0.25029 | AX3: 0.25029 | AY3: 0.21802326 | AZ3: 0.21802326 | BA3: 0.18661781 | BB3: 0.18661781 | BC3: 0.18661781 | BD3: 0.18661781 | BE3: 0.18661781 | BF3: 0.18661781 | BG3: 0.18661781 | BH3: 0.18661781 | BI3: 0.18661781 | BJ3: 0.18661781 | BK3: 0.18661781 | BL3: 0.18661781 | BM3: 0.18661781 | BN3: 0.18661781
A4: SAVING | B4: 0.1505 | C4: 0.083738979 | D4: 0.0775 | E4: 0.1081 | F4: 0.0821 | G4: 0.147 | H4: 0.1709 | I4: 0.1709 | J4: 0.1434 | K4: 0.1833 | L4: 0.2704 | M4: 0.3498 | N4: 0.2247 | O4: 0.2082 | P4: 0.1454 | Q4: 0.3027 | R4: 0.2543 | S4: 0.2025 | T4: 0.24028237 | U4: 0.37181423 | V4: 0.45627707 | W4: 0.45627707 | X4: 0.46279081 | Y4: 0.38379861 | Z4: 0.40568239 | AA4: 0.065808008 | AB4: 0.20013057 | AC4: 0.27644144 | AD4: 0.27644144 | AE4: 0.34042913 | AF4: 0.34436295 | AG4: 0.39814103 | AH4: 0.37576912 | AI4: 0.32334781 | AJ4: 0.38222598 | AK4: 0.32041015 | AL4: 0.30858304 | AM4: 0.22407967 | AN4: 0.21237738 | AO4: 0.19944564 | AP4: 0.19479799 | AQ4: 0.16352213 | AR4: 0.18343253 | AS4: 0.21992993 | AT4: 0.17404988 | AU4: 0.27337651 | AV4: 0.21815124 | AW4: 0.34438325 | AX4: 0.23867652 | AY4: 0.077364009 | AZ4: 0.020714114 | BA4: 0.046495652 | BB4: 0.041848008 | BC4: 0.39767921 | BD4: 0.39497695 | BE4: 0.44919463 | BF4: 0.42676727 | BG4: 0.44635376 | BH4: 0.51681758 | BI4: 0.46994453 | BJ4: 0.48211653 | BK4: 0.42186829 | BL4: 0.31255652 | BM4: 0.32406236 | BN4: 0.36236515
A5: TRANSFER | B5: 0.2 | C5: 0.12978453 | D5: 0.12978453 | E5: 0.12978453 | F5: 0.12978453 | G5: 0.12978453 | H5: 0.12978453 | I5: 0.12978453 | J5: 0.12978453 | K5: 0.12978453 | L5: 0.12978453 | M5: 0.11469091 | N5: 0.13543528 | O5: 0.13935069 | P5: 0.1062467 | Q5: 0.044558261 | R5: 0.089116522 | S5: 0.15337024 | T5: 0.10608867 | U5: 0.10608867 | V5: 0.134127 | W5: 0.134127 | X5: 0.134127 | Y5: 0.134127 | Z5: 0.15176703 | AA5: 0.25710367 | AB5: 0.17578586 | AC5: 0.14954999 | AD5: 0.14954999 | AE5: 0.17276496 | AF5: 0.15199602 | AG5: 0.15364386 | AH5: 0.14004288 | AI5: 0.12635977 | AJ5: 0.12103779 | AK5: 0.18961 | AL5: 0.18961 | AM5: 0.18961 | AN5: 0.18961 | AO5: 0.18961 | AP5: 0.18961 | AQ5: 0.18961 | AR5: 0.18961 | AS5: 0.18961 | AT5: 0.18961 | AU5: 0.18961 | AV5: 0.18961 | AW5: 0.18961 | AX5: 0.18961 | AY5: 0.18961 | AZ5: 0.18961 | BA5: 0.18961 | BB5: 0.18961 | BC5: 0.1497457 | BD5: 0.12897676 | BE5: 0.1306246 | BF5: 0.11702362 | BG5: 0.10334051 | BH5: 0.098018526 | BI5: 0.14501189 | BJ5: 0.17481617 | BK5: 0.12333031 | BL5: 0.24638071 | BM5: 0.13054924 | BN5: 0.14722802
A6: WITHDRAW | B6: 0.089496034 | C6: 0.089496034 | D6: 0.089496034 | E6: 0.089496034 | F6: 0.089496034 | G6: 0.089496034 | H6: 0.0656 | I6: 0.0656 | J6: 0.0656 | K6: 0.0656 | L6: 0.0656 | M6: 0.056580794 | N6: 0.096184024 | O6: 0.041507346 | P6: 0.041507346 | Q6: 0.041507346 | R6: 0.083014691 | S6: 0.072891892 | T6: 0.061681176 | U6: 0.061681176 | V6: 0 | W6: 0 | X6: 0 | Y6: 0.10517093 | Z6: 0.04766029 | AA6: 0.086769409 | AB6: 0.059621948 | AC6: 0.095921265 | AD6: 0.095921265 | AE6: 0.06238222 | AF6: 0.048955672 | AG6: 0.072459828 | AH6: 0.0910176 | AI6: 0.042137706 | AJ6: 0.058262544 | AK6: 0.040625096 | AL6: 0.031556427 | AM6: 0.06083549 | AN6: 0.049112275 | AO6: 0.085411593 | AP6: 0.044050437 | AQ6: 0.06238222 | AR6: 0.048955672 | AS6: 0.072459828 | AT6: 0.0910176 | AU6: 0.042137706 | AV6: 0.058262544 | AW6: 0.040625096 | AX6: 0.031556427 | AY6: 0.06083549 | AZ6: 0.049112275 | BA6: 0.085411593 | BB6: 0.044050437 | BC6: 0.059935715 | BD6: 0.046509167 | BE6: 0.070013324 | BF6: 0 | BG6: 0.039691202 | BH6: 0.055816039 | BI6: 0.038178591 | BJ6: 0.029109923 | BK6: 0.049772918 | BL6: 0.046187491 | BM6: 0.061419358 | BN6: 0.042885952
A7: GROCERY | B7: 0.051965689 | C7: 0.051965689 | D7: 0.051965689 | E7: 0.051965689 | F7: 0.051965689 | G7: 0.051965689 | H7: 0.051965689 | I7: 0.051965689 | J7: 0.051965689 | K7: 0.051965689 | L7: 0.051965689 | M7: 0.077 | N7: 0.077 | O7: 0.077 | P7: 0.090303349 | Q7: 0.096546144 | R7: 0.07347102 | S7: 0.092779207 | T7: 0.061885956 | U7: 0.061885956 | V7: 0.10674013 | W7: 0.10674013 | X7: 0.12291533 | Y7: 0.11709013 | Z7: 0.071135472 | AA7: 0.076180782 | AB7: 0.084188829 | AC7: 0.071535841 | AD7: 0.071535841 | AE7: 0.085898602 | AF7: 0.065602855 | AG7: 0.069517164 | AH7: 0.10313167 | AI7: 0.061838073 | AJ7: 0.076992391 | AK7: 0.063641927 | AL7: 0.051665062 | AM7: 0.061830342 | AN7: 0.077308224 | AO7: 0.064655235 | AP7: 0.094829046 | AQ7: 0.085898602 | AR7: 0.065602855 | AS7: 0.069517164 | AT7: 0.10313167 | AU7: 0.061838073 | AV7: 0.076992391 | AW7: 0.063641927 | AX7: 0.051665062 | AY7: 0.061830342 | AZ7: 0.077308224 | BA7: 0.064655235 | BB7: 0.094829046 | BC7: 0.083485697 | BD7: 0.063189951 | BE7: 0.067104259 | BF7: 0.13340039 | BG7: 0.059425168 | BH7: 0.074579486 | BI7: 0.061229022 | BJ7: 0.049252157 | BK7: 0.057261828 | BL7: 0.059291678 | BM7: 0.061106553 | BN7: 0.082356314
A8: GOLD | B8: 0.056461007 | C8: 0.0113 | D8: 0.056461007 | E8: 0.0259 | F8: 0.0519 | G8: 0.056461007 | H8: 0.056461007 | I8: 0.056461007 | J8: 0.056461007 | K8: 0.056461007 | L8: 0.056461007 | M8: 0.019384469 | N8: 0.019384469 | O8: 0.042691097 | P8: 0.11421577 | Q8: 0.019384469 | R8: 0.038768939 | S8: 0.065496466 | T8: 0.083459457 | U8: 0.083459457 | V8: 0 | W8: 0 | X8: 0 | Y8: 0 | Z8: 0.037639776 | AA8: 0 | AB8: 0.044947611 | AC8: 0.069399082 | AD8: 0.094866353 | AE8: 0.04723874 | AF8: 0.060521893 | AG8: 0 | AH8: 0 | AI8: 0 | AJ8: 0 | AK8: 0 | AL8: 0 | AM8: 0 | AN8: 0 | AO8: 0 | AP8: 0 | AQ8: 0.04723874 | AR8: 0.060521893 | AS8: 0 | AT8: 0 | AU8: 0 | AV8: 0 | AW8: 0 | AX8: 0.037639776 | AY8: 0 | AZ8: 0.044947611 | BA8: 0.037639776 | BB8: 0.037639776 | BC8: 0.047678339 | BD8: 0.060961492 | BE8: 0 | BF8: 0 | BG8: 0 | BH8: 0 | BI8: 0 | BJ8: 0.016068456 | BK8: 0 | BL8: 0.019549749 | BM8: 0.064435874 | BN8: 0
A9: EDUCATION | B9: 0 | C9: 0 | D9: 0.03059 | E9: 0.03059 | F9: 0.03059 | G9: 0.03059 | H9: 0.03059 | I9: 0.03059 | J9: 0.03988 | K9: 0 | L9: 0 | M9: 0.01120975 | N9: 0.01120975 | O9: 0.026504725 | P9: 0.026285127 | Q9: 0.026504725 | R9: 0.022419501 | S9: 0.018308366 | T9: 0.021260317 | U9: 0.021260317 | V9: 0.040596324 | W9: 0.040596324 | X9: 0.012963354 | Y9: 0 | Z9: 0 | AA9: 0 | AB9: 0.020395441 | AC9: 0.016896225 | AD9: 0.016896225 | AE9: 0.013222387 | AF9: 0.015243688 | AG9: 0.009907158 | AH9: 0 | AI9: 0.0910176 | AJ9: 0.0910176 | AK9: 0.0910176 | AL9: 0.0910176 | AM9: 0.0910176 | AN9: 0.0910176 | AO9: 0.0910176 | AP9: 0.0910176 | AQ9: 0.0910176 | AR9: 0.0910176 | AS9: 0.0910176 | AT9: 0.0910176 | AU9: 0.0910176 | AV9: 0.0910176 | AW9: 0 | AX9: 0.0910176 | AY9: 0.16 | AZ9: 0.16 | BA9: 0.16 | BB9: 0.16 | BC9: 0.012342488 | BD9: 0.014363789 | BE9: 0.0090272586 | BF9: 0.025436692 | BG9: 0.0053658056 | BH9: 0 | BI9: 0 | BJ9: 0 | BK9: 0 | BL9: 0.0094553609 | BM9: 0.0086680449 | BN9: 0.0089813
A10: TRAVEL | B10: 0.024441314 | C10: 0.024441314 | D10: 0.024441314 | E10: 0.024441314 | F10: 0.024441314 | G10: 0.024441314 | H10: 0.024441314 | I10: 0.024441314 | J10: 0.024441314 | K10: 0.024441314 | L10: 0.024441314 | M10: 0.011104563 | N10: 0.011104563 | O10: 0.011104563 | P10: 0.022052158 | Q10: 0.011104563 | R10: 0.022209125 | S10: 0.019470801 | T10: 0.021250243 | U10: 0.021250243 | V10: 0 | W10: 0 | X10: 0 | Y10: 0 | Z10: 0.010350902 | AA10: 0.026593623 | AB10: 0.016774531 | AC10: 0.013998737 | AD10: 0.013998737 | AE10: 0.017867171 | AF10: 0.018576034 | AG10: 0.02359702 | AH10: 0 | AI10: 0.012844425 | AJ10: 0.019454411 | AK10: 0.014548908 | AL10: 0.0080963124 | AM10: 0.019613904 | AN10: 0.015170902 | AO10: 0.012395108 | AP10: 0.022158502 | AQ10: 0.017867171 | AR10: 0.018576034 | AS10: 0.02359702 | AT10: 0 | AU10: 0.012844425 | AV10: 0.019454411 | AW10: 0.014548908 | AX10: 0.0080963124 | AY10: 0.019613904 | AZ10: 0.015170902 | BA10: 0.012395108 | BB10: 0.022158502 | BC10: 0.020258227 | BD10: 0.020967089 | BE10: 0.012752296 | BF10: 0 | BG10: 0.015235481 | BH10: 0.021845467 | BI10: 0.016939964 | BJ10: 0.010487368 | BK10: 0.021538664 | BL10: 0.027015515 | BM10: 0.020799111 | BN10: 0.038242014
A11: SHOPPING | B11: 0.026670865 | C11: 0.026670865 | D11: 0.026670865 | E11: 0.026670865 | F11: 0.026670865 | G11: 0.026670865 | H11: 0.026670865 | I11: 0.026670865 | J11: 0.026670865 | K11: 0.026670865 | L11: 0.026670865 | M11: 0.009156772 | N11: 0.021301191 | O11: 0.021289693 | P11: 0.021115494 | Q11: 0.036184084 | R11: 0.018313544 | S11: 0.0097310455 | T11: 0.0083399158 | U11: 0.0083399158 | V11: 0.0063078616 | W11: 0.0063078616 | X11: 0.0063176181 | Y11: 0.0082453845 | Z11: 0.0077848761 | AA11: 0.013183668 | AB11: 0.024507448 | AC11: 0.013258431 | AD11: 0.013258431 | AE11: 0.011286655 | AF11: 0.010992875 | AG11: 0.010582803 | AH11: 0.01667889 | AI11: 0.008293841 | AJ11: 0.012158676 | AK11: 0.013973495 | AL11: 0.011758468 | AM11: 0.0133626 | AN11: 0.026063058 | AO11: 0.014814041 | AP11: 0.028437359 | AQ11: 0.011286655 | AR11: 0.010992875 | AS11: 0.010582803 | AT11: 0.01667889 | AU11: 0.008293841 | AV11: 0.012158676 | AW11: 0.013973495 | AX11: 0.011758468 | AY11: 0.0133626 | AZ11: 0.026063058 | BA11: 0.014814041 | BB11: 0.028437359 | BC11: 0.010346058 | BD11: 0.010052278 | BE11: 0.0096422058 | BF11: 0.015738293 | BG11: 0.0073532439 | BH11: 0.011218079 | BI11: 0.013032898 | BJ11: 0.010817871 | BK11: 0.014457092 | BL11: 0.016667987 | BM11: 0.014471321 | BN11: 0.022031105
A12: TRANSPORT | B12: 0.049298916 | C12: 0.049298916 | D12: 0.1 | E12: 0.1 | F12: 0.1 | G12: 0.049298916 | H12: 0.049298916 | I12: 0.049298916 | J12: 0.049298916 | K12: 0.049298916 | L12: 0.049298916 | M12: 0.0083521764 | N12: 0.012096071 | O12: 0.030056474 | P12: 0.023343203 | Q12: 0.044332876 | R12: 0.016704353 | S12: 0 | T12: 0.03 | U12: 0.03 | V12: 0.01073 | W12: 0.01073 | X12: 0.01073 | Y12: 0.01073 | Z12: 0.01073 | AA12: 0.01073 | AB12: 0.01073 | AC12: 0.01073 | AD12: 0.01073 | AE12: 0 | AF12: 0.034724212 | AG12: 0.034368006 | AH12: 0.034368006 | AI12: 0.10878145 | AJ12: 0 | AK12: 0.028458018 | AL12: 0.05 | AM12: 0.05 | AN12: 0.05 | AO12: 0.05 | AP12: 0.05 | AQ12: 0.05 | AR12: 0.05 | AS12: 0.05 | AT12: 0.05 | AU12: 0.05 | AV12: 0.05 | AW12: 0.05 | AX12: 0.05 | AY12: 0.16 | AZ12: 0.16 | BA12: 0.16 | BB12: 0.16 | BC12: 0 | BD12: 0.041360293 | BE12: 0.041004087 | BF12: 0.059787691 | BG12: 0.11541753 | BH12: 0 | BI12: 0.035094099 | BJ12: 0 | BK12: 0.085418705 | BL12: 0.032341676 | BM12: 0.07282174 | BN12: 0.068242958
A13: TELECOM | B13: 0.015874922 | C13: 0.015874922 | D13: 0.015874922 | E13: 0.015874922 | F13: 0.015874922 | G13: 0.015874922 | H13: 0.015874922 | I13: 0.015874922 | J13: 0.015874922 | K13: 0.015874922 | L13: 0.015874922 | M13: 0.0075705445 | N13: 0.0082995669 | O13: 0.018007908 | P13: 0.016543983 | Q13: 0.018859692 | R13: 0.015141089 | S13: 0.015791306 | T13: 0.01460349 | U13: 0.01460349 | V13: 0.019054173 | W13: 0.019054173 | X13: 0.01931028 | Y13: 0.014641809 | Z13: 0.012060279 | AA13: 0.01239881 | AB13: 0.020684095 | AC13: 0.012176337 | AD13: 0.012176337 | AE13: 0.015193391 | AF13: 0.013405971 | AG13: 0.011720294 | AH13: 0.020578685 | AI13: 0.012038304 | AJ13: 0.017630791 | AK13: 0.011731733 | AL13: 0.010868005 | AM13: 0.010381865 | AN13: 0.020086181 | AO13: 0.011578422 | AP13: 0.016822124 | AQ13: 0.015193391 | AR13: 0.013405971 | AS13: 0.011720294 | AT13: 0.020578685 | AU13: 0.012038304 | AV13: 0.017630791 | AW13: 0.011731733 | AX13: 0.010868005 | AY13: 0.010381865 | AZ13: 0.020086181 | BA13: 0.011578422 | BB13: 0.016822124 | BC13: 0.014923229 | BD13: 0.013135809 | BE13: 0.011450131 | BF13: 0.020308523 | BG13: 0.011768142 | BH13: 0.017360628 | BI13: 0.011461571 | BJ13: 0.010597842 | BK13: 0.0099505971 | BL13: 0.014815007 | BM13: 0.014058668 | BN13: 0.01572172
A14: FOOD | B14: 0.015933958 | C14: 0.015933958 | D14: 0.015933958 | E14: 0.015933958 | F14: 0.015933958 | G14: 0.015933958 | H14: 0.015933958 | I14: 0.015933958 | J14: 0.015933958 | K14: 0.015933958 | L14: 0.015933958 | M14: 0.00668352 | N14: 0.017726307 | O14: 0.015639378 | P14: 0.021861945 | Q14: 0.0092664721 | R14: 0.011832289 | S14: 0.011147491 | T14: 0.0094113399 | U14: 0.0094113399 | V14: 0 | W14: 0 | X14: 0.0085910628 | Y14: 0 | Z14: 0.0058652786 | AA14: 0.015504885 | AB14: 0.013821802 | AC14: 0.01211007 | AD14: 0.01211007 | AE14: 0.011899147 | AF14: 0.010793042 | AG14: 0.0082583677 | AH14: 0.010104784 | AI14: 0.0072619106 | AJ14: 0.013098562 | AK14: 0.013647881 | AL14: 0.013474901 | AM14: 0.016495911 | AN14: 0.014573458 | AO14: 0.012861726 | AP14: 0.01259528 | AQ14: 0.011899147 | AR14: 0.010793042 | AS14: 0.0082583677 | AT14: 0.010104784 | AU14: 0.0072619106 | AV14: 0.013098562 | AW14: 0.013647881 | AX14: 0.013474901 | AY14: 0.016495911 | AZ14: 0.014573458 | BA14: 0.012861726 | BB14: 0.01259528 | BC14: 0.01278714 | BD14: 0.011681035 | BE14: 0.0091463605 | BF14: 0.010992777 | BG14: 0.0081499035 | BH14: 0.013986555 | BI14: 0.014535874 | BJ14: 0.014362894 | BK14: 0.018563835 | BL14: 0.021769449 | BM14: 0.014696066 | BN14: 0.015704911
... A18: SERVICE | B18: 0.0023011471 | C18: 0.0023011471 | D18: 0.0023011471 | E18: 0.0023011471 | F18: 0.0023011471 | G18: 0.0023011471 | H18: 0.0023011471 | I18: 0.0023011471 | J18: 0.0023011471 | K18: 0.0023011471 | L18: 0.0023011471 | M18: 0.0021989447 | N18: 0.0062364695 | O18: 0.0023408584 | P18: 0.0023230815 | Q18: 0.0017946094 | R18: 0.0022053877 | S18: 0.0011725796 | T18: 0.00093679814 | U18: 0.00093679814 | V18: 0.00094966862 | W18: 0.00094966862 | X18: 0.00095454685 | Y18: 0.00091801018 | Z18: 0.001634396 | AA18: 0.0033499388 | AB18: 0.0016400166 | AC18: 0.0015527394 | AD18: 0.0015527394 | AE18: 0.0010798791 | AF18: 0.00082637101 | AG18: 0.0009317416 | AH18: 0.00079096257 | AI18: 0.0012916343 | AJ18: 0.00081453623 | AK18: 0.0019955723 | AL18: 0.0011352697 | AM18: 0.0024561647 | AN18: 0.0015473161 | AO18: 0.0014600389 | AP18: 0.001077474 | AQ18: 0.0010798791 | AR18: 0.00082637101 | AS18: 0.0009317416 | AT18: 0.00079096257 | AU18: 0.0012916343 | AV18: 0.00081453623 | AW18: 0.0019955723 | AX18: 0.0011352697 | AY18: 0.0024561647 | AZ18: 0.0015473161 | BA18: 0.0014600389 | BB18: 0.001077474 | BC18: 0.0010696861 | BD18: 0.00081617796 | BE18: 0.00092154855 | BF18: 0.00078076951 | BG18: 0.0012814413 | BH18: 0.00080434317 | BI18: 0.0019853793 | BJ18: 0.0011250767 | BK18: 0.0019984875 | BL18: 0.0012568418 | BM18: 0.001687771 | BN18: 0.0014348046
B21: 13730 | C21: =C2-C8 -> 0.98866645 | D21: =D2-D4 -> 0.92247956 | E21: =E2-E8 -> 0.97411856 | F21: =F2-F4 -> 0.91791856 | G21: =G2-G4 -> 0.85302095 | H21: =H2-H4 -> 0.82912492 | I21: =I2-I4 -> 0.82912492 | J21: =J2-J4 -> 0.85661492 | K21: =K2-K4 -> 0.81673492 | L21: =L2-L4 -> 0.72956369 | M21: =M2-M4 -> 0.65019383 | ... Z21: =Z2-Z4 -> 0.59431761 | AA21: =AA2-AA5 -> 0.74289633 | AB21: =AB2-AB4 -> 0.79986943 | AC21: =AC2-AC4 -> 0.72355856 | AD21: =AD2-AD8 -> 0.90513365 | AE21: =AE2-AE5 -> 0.82723504 | AF21: =AF2-AF5 -> 0.84800398 | AG21: =AG2-AG10 -> 0.97640298 | AH21: =AH2-AH6 -> 0.9089824 | AI21: =AI2-AI4 -> 0.67665219 | AJ21: =AJ2-AJ4 -> 0.61777402 | AK21: =AK2-AK4 -> 0.67958985 | AL21: =AL2-AL4 -> 0.69141696 | AM21: =AM2-AM4 -> 0.77592033 | AN21: =AN2-AN4 -> 0.78762262 | AO21: =AO2-AO4 -> 0.80055436 | AP21: =AP2-AP4 -> 0.80520201 | ... BN21: =BN2-BN4 -> 0.63763485
A22: 4100 | B22: =A22/B21 -> 0.29861617 | C22: 1 | D22: 1 | E22: 1 | F22: 1 | G22: 1 | H22: 1 | I22: 1 | J22: 1 | K22: 1 | L22: 1 | M22: 1 | N22: 1 | O22: 1 | P22: 1 | Q22: 1 | R22: 1 | S22: 1 | T22: 1 | U22: 1 | V22: 1 | W22: 1 | X22: 1 | Y22: 1 | Z22: 1 | AA22: 1 | AB22: 1 | AC22: 1 | AD22: 1 | AE22: 1 | AF22: 1 | AG22: 1 | AH22: 1 | AI22: 1 | AJ22: 1 | AK22: 1 | AL22: 1 | AM22: 1 | AN22: 1 | AO22: 1 | AP22: 1 | AQ22: 1 | AR22: 1 | AS22: 1 | AT22: 1 | AU22: 1 | AV22: 1 | AW22: 1 | AX22: 1 | AY22: 1 | AZ22: 1 | BA22: 1 | BB22: 1 | BC22: 1 | BD22: 1 | BE22: 1 | BF22: 1 | BG22: 1 | BH22: 1 | BI22: 1 | BJ22: 1 | BK22: 1 | BL22: 1 | BM22: 1 | BN22: 1
C23: =C22-C21 -> 0.011333547 | D23: =D22-D21 -> 0.077520435 | E23: =E22-E21 -> 0.025881442 | F23: =F22-F21 -> 0.082081442 | G23: =G22-G21 -> 0.14697905 | H23: =H22-H21 -> 0.17087508 | I23: =I22-I21 -> 0.17087508 | J23: =J22-J21 -> 0.14338508 | ... BN23: =BN22-BN21 -> 0.36236515
BL29: =+BE32 -> 0

Sheet Budget_Grid
A1: Trans_type | B1: B_Fin_Type | C1: 43678 | D1: 43709 | E1: 43739 | F1: 43770 | G1: 43800 | H1: 43831 | I1: 43862 | J1: 43891 | K1: 43922 | L1: 43952 | M1: 43983 | N1: 44013 | O1: 44044 | P1: 44075 | Q1: 44105 | R1: 44136 | S1: 44166 | T1: 44197 | U1: 44228 | V1: 44256 | W1: 44287 | X1: 44317 | Y1: 44348 | Z1: 44378 | AA1: 44409 | AB1: 44440 | AC1: 44470 | AD1: 44501 | AE1: 44531 | AF1: 44562 | AG1: 44593 | AH1: 44621 | AI1: 44652 | AJ1: 44682 | AK1: 44713 | AL1: 44743 | AM1: 44774 | AN1: 44805 | AO1: 44835 | AP1: 44866 | AQ1: 44896 | AR1: 44927 | AS1: 44958 | AT1: 44986 | AU1: 45017 | AV1: 45047 | AW1: 45078 | AX1: 45108 | AY1: 45139 | AZ1: 45170 | BA1: 45200 | BB1: 45231 | BC1: 45261 | BD1: 45292 | BE1: 45323 | BF1: 45352 | BG1: 45383 | BH1: 45413 | BI1: 45444 | BJ1: 45474 | BK1: 45505 | BL1: 45536 | BM1: 45566 | BN1: 45597 | BO1: 45627
A2: SALARY | B2: CREDIT | C2: 13730 | D2: 13730 | E2: 13730 | F2: 13730 | G2: 13730 | H2: 13730 | I2: 13730 | J2: 13730 | K2: 13730 | L2: 13730 | M2: 14425 | N2: 14425 | O2: 12360 | P2: 12360 | Q2: 12360 | R2: 12360 | S2: 12360 | T2: 12360 | U2: 12360 | V2: 20400 | W2: 18639 | X2: 18639 | Y2: 18639 | Z2: 18639 | AA2: 18639 | AB2: 18639 | AC2: 18639 | AD2: 18639 | AE2: 20837 | AF2: 20640 | AG2: 20640 | AH2: 20640 | AI2: 20640 | AJ2: 20640 | AK2: 21974 | AL2: 21974 | AM2: 21974 | AN2: 21974 | AO2: 21974 | AP2: 21974 | AQ2: 21974 | AR2: 21974 | AS2: 21974 | AT2: 21974 | AU2: 21974 | AV2: 21974 | AW2: 21974 | AX2: 21974 | AY2: 21974 | AZ2: 29472 | BA2: 29472 | BB2: 29472 | BC2: 29472 | BD2: 29472 | BE2: 29472 | BF2: 29472 | BG2: 29472 | BH2: 29472 | BI2: 29472 | BJ2: 29472 | BK2: 29472 | BL2: 29472 | BM2: 29472 | BN2: 29472 | BO2: 29472
A3: RENT | B3: DEBIT | C3: =C$2*'%BUDGET'!B3 -> 3999.549 | D3: =D$2*'%BUDGET'!C3 -> 6499.782 | E3: =E$2*'%BUDGET'!D3 -> 4849.436 | F3: =F$2*'%BUDGET'!E3 -> 4849.436 | G3: =G$2*'%BUDGET'!F3 -> 4849.436 | H3: =H$2*'%BUDGET'!G3 -> 4849.436 | I3: =I$2*'%BUDGET'!H3 -> 4849.436 | J3: =J$2*'%BUDGET'!I3 -> 4849.436 | ... BO3: =BO$2*'%BUDGET'!BN3 -> 5500
A4: SAVING | B4: DEBIT | C4: =C$2*'%BUDGET'!B4 -> 2066.365 | D4: =D$2*'%BUDGET'!C4 -> 1149.7362 | E4: =E$2*'%BUDGET'!D4 -> 1064.075 | F4: =F$2*'%BUDGET'!E4 -> 1484.213 | G4: =G$2*'%BUDGET'!F4 -> 1127.233 | H4: =H$2*'%BUDGET'!G4 -> 2018.31 | I4: =I$2*'%BUDGET'!H4 -> 2346.457 | J4: =J$2*'%BUDGET'!I4 -> 2346.457 | ... BO4: =BO$2*'%BUDGET'!BN4 -> 10679.626
A5: TRANSFER | B5: DEBIT | C5: =C$2*'%BUDGET'!B5 -> 2746 | D5: =D$2*'%BUDGET'!C5 -> 1781.9416 | E5: =E$2*'%BUDGET'!D5 -> 1781.9416 | F5: =F$2*'%BUDGET'!E5 -> 1781.9416 | G5: =G$2*'%BUDGET'!F5 -> 1781.9416 | H5: =H$2*'%BUDGET'!G5 -> 1781.9416 | I5: =I$2*'%BUDGET'!H5 -> 1781.9416 | J5: =J$2*'%BUDGET'!I5 -> 1781.9416 | ... BO5: =BO$2*'%BUDGET'!BN5 -> 4339.1041
A6: WITHDRAW | B6: DEBIT | C6: =C$2*'%BUDGET'!B6 -> 1228.7805 | D6: =D$2*'%BUDGET'!C6 -> 1228.7805 | E6: =E$2*'%BUDGET'!D6 -> 1228.7805 | F6: =F$2*'%BUDGET'!E6 -> 1228.7805 | G6: =G$2*'%BUDGET'!F6 -> 1228.7805 | H6: =H$2*'%BUDGET'!G6 -> 1228.7805 | I6: =I$2*'%BUDGET'!H6 -> 900.688 | J6: =J$2*'%BUDGET'!I6 -> 900.688 | ... BO6: =BO$2*'%BUDGET'!BN6 -> 1263.9348
A7: GROCERY | B7: DEBIT | C7: =C$2*'%BUDGET'!B7 -> 713.48891 | D7: =D$2*'%BUDGET'!C7 -> 713.48891 | E7: =E$2*'%BUDGET'!D7 -> 713.48891 | F7: =F$2*'%BUDGET'!E7 -> 713.48891 | G7: =G$2*'%BUDGET'!F7 -> 713.48891 | H7: =H$2*'%BUDGET'!G7 -> 713.48891 | I7: =I$2*'%BUDGET'!H7 -> 713.48891 | J7: =J$2*'%BUDGET'!I7 -> 713.48891 | ... BO7: =BO$2*'%BUDGET'!BN7 -> 2427.2053
A8: GOLD | B8: DEBIT | C8: =C$2*'%BUDGET'!B8 -> 775.20962 | D8: =D$2*'%BUDGET'!C8 -> 155.149 | E8: =E$2*'%BUDGET'!D8 -> 775.20962 | F8: =F$2*'%BUDGET'!E8 -> 355.607 | G8: =G$2*'%BUDGET'!F8 -> 712.587 | H8: =H$2*'%BUDGET'!G8 -> 775.20962 | I8: =I$2*'%BUDGET'!H8 -> 775.20962 | J8: =J$2*'%BUDGET'!I8 -> 775.20962 | ... BO8: =BO$2*'%BUDGET'!BN8 -> 0
A9: EDUCATION | B9: DEBIT | C9: =C$2*'%BUDGET'!B9 -> 0 | D9: =D$2*'%BUDGET'!C9 -> 0 | E9: =E$2*'%BUDGET'!D9 -> 420.0007 | F9: =F$2*'%BUDGET'!E9 -> 420.0007 | G9: =G$2*'%BUDGET'!F9 -> 420.0007 | H9: =H$2*'%BUDGET'!G9 -> 420.0007 | I9: =I$2*'%BUDGET'!H9 -> 420.0007 | J9: =J$2*'%BUDGET'!I9 -> 420.0007 | ... BO9: =BO$2*'%BUDGET'!BN9 -> 264.69687
A10: TRAVEL | B10: DEBIT | C10: =C$2*'%BUDGET'!B10 -> 335.57925 | D10: =D$2*'%BUDGET'!C10 -> 335.57925 | E10: =E$2*'%BUDGET'!D10 -> 335.57925 | F10: =F$2*'%BUDGET'!E10 -> 335.57925 | G10: =G$2*'%BUDGET'!F10 -> 335.57925 | H10: =H$2*'%BUDGET'!G10 -> 335.57925 | I10: =I$2*'%BUDGET'!H10 -> 335.57925 | J10: =J$2*'%BUDGET'!I10 -> 335.57925 | ... BO10: =BO$2*'%BUDGET'!BN10 -> 1127.0686
A11: SHOPPING | B11: DEBIT | C11: =C$2*'%BUDGET'!B11 -> 366.19097 | D11: =D$2*'%BUDGET'!C11 -> 366.19097 | E11: =E$2*'%BUDGET'!D11 -> 366.19097 | F11: =F$2*'%BUDGET'!E11 -> 366.19097 | G11: =G$2*'%BUDGET'!F11 -> 366.19097 | H11: =H$2*'%BUDGET'!G11 -> 366.19097 | I11: =I$2*'%BUDGET'!H11 -> 366.19097 | J11: =J$2*'%BUDGET'!I11 -> 366.19097 | ... BO11: =BO$2*'%BUDGET'!BN11 -> 649.30072
A12: TRANSPORT | B12: DEBIT | C12: =C$2*'%BUDGET'!B12 -> 676.87412 | D12: =D$2*'%BUDGET'!C12 -> 676.87412 | E12: =E$2*'%BUDGET'!D12 -> 1373 | F12: =F$2*'%BUDGET'!E12 -> 1373 | G12: =G$2*'%BUDGET'!F12 -> 1373 | H12: =H$2*'%BUDGET'!G12 -> 676.87412 | I12: =I$2*'%BUDGET'!H12 -> 676.87412 | J12: =J$2*'%BUDGET'!I12 -> 676.87412 | ... BO12: =BO$2*'%BUDGET'!BN12 -> 2011.2565
A13: TELECOM | B13: DEBIT | C13: =C$2*'%BUDGET'!B13 -> 217.96267 | D13: =D$2*'%BUDGET'!C13 -> 217.96267 | E13: =E$2*'%BUDGET'!D13 -> 217.96267 | F13: =F$2*'%BUDGET'!E13 -> 217.96267 | G13: =G$2*'%BUDGET'!F13 -> 217.96267 | H13: =H$2*'%BUDGET'!G13 -> 217.96267 | I13: =I$2*'%BUDGET'!H13 -> 217.96267 | J13: =J$2*'%BUDGET'!I13 -> 217.96267 | ... BO13: =BO$2*'%BUDGET'!BN13 -> 463.35054
A14: FOOD | B14: DEBIT | C14: =C$2*'%BUDGET'!B14 -> 218.77324 | D14: =D$2*'%BUDGET'!C14 -> 218.77324 | E14: =E$2*'%BUDGET'!D14 -> 218.77324 | F14: =F$2*'%BUDGET'!E14 -> 218.77324 | G14: =G$2*'%BUDGET'!F14 -> 218.77324 | H14: =H$2*'%BUDGET'!G14 -> 218.77324 | I14: =I$2*'%BUDGET'!H14 -> 218.77324 | J14: =J$2*'%BUDGET'!I14 -> 218.77324 | ... BO14: =BO$2*'%BUDGET'!BN14 -> 462.85513
... A18: SERVICE | B18: DEBIT | C18: =C$2*'%BUDGET'!B18 -> 31.59475 | D18: =D$2*'%BUDGET'!C18 -> 31.59475 | E18: =E$2*'%BUDGET'!D18 -> 31.59475 | F18: =F$2*'%BUDGET'!E18 -> 31.59475 | G18: =G$2*'%BUDGET'!F18 -> 31.59475 | H18: =H$2*'%BUDGET'!G18 -> 31.59475 | I18: =I$2*'%BUDGET'!H18 -> 31.59475 | J18: =J$2*'%BUDGET'!I18 -> 31.59475 | ... BO18: =BO$2*'%BUDGET'!BN18 -> 42.28656

Sheet FIN_Year
A1: Sr No | B1: Fin_Year | C1: B_Month_Year | D1: B_Month_Num
A2: 1 | B2: 2019-20 | C2: 43556 | D2: 43556
A3: 2 | B3: 2019-20 | C3: 43586 | D3: 43586
A4: 3 | B4: 2019-20 | C4: 43617 | D4: 43617
A5: 4 | B5: 2019-20 | C5: 43647 | D5: 43647
A6: 5 | B6: 2019-20 | C6: 43678 | D6: 43678
A7: 6 | B7: 2019-20 | C7: 43709 | D7: 43709
A8: 7 | B8: 2019-20 | C8: 43739 | D8: 43739
A9: 8 | B9: 2019-20 | C9: 43770 | D9: 43770
A10: 9 | B10: 2019-20 | C10: 43800 | D10: 43800
A11: 10 | B11: 2019-20 | C11: 43831 | D11: 43831
A12: 11 | B12: 2019-20 | C12: 43862 | D12: 43862
A13: 12 | B13: 2019-20 | C13: 43891 | D13: 43891
... A73: 72 | B73: 2024-25 | C73: 45717 | D73: 45717

Sheet Gold_Qual
A1: Fineness_From | B1: Fineness_Till | C1: Carat | D1: Gold_Content_From_% | E1: Gold_Content_Till_%
A2: 333 | B2: =A3-1 -> 374 | C2: 8 | D2: 33.3 | E2: =B2%*10 -> 37.4
A3: 375 | B3: =A4-1 -> 416 | C3: 9 | D3: =A3/10 -> 37.5 | E3: =B3%*10 -> 41.6
A4: 417 | B4: =A5-1 -> 584 | C4: 10 | D4: =A4/10 -> 41.7 | E4: =B4%*10 -> 58.4
A5: 585 | B5: =A6-1 -> 619 | C5: 14 | D5: =A5/10 -> 58.5 | E5: =B5%*10 -> 61.9
A6: 620 | B6: =A7-1 -> 749 | C6: 14.8 | D6: =A6/10 -> 62 | E6: =B6%*10 -> 74.9
A7: 750 | B7: =A8-1 -> 799 | C7: 18 | D7: =A7/10 -> 75 | E7: =B7%*10 -> 79.9
A8: 800 | B8: =A9-1 -> 874 | C8: 19.2 | D8: =A8/10 -> 80 | E8: =B8%*10 -> 87.4
A9: 875 | B9: =A10-1 -> 915 | C9: 21 | D9: =A9/10 -> 87.5 | E9: =B9%*10 -> 91.5
A10: 916 | B10: =A11-1 -> 989 | C10: 22 | D10: =A10/10 -> 91.6 | E10: =B10%*10 -> 98.9
A11: 990 | B11: =A12-1 -> 998 | C11: 24 | D11: =A11/10 -> 99 | E11: =B11%*10 -> 99.8
A12: 999 | B12: 1000 | C12: 24 | D12: =A12/10 -> 99.9 | E12: =B12%*10 -> 100
